Workbook
Name _________C: '[1]B S'!#REF!
Name _________C: '[1]B S'!#REF!
Name _________C: '[1]B S'!#REF!
Name _________C: '[1]B S'!#REF!
Name _________ESC1: #REF!
Name _________ESC1: #REF!
Name _________ESC1: #REF!
Name _________ESC1: #REF!
Name _________TB1: [2]LIST!$C$123:$P$132
Name ________C: '[1]B S'!#REF!
Name ________C: '[1]B S'!#REF!
Name ________C: '[1]B S'!#REF!
Name ________C: '[1]B S'!#REF!
Name ________ESC1: #REF!
Name ________ESC1: #REF!
Name ________ESC1: #REF!
Name ________ESC1: #REF!
Name ________TB1: [2]LIST!$C$123:$P$132
Name _______C: '[1]B S'!#REF!
Name _______C: '[1]B S'!#REF!
Name _______C: '[1]B S'!#REF!
Name _______C: '[1]B S'!#REF!
Name _______ESC1: #REF!
Name _______ESC1: #REF!
Name _______ESC1: #REF!
Name _______ESC1: #REF!
Name _______TB1: [2]LIST!$C$123:$P$132
Name ______C: '[1]B S'!#REF!
Name ______C: '[1]B S'!#REF!
Name ______C: '[1]B S'!#REF!
Name ______C: '[1]B S'!#REF!
Name ______ESC1: #REF!
Name ______ESC1: #REF!
Name ______ESC1: #REF!
Name ______ESC1: #REF!
Name ______TB1: [2]LIST!$C$123:$P$132
Name _____C: '[1]B S'!#REF!
Name _____C: '[1]B S'!#REF!
Name _____C: '[1]B S'!#REF!
Name _____C: '[1]B S'!#REF!
Name _____ESC1: #REF!
Name _____ESC1: #REF!
Name _____ESC1: #REF!
Name _____ESC1: #REF!
Name _____TB1: [2]LIST!$C$123:$P$132
Name ____C: '[1]B S'!#REF!
Name ____C: '[1]B S'!#REF!
Name ____C: '[1]B S'!#REF!
Name ____C: '[1]B S'!#REF!
Name ____ESC1: #REF!
Name ____ESC1: #REF!
Name ____ESC1: #REF!
Name ____ESC1: #REF!
Name ____TB1: [2]LIST!$C$123:$P$132
Name ___C: '[1]B S'!#REF!
Name ___C: '[1]B S'!#REF!
Name ___C: '[1]B S'!#REF!
Name ___C: '[1]B S'!#REF!
Name ___ESC1: #REF!
Name ___ESC1: #REF!

Sheet Analysis 20-21
A1: Overall Variance analysis
A3: Particulars | B3: 2019-20 | D3: 2020-21 | F3: Variance | G3: Percentage change over previous year
B4: Actual | C4: Percentage on sales | D4: Actual | E4: Percentage on sales
A5: Revenue:
A6: Sales | B6: 3.2895775e+08 | D6: 2.587758e+08 | F6: =D6-B6 -> -70181952 | G6: =F6/B6 -> -0.2133464
A7: other Income | B7: 10903544 | D7: 5691621 | F7: =D7-B7 -> -5211923 | G7: =F7/B7 -> -0.47800266
F8: =F6+F7 -> -75393875
A9: Expenses
A10: Construction and operating
A11: Construction Material Consumed | B11: 69930964 | C11: =B11/B6 -> 0.21258342 | D11: 81386421 | E11: =D11/D6 -> 0.31450554 | F11: =B11-D11 -> -11455457 | G11: =E11-C11 -> 0.10192212
A12: Wages paid | B12: 102541739 | C12: =B12/B6 -> 0.31171705 | D12: 95817327 | E12: =D12/D6 -> 0.37027159 | F12: =B12-D12 -> 6724412.3 | G12: =E12-C12 -> 0.058554544
A13: Construction Work Expenses | B13: 41641425 | C13: =B13/B6 -> 0.12658594 | D13: 32380431 | E13: =D13/D6 -> 0.12512929 | F13: =B13-D13 -> 9260993.7 | G13: =E13-C13 -> -0.0014566492
A14: EMPLOYEE BENEFITS EXPENSE | F14: =B14-D14 -> 0 | G14: =E14-C14 -> 0
A15: Salaries and wages | B15: 29509489 | C15: =B15/B6 -> 0.089706016 | D15: 27106724 | E15: =D15/D6 -> 0.10474984 | F15: =B15-D15 -> 2402765 | G15: =E15-C15 -> 0.015043827
A16: Contribution to PF and other funds | B16: 4628619 | C16: =B16/B6 -> 0.014070558 | D16: 4023696 | F16: =B16-D16 -> 604923 | G16: =E16-C16 -> -0.014070558
A17: Director’s Remuneration | B17: 3780000 | C17: =B17/ B6 -> 0.011490837 | D17: 3677400 | E17: =D17/D6 -> 0.014210757 | F17: =B17-D17 -> 102600 | G17: =E17-C17 -> 0.0027199197
A18: Staff welfare expenses | B18: 289262 | C18: =B18/B6 -> 0.00087932873 | D18: 59275 | E18: =D18/D6 -> 0.00022905929 | F18: =B18-D18 -> 229987 | G18: =E18-C18 -> -0.00065026944
A19: Administrative and other expenses | B19: 18130831 | C19: =B19/B6 -> 0.055115986 | D19: 16158934 | E19: =D19/D6 -> 0.06244376 | F19: =B19-D19 -> 1971897 | G19: =E19-C19 -> 0.0073277736
A20: Change in inventory | B20: 11025000 | C20: =B20/B6 -> 0.033514942 | D20: -18800000 | E20: =D20/D6 -> -0.072649762 | F20: =B20-D20 -> 29825000 | G20: =E20-C20 -> -0.1061647
A21: CSR Fund | B21: 2860000 | C21: =B21/B6 -> 0.0086941257 | D21: 873749.9 | F21: =B21-D21 -> 1986250.1 | G21: =E21-C21 -> -0.0086941257
A22: Depreciation | B22: 3467812 | C22: =B22/B6 -> 0.010541816 | D22: 3900665.2 | E22: =D22/D6 -> 0.015073532 | F22: =B22-D22 -> -432853.2 | G22: =E22-C22 -> 0.004531716
F23: =SUM(F11:F22) -> 41220518
A24: Profit 2019-20 | B24: 52056151 | C24: =B24/B6 -> 0.15824571
A25: Profit 2020-21 | B25: 18639394 | C25: =B25/D6 -> 0.072029126
A27: Decrease in Profit | B27: =B25-B24 -> -33416757
A30: Efficiency variance
A32: Particulars | B32: Percentage on Sales on 2019-20 | C32: Expected | D32: Actual | E32: Variance from Expected
A35: Sales for the period 2020 to 2021 | B35: =D6 -> 2.587758e+08 | D35: =B35 -> 2.587758e+08
A37: CONSTRUCTION AND OPERATING
A38: Construction Material Consumed | B38: =C11 -> 0.21258342 | C38: =$D$35*B38 -> 55011445 | D38: =D11 -> 81386421 | E38: =C38-D38 -> -26374977
A39: Wages paid | B39: =C12 -> 0.31171705 | C39: =$D$35*B39 -> 80664828 | D39: =D12 -> 95817327 | E39: =C39-D39 -> -15152499
A40: Construction Work Expenses | B40: =C13 -> 0.12658594 | C40: =$D$35*B40 -> 32757377 | D40: =D13 -> 32380431 | E40: =C40-D40 -> 376945.55
A41: EMPLOYEE BENEFITS EXPENSE | B41: =C14 -> 0 | D41: =D14 -> 0
A42: Salaries and wages | B42: =C15 -> 0.089706016 | C42: =$D$35*B42 -> 23213746 | D42: =D15 -> 27106724 | E42: =C42-D42 -> -3892978.3
A43: Contribution to Provident and other funds | B43: =C16 -> 0.014070558 | C43: =$D$35*B43 -> 3641119.8 | D43: =D16 -> 4023696 | E43: =C43-D43 -> -382576.21
A44: Director’s Remuneration | B44: =C17 -> 0.011490837 | C44: =$D$35*B44 -> 2973550.6 | D44: =D17 -> 3677400 | E44: =C44-D44 -> -703849.4
A45: Staff welfare expenses | B45: =C18 -> 0.00087932873 | C45: =$D$35*B45 -> 227548.99 | D45: =D18 -> 59275 | E45: =C45-D45 -> 168273.99
A46: Administrative and other expenses | B46: =C19 -> 0.055115986 | C46: =$D$35*B46 -> 14262683 | D46: =D19 -> 16158934 | E46: =C46-D46 -> -1896250.4
A47: Change in inventory | B47: =C20 -> 0.033514942 | C47: =$D$35*B47 -> 8672855.9 | D47: =D20 -> -18800000 | E47: =C47-D47 -> 27472856
A48: CSR Fund | B48: =C21 -> 0.0086941257 | C48: =$D$35*B48 -> 2249829.3 | D48: 873749.9 | E48: =C48-D48 -> 1376079.4
A49: Depreciation | B49: =C22 -> 0.010541816 | C49: =B35*B49 -> 2727966.8 | D49: =D22 -> 3900665.2 | E49: =C49-D49 -> -1172698.4
C50: =SUM(C38:C49) -> 2.2640295e+08 | D50: =SUM(D38:D49) -> 2.4658462e+08 | E50: =SUM(E38:E49) -> -20181673
A52: If the expenses were within the budget then the profit would have been(without considering CSR)
A54: Total Actual Income | C54: =D6-D7 -> 2.5308418e+08
A55: Budgeted Expense | C55: =C50-C48 -> 2.2415312e+08
B56: Expected profit | C56: =C54-C55 -> 28931055
B57: Actual profit | C57: =B65 -> 46240223
B58: Difference | C58: =C56-C57 -> -17309168
A61: Income Statement
A63: Particulars | B63: 2020-21 | C63: 2019-20
A65: Earning before Tax | B65: =+PL!C35 -> 46240223 | C65: 52056151
A66: Less: Tax Expenses | B66: =+IT!E46 -> 10965295 | C66: 11161938
A67: Earning after Tax | B67: =B65-B66 -> 35274928 | C67: =C65-C66 -> 40894214
A68: Add: Depreciation | B68: 3900665.2 | C68: 3467812
A69: Profit before depreciation and Tax | B69: =B67+B68 -> 39175593 | C69: =C67+C68 -> 44362026
A72: Tax Payable calculation
B74: 2020-21
A75: Particulars | B75: Considering Depreciation | C75: Without considering depreciation
A78: Total Taxable Income | B78: =+IT!E40 -> 43568400 | C78: =+IT!E40+IT!D28-IT!D16 -> 47168607
A79: Tax @ 22% | B79: =B78*22% -> 9585048.1 | C79: =C78*22% -> 10377094
A80: Add: Surcharge @ 10% | B80: =ROUND(+B79*10%,0.1) -> 958505 | C80: =C79*10/100 -> 1037709.4
B81: =B79+B80 -> 10543553 | C81: =C79+C80 -> 11414803
A82: Add: Cess @ 4% | B82: =ROUND(+B81*4%,-1) -> 421740 | C82: =C81*4/100 -> 456592.12
A84: Tax Payable | B84: =B81+B82 -> 10965293 | C84: =C81+C82 -> 11871395
A86: Disclaimer: Computing Total income without considering depreciation is not possible under Income Tax Act. The computation made for personal analysing purpose only.

Sheet WIP
A1: SATHIAPAL ENGINEERS (INDIA) LIMITED
A2: 14, Temple St., Alagappa Nagar,
A3: Kilpauk,
A4: Chennai - 600 010
A5: CIN: U74210TN2002PLC048568
A6: Cost Breakup of Ledger
A7: 1-Apr-2020 to 31-Mar-2021 | G7: WIP
B8: Ledger: Contract Receipts A/c
B9: SATHIAPAL ENGINEERS (INDIA) LIMITED - (From 1-Apr-2007) - (from 1-Apr-2012)
A10: Particulars | B10: 1-Apr-2020 to 31-Mar-2021
B11: Transactions | D11: Closing | E11: Closing in Tally | G11: contracts
B12: Debit | C12: Credit | D12: Balance | G12: purchase
A13: Primary Cost Category | G13: direct expense
A14: 21 Sugar Project | B14: 999 | C14: 0 | D14: =C14-B14 -> -999 | E14: 2288440 | G14: indirect expense
A15: CCCL.Dhachepalli Project | B15: 1306369 | C15: 2887464 | D15: =C15-B15 -> 1581095
A16: CCCL-Vizag Project | B16: 20402422 | C16: 38346998 | D16: =C16-B16 -> 17944576
A17: Coromandal Engg Co Ltd (RMC) | B17: 3540 | C17: 4278200 | D17: =C17-B17 -> 4274660
A18: Coromandal (Ramco Ariyalur) Project | B18: 1981824 | C18: 3457145 | D18: =C18-B18 -> 1475321
A19: Coromandal (Ramco) Project | B19: 63946 | C19: 669816 | D19: =C19-B19 -> 605870 | I19: fd | J19: 1084824
A20: Dalmia Cement 2020 Project | B20: 7612028 | C20: 6972946 | D20: =C20-B20 -> -639082 | J20: 638212
A21: EID Parry Karnataka Project | B21: 9309785 | C21: 9194400 | D21: =C21-B21 -> -115385 | J21: 3797980 | K21: 3856336
A22: Gujarat Ambuja Himatnagar Project | B22: 1811569 | C22: 2100000 | D22: =C22-B22 -> 288431 | J22: =J19+J20+J21 -> 5521016 | K22: =J19+J20+K21 -> 5579372
A23: Hotel Sadhabishgam Project | C23: 127118 | D23: 127118
A24: ITC Bhadrachalam Telangana 2019 Project | B24: 31197721 | C24: 30302188 | D24: =C24-B24 -> -895533
A25: KEC Project (Chimney) Jharkhand | B25: 10079786 | C25: 10460923 | D25: =C25-B25 -> 381137 | J25: =K22-J22 -> 58356
A26: Mela Gurumuhurtham Project | B26: 240000 | C26: 6000000 | D26: =C26-B26 -> 5760000
A27: MRN Cane Power II Project - Karnataka | B27: 2779311 | C27: 1452882 | D27: =C27-B27 -> -1326429 | G27: =D24+D27+D28+D34+D35+D37+D39+D20+D21+D14 -> -17581760
A28: Nirma Project | B28: 14377479 | C28: 7828408 | D28: =C28-B28 -> -6549071
A29: Novoco Project | B29: 1595944 | C29: 2658875 | D29: =C29-B29 -> 1062931
A30: Nuvoco Jojobera Cement Jharkhand Project | B30: 8709756 | C30: 11032518 | D30: =C30-B30 -> 2322762
A31: Philips Carban Project | B31: 6005878 | C31: 12209897 | D31: =C31-B31 -> 6204019
A32: Ramco Cement R R Nagar Project | B32: 28153750 | C32: 30465628 | D32: =C32-B32 -> 2311877.9
A33: RSK Kaliyaraj Project | B33: 0.36 | C33: 2966102 | D33: =C33-B33 -> 2966101.6
A34: Rungta Mines (Chaliyama-Jharkhand) Project | B34: 9371874 | C34: 6595887 | D34: =C34-B34 -> -2775987
A35: Rungta Mines (Kamanda-Odisha) Project | B35: 8231261 | C35: 6611838 | D35: =C35-B35 -> -1619423
A36: Sanghi Industries CPP Chimney Project | B36: 34045 | C36: 2142212 | D36: =C36-B36 -> 2108167
A37: Sanghi Industries II Project | B37: 3712881 | C37: 1329081 | D37: =C37-B37 -> -2383800
A38: Satguru Cement Pvt Ltd | B38: 19623428 | C38: 28562740 | D38: =C38-B38 -> 8939312
A39: Sayaji Industries Ltd Project | B39: 4627201 | C39: 3351150 | D39: =C39-B39 -> -1276051
A40: SRR Projects Pvt Ltd Project | C40: 62345 | D40: =C40-B40 -> 62345
A41: Tarun Construction (Wonder Cement) Project | B41: 1156807 | C41: 2288489 | D41: =C41-B41 -> 1131682
A42: TNPL Unit II Project | B42: 14160916 | C42: 14312421 | D42: =C42-B42 -> 151505
A43: TPL Staff Quarters | C43: 600000 | D43: =C43-B43 -> 600000
A44: Z Resurgent (Ismt) Project | C44: 1700000 | D44: =C44-B44 -> 1700000
A45: Z Vilanagar Project | C45: 900000 | D45: 900000

Sheet IT
B2: Assessee's Name | C2: M/s. Sathiapal Engineers (India) Private Limited (Formerly known as M/S Sathiapal Engineers (India) Limited) | D2: Status | E2: Private Limited Company
C3: =BS!A3 -> CIN: U74210TN2002PLC048568
B4: Date of Incorporation | C4: 07.03.2002 | D4: PAN | E4: AAHCS2295P | W4: AMOUNT DUE | Y4: =ROUND(+#REF!,-2) -> #REF!
B5: Nature of Business | C5: Engineering & Construction | D5: I.T.Juri | E5: CO.RANGE VI(1) | T5: DUE DATE | V5: PAID | W5: AMOUNT | Y5: CHARGED
B6: Address: Registered Office: | C6: New No. 57, Old No. 3, Canal Road, | D6: Asst. Year | E6: 2023-24
C7: Kilpauk Garden Colony, Kilpauk, Chennai 600 010. | D7: Year Ending | E7: 31.03.2023 | T7: 15.09.2005 | U7: 0 | V7: 0 | W7: =+#REF!+V7 -> #REF! | X7: =+#REF!-W7 -> #REF! | Y7: =ROUND(X7*1%*3,0) -> #REF!
B9: STATEMENT OF TOTAL INCOME ( in '000s)
B10: INCOME FROM BUSINESS
B11: Net Profit as per Profit & Loss A/c. | E11: =+PL!C35 -> 46240223 | T11: 15.03.2006 | U11: 0 | V11: 0 | W11: =+#REF!+V11 -> #REF! | X11: =+#REF!-W11 -> #REF! | Y11: =ROUND(X11*1%*1,0) -> #REF!
B12: LESS: INCOME CONSIDERED SEPARATELY
B13: Interest Income | D13: =Notes!J235 -> 3323836 | E13: =+Notes!J235 -> 3323836
E14: =E11-E13 -> 42916387
B15: ADD:INADMISSIBLE EXPENSES:
B16: Depreciation as per Companies Act | D16: =Dep_Co!K26 -> 8219826.5
B17: Disallowance U/s 40A(3) | D17: =Disallowance!D14 -> 367821 | G17: 14296407
B18: Disallowance U/s 40(a)(i) | D18: =I18 -> 123600 | G18: =412000 -> 412000 | H18: =G18*30% -> 123600 | I18: =H18 -> 123600
B19: Disallowance U/s 36(1)(va) | D19: 0 | F19: 382438
B20: Disallowance U/s 37(i) | D20: =H23 -> 125012.94 | F20: Penalty | H20: 125382.94
B21: Capital Expenditure | D21: 0
B22: Donation | D22: =261950 -> 261950 | E22: =SUM(D16:D22) -> 9098210.4 | F22: =Notes!J281-100000 -> 161950 | G22: 261950 | H22: =185*2 -> 370
H23: =H20-H22 -> 125012.94
E26: =E14+E22 -> 52014597 | G26: 100000 | W26: Total | Y26: =SUM(Y6:Y16) -> #REF!
B27: LESS: ADMISSIBLE EXPENSES
B28: Depreciation as per Income Tax Act | D28: =Dep_IT!I23 -> 11820033 | E28: =D28 -> 11820033
B29: Donation | D29: =G26*50% -> 50000 | E29: =D29 -> 50000
E30: =E26+E29-E28 -> 40244564
B31: INCOME FROM OTHER SOURCES:
B32: Interest Income | D32: =D13 -> 3323836 | E32: =D32 -> 3323836
B35: GROSS TOTAL INCOME
B36: Income from Business | E36: =E30 -> 40244564
B37: Income from other sources | E37: =E32 -> 3323836
E38: =SUM(E36:E37) -> 43568400
E39: or
C40: TOTAL INCOME (as rounded off) | E40: =E38 -> 43568400
B41: STATEMENT OF TAXES
B42: I . Tax on Total Income @ 22% u/s 115 BAA | E42: =E40*0.22 -> 9585048.1
B43: Add: Surcharge @ 10% on above | E43: =E42*10% -> 958504.81
E44: =E42+E43 -> 10543553
B45: Add: Education cess @ 4% on above | E45: =E44*4% -> 421742.12
E46: =+E44+E45 -> 10965295
B47: Less: Tax Deducted At Source(As per Form 26AS) | E47: =10071025 -> 10071025
E48: =E46-E47 -> 894270.03 | G48: 11126150
B49: Less: Advance Income Tax | E49: =Notes!J210 -> 3800000 | F49: =E47 -> 10071025 | G49: =G48-E49 -> 7326150 | U49: =52*800 -> 41600
E50: =E48-E49 -> -2905730
B51: Add Intrest u/s - 234C | E51: 0
E52: =E50+E51 -> -2905730 | G52: p l ac | H52: 10965295
E53: or | G53: current tax exp | I53: 10965295
B54: Less: Tax paid u/s 140A | E54: 0
B55: Balance Tax Due/ Refund receivable | E55: =E52 -> -2905730
D56: For and on behalf of the Board of Directors
E57: =+BS!F55
C61: (S. KUMARAN) | E61: (K. VISALAKSHI)
C62: Managing Director | E62: Director
B65: =BS!A63 -> Place: Chennai
B66: =BS!A64 -> Date: 07-09-2023
C68: For and on behalf of the Board of Directors
B73: Place : Chennai | C73: (S. KUMARAN) | E73: ( K.VISALAKSHI)
B74: =BS!A64 -> Date: 07-09-2023 | C74: Managing Director | E74: Director
C75: =BS!D63 -> DIN No.01926196 | E75: =BS!E63 -> DIN No.01926144
B97: Interest Calculation
B98: Tax payable | C98: =+E46 -> 10965295
B99: Less:TDS | C99: 0
C100: =+C98-C99 -> 10965295
B101: Less:Advance tax | C101: =SUM(#REF!) -> #REF!
B102: Balance | C102: =C100-C101 -> #REF!
B103: 90% calaculation | C103: =ROUND(C100*90%,0) -> 9868766
B105: Interest u/s 234B
B106: Amount | C106: No of month | D106: Rate of Interest | E106: Interest
B107: =IF(C101<C103,C102,0) -> #REF! | C107: 7 | D107: 0.01 | E107: =ROUND(B107*C107*D107,0) -> #REF!
B109: Interest u/s 234B
B110: Due date | C110: Instalment | D110: Instalment paid | E110: Diff
B111: 42536 | C111: =$C$100*15% -> 1644794.3 | D111: =#REF! -> #REF! | E111: =C111-D111 -> #REF! | F111: No.of month | G111: Rate of inter | H111: Interest | I111: Gap
B112: 42628 | C112: =$C$100*45% -> 4934382.8 | D112: =D111+#REF! -> #REF! | E112: =C112-D112 -> #REF! | F112: 3 | G112: 0.01 | H112: =ROUND(IF(D111<I112,E111*F112*G112,0),0) -> #REF! | I112: =ROUND($C$100*12%,0) -> 1315835
B113: 42719 | C113: =$C$100*75% -> 8223971.3 | D113: =D112+#REF! -> #REF! | E113: =C113-D113 -> #REF! | F113: 3 | G113: 0.01 | H113: =ROUND(IF(D112<I113,E112*F113*G113,0),0) -> #REF! | I113: =ROUND($C$100*36%,0) -> 3947506
B114: 42809 | C114: =$C$100*100% -> 10965295 | D114: =D113+#REF! -> #REF! | E114: =C114-D114 -> #REF! | F114: 3 | G114: 0.01 | H114: =ROUND(IF(D113<I114,E113*F114*G114,0),0) -> #REF! | I114: =ROUND($C$100*75%,0) -> 8223971
B115: Total | F115: 1 | G115: 0.01 | H115: =ROUND(IF(D114<I115,E114*F115*G115,0),0) -> #REF! | I115: =ROUND($C$100*100%,0) -> 10965295
B116: Total | H116: =SUM(H112:H115) -> #REF!
H117: =H116+E107 -> #REF!

Sheet Disallowance
B3: Si.no | C3: Particulars | D3: Amount
B4: 1 | C4: Benz car service | D4: 28633
B5: =B4+1 -> 2 | C5: Marriage Gift to Mr. velappan | D5: 30600
B6: =B5+1 -> 3 | C6: Sillvan Gift | D6: 10490
B7: =B6+1 -> 4 | C7: Angusamy gst notice purpose | E7: 44977 | F7: GST - AMOUNT PAID TO COMMISSIONER
B8: =B7+1 -> 5 | C8: Wagnor Car service | D8: 20157
B9: =B8+1 -> 6 | C9: Skoda car serivce | D9: 61383
B10: =B9+1 -> 7 | C10: Benz car service | D10: 12558
B11: 8 | C11: Audit fees
D12: =SUM(D4:D10) -> 163821
C13: Godown rent | D13: 204000
D14: =D12+D13 -> 367821

Sheet policies old
A2: =+BS!A2 -> M/s. Sathiapal Engineers (India) Private Limited (Formerly known as M/S Sathiapal Engineers (India) Limited)
A3: =+BS!A4 -> New No. 57, Old No. 3, Canal Road, Kilpauk Garden Colony, Kilpauk, Chennai 600 010.
A4: Notes forming part of the financial statements
A6: Ref No. | B6: Note | C6: Particulars
B8: 1 | C8: Corporate information
C9: M/s. Sathiapal Engineers (India) Private Limited formerly known as M/s. Sathiapal Engineers (India) Limitedis registered with the Chennai Registrar of Companies as a Public Limited Company on 07th March 2002 vide Registration no. U74210TN2002PLCO48568
C11: .
C12: The registered office of the company is located at New No.14, Old No.25, Temple Street, Alagappa Nagar, Kilpauk, Chennai - 600 010.
C14: The Principal activities of the Company is to engage in microfinance activities with the ultimate objective of benefiting the poor and downtrodden, (organized in the form of Self Help Groups) for enhancement of their livelihoods in a financially viable manner. The Company generally provides small value collateral free loans upto Rs. 1,00,000 for a tenor of 20 months with monthly repayment.
C15: The Principal activities of the Company is undertaking Specialised Construction of Tall Structures like Silos for Cement Plants, RCC Chimneys for Power, Suger, Paper, Chemical, etc., thro Slip-Form Technology and also Construction of Educational Institutions.
C16: The Company was converted from Public Company to Private company with effect from 10th April 2019 and herein after called as M/s.Sathiapal Engineers (India) Private limited.
A18: AS 1.1 | B18: 2 | C18: Significant accounting policies
A19: i | C19: The significant accounting policies have been predominantly presented below in the order of the Accounting Standards notified under the Companies (Accounting Standards) Rules, 2006 (as amended). The order of presentation may be customised for each Company.
A20: i | C20: The significant accounting policies would need to be customised for each Company based on its applicability and relevance. For example, in case of a Small and Medium Sized Company, it should state in its financial statements that "The Company is a Small and Medium Sized Company as defined in the General Instructions in respect of Accounting Standards notified under the Companies (Accounting Standards) Rules, 2006 (as amended). Accordingly, the Company has complied with the Accounting Standards as applicable to a Small and Medium Sized Company." and should also modify the accounting policies suitably. Similarly, companies that have not opted for the transition provisions in para 46 / 46A of AS 11 The Effects of Changes in Foreign Exchange Rates and companies that have not opted for Hedge Accounting should modify the accounting policies on Foreign Currency Transactions and Translations and Hedge Accounting, respectively.
B21: 2.1 | C21: Basis of accounting and preparation of financial statements
C23: The financial statements of the Company have been prepared in accordance with the Generally Accepted Accounting Principles in India (Indian GAAP). The Company has prepared these financials statements to comply in all material respects with the Accounting Standards notified under the Companies (Accounting Standards) Rules, 2014 (as amended) and the relevant provisions of the Companies Act, 2013. The financial statements have been prepared on accrual basis and the directions issued by the Reserve Bank of India to the extent applicable to the Company.
B25: =B21+0.1 -> 2.2 | C25: Use of estimates
C27: The preparation of the financial statements in conformity with Indian GAAP and that requires the Management to make estimates and assumptions that affect the reported amounts of assets and liabilities and disclosure of contingent assets and liabilities at the date of the financial statements and reported amounts of revenues and expenses during the reporting period. Although such estimates are made on a reasonable and prudent basis taking into account all available information, actual results could differ from those estimates.
A29: AS 2.26.a | B29: =B25+0.1 -> 2.3 | C29: Inventories
C31: Inventories are valued at cost (on FIFO ) and providing for obsolescence and other losses, where considered necessary. Cost of raw materials, Packing materials, Stores, Spares and Consumables includes all charges in bringing the goods to the point of sale, including octroi and other levies, transit insurance and receiving charges.
A34: =$A$2 -> M/s. Sathiapal Engineers (India) Private Limited (Formerly known as M/S Sathiapal Engineers (India) Limited)
A35: =$A$3 -> New No. 57, Old No. 3, Canal Road, Kilpauk Garden Colony, Kilpauk, Chennai 600 010.
A36: =$A$4 -> Notes forming part of the financial statements | B36: Notes forming part of the financial statements
B38: Note 2 Significant accounting policies (contd.)
A40: Ref No. | B40: Note | C40: Particulars
B43: =B29+0.1 -> 2.4 | C43: Cash and cash equivalents (for purposes of Cash Flow Statement)
A45: AS 3.5.2 | C45: Cash comprises cash on hand and demand deposits with banks. Cash equivalents are short-term balances (with an original maturity of three months or less from the date of acquisition), highly liquid investments that are readily convertible into known amounts of cash and which are subject to insignificant risk of changes in value.
B47: =B43+0.1 -> 2.5 | C47: Cash flow statement
C49: Cash flows are prepared in accordance with the indirect method prescribed in Accounting Standard-3.
B51: =B47+0.1 -> 2.6 | C51: Fixed Assets
C53: Fixed assets are stated at cost net of depreciation. The cost of an asset comprises its purchase price and any cost directly attributable for bringing the asset to its working condition and location for its intended use.
B55: =B51+0.1 -> 2.7 | C55: Depreciation
A57: AS 6.29 AS 26.63 AS 26.78 AS 26.90.a AS 26.90.b AS 26.94.a | C57: Depreciable amount for assets is the cost of an asset, or other amount substituted for cost, less its estimated residual value. Depreciation on tangible fixed assets has been provided on Straight Line value method as per the useful life prescribed in Schedule II to the Companies Act, 2013.
C58: Depreciation on additions is charged proportionately from the date of acquisition/installation.
C59: Individual assets costing less than Rs. 5000/- are depreciated in ful, in the year of acquisition.
B70: =B55+0.1 -> 2.8 | C70: Receivables
C72: Receivables under Financing activity include Gold Loans, Mortgage Loans and Business Loans. Loans are classified into 'Performing and Non-Performing' assets in terms of the Non Banking Financial Companies Prudential Norms (Reserve Bank) Directions, 1998 issued by the Reserve Bank of India as amended from time to time.
B74: =B55+0.1 -> 2.8 | C74: Revenue recognition
C76: Revenues from Interest on loans financed by the company is recognized on accrual basis, considering the directions issued by the Reserve Bank of India from time to time in terms of the Non Banking Financial Companies Prudential Norms (Reserve Bank) Directions, 1998. Loans are classified into 'Performing and Non-Performing' assets in terms of the said Directions.
C77: Revenues from loan documentation and meeting charges are recognised as income on cash basis.
C78: Revenue is recognized to the extent that it is probable that the economic benefits will flow to the Company and the revenue can be reliably measured.
C79: Sale of goods
C80: Sales are recognised, net of returns and trade discounts, on transfer of significant risks and rewards of ownership to the buyer, which generally coincides with the delivery of goods to customers. Sales include excise duty but exclude sales tax and value added tax.
C81: Revenue from interest income on Fixed Deposits with Banks is recognized on time proportion basis taking into account the amount outstanding and the rate applicable.
C82: Sale of goods
A83: GN 9.1.3 GN 9.1.4 GN 9.1.5 AS 9.11 | C83: Sales are recognised, net of returns and trade discounts, on transfer of significant risks and rewards of ownership to the buyer, which generally coincides with the delivery of goods to customers. Sales include excise duty but exclude sales tax and value added tax.
A85: AS 7.38.b AS 7.38.c AS 9.12 | C85: Income from services
C86: Revenues from contracts priced on a time and Material & Labour basis are recognised when services are rendered and related costs are incurred. Foreseeable losses on such contracts are recognised when probable.
C87: Interest Income on securitisation is recognized on accrual basis.
C89: Dividend Income is recognized when the right to receive is established.
A92: =$A$2 -> M/s. Sathiapal Engineers (India) Private Limited (Formerly known as M/S Sathiapal Engineers (India) Limited)
A93: =$A$3 -> New No. 57, Old No. 3, Canal Road, Kilpauk Garden Colony, Kilpauk, Chennai 600 010.
A94: =$A$4 -> Notes forming part of the financial statements | B94: Notes forming part of the financial statements
B96: Note 2 Significant accounting policies (contd.)
A98: Ref No. | B98: Note | C98: Particulars
A101: AS 9.13 | B101: =B74+0.1 -> 2.9 | C101: Other income
C103: Interest income on Bank Deposit is accounted on accrual basis.
C104: Dividend income is accounted for when the right to receive it is established.
B106: =B101+0.1 -> 3 | C106: Tangible fixed assets
A108: AS 10.20 AS 10.23 AS 10.8.2 | C108: Fixed assets, except __ and ___ are carried at cost less accumulated depreciation and impairment losses, if any. The cost of fixed assets includes interest on borrowings attributable to acquisition of qualifying fixed assets up to the date the asset is ready for its intended use and other incidental expenses incurred up to that date. Exchange differences arising on restatement / settlement of long-term foreign currency borrowings relating to acquisition of depreciable fixed assets are adjusted to the cost of the respective assets and depreciated over the remaining useful life of such assets. Machinery spares which can be used only in connection with an item of fixed asset and whose use is expected to be irregular are capitalised and depreciated over the useful life of the principal item of the relevant assets. Subsequent expenditure relating to fixed assets is capitalised only if such expenditure results in an increase in the future benefits from such asset beyond its previously assessed standard of performance. Fixed assets acquired and put to use for project purpose are capitalised and depreciation thereon is included in the project cost till commissioning of the project.
A110: AS 10.22 | C110: Fixed assets acquired in full or part exchange for another asset are recorded at the fair market value or the net book value of the asset given up, adjusted for any balancing cash consideration. Fair market value is determined either for the assets acquired or asset given up, whichever is more clearly evident. Fixed assets acquired in exchange for securities of the Company are recorded at the fair market value of the assets or the fair market value of the securities issued, whichever is more clearly evident.
A112: AS 10.27 AS 10.30 | C112: The Company revalued all its ___ and ___ that existed on 1 April, 200X. The revalued assets are carried at the revalued amounts less accumulated depreciation and impairment losses, if any. Increase in the net book value on such revaluation is credited to "Revaluation reserve account" except to the extent such increase is related to and not greater than a decrease arising from a revaluation / impairment that was previously recognised in the Statement of Profit and Loss, in which case such amount is credited to the Statement of Profit and Loss. Decrease in book value on revaluation is charged to the Statement of Profit and Loss except where such decrease relates to a previously recognised increase that was credited to the Revaluation reserve, in which case the decrease is charged to the Revaluation reserve to the extent the reserve has not been subsequently reversed / utilised.
A114: AS 10.24 | C114: Fixed assets retired from active use and held for sale are stated at the lower of their net book value and net realisable value and are disclosed separately in the Balance Sheet.
C116: Capital work-in-progress:
C117: Projects under which assets are not ready for their intended use and other capital work-in-progress are carried at cost, comprising direct cost, related incidental expenses and attributable interest.
A120: =$A$2 -> M/s. Sathiapal Engineers (India) Private Limited (Formerly known as M/S Sathiapal Engineers (India) Limited)
A121: =$A$3 -> New No. 57, Old No. 3, Canal Road, Kilpauk Garden Colony, Kilpauk, Chennai 600 010.
A122: =$A$4 -> Notes forming part of the financial statements | B122: Notes forming part of the financial statements
B124: Note 2 Significant accounting policies (contd.)
A126: Ref No. | B126: Note | C126: Particulars
B128: 2.1 | C128: Intangible assets
A130: AS 26.23 AS 26.59 AS 26.62 | C130: Intangible assets are carried at cost less accumulated amortisation and impairment losses, if any. The cost of an intangible asset comprises its purchase price, including any import duties and other taxes (other than those subsequently recoverable from the taxing authorities), and any directly attributable expenditure on making the asset ready for its intended use and net of any trade discounts and rebates. Subsequent expenditure on an intangible asset after its purchase / completion is recognised as an expense when incurred unless it is probable that such expenditure will enable the asset to generate future economic benefits in excess of its originally assessed standards of performance and such expenditure can be measured and attributed to the asset reliably, in which case such expenditure is added to the cost of the asset. Refer Note 2.21 for accounting for Research and Development Expenses.
B184: ='[30]Addl Info to the FS'!#REF!+0.01 -> #REF! | C184: Government grants, subsidies and export incentives
A186: AS 12.13 AS 12.14 AS 12.15 AS 12.16 AS 12.17 | C186: Government grants and subsidies are recognised when there is reasonable assurance that the Company will comply with the conditions attached to them and the grants / subsidy will be received. Government grants whose primary condition is that the Company should purchase, construct or otherwise acquire capital assets are presented by deducting them from the carrying value of the assets. The grant is recognised as income over the life of a depreciable asset by way of a reduced depreciation charge.
C187: Export benefits are accounted for in the year of exports based on eligibility and when there is no uncertainty in receiving the same.
C188: Government grants in the nature of promoters' contribution like investment subsidy, where no repayment is ordinarily expected in respect thereof, are treated as capital reserve. Government grants in the form of non-monetary assets, given at a concessional rate, are recorded on the basis of their acquisition cost. In case the non-monetary asset is given free of cost, the grant is recorded at a nominal value. Other government grants and subsidies are recognised as income over the periods necessary to match them with the costs for which they are intended to compensate, on a systematic basis.
B190: =B184+0.01 -> #REF! | C190: Investments
A192: AS 13.28 AS 13.31 AS 13.32 AS 13.35.a | C192: Long-term investments (excluding investment properties), are carried individually at cost less provision for diminution, other than temporary, in the value of such investments. Current investments are carried individually, at the lower of cost and fair value. Cost of investments include acquisition charges such as brokerage, fees and duties. Investment properties are carried individually at cost less accumulated depreciation and impairment, if any. Investment properties are capitalised and depreciated (where applicable) in accordance with the policy stated for Tangible Fixed Assets. Impairment of investment property is determined in accordance with the policy stated for Impairment of Assets.
B194: =2.1 -> 2.1 | C194: Employee benefits
C196: a. Short term employee benefits including salaries, social security contributions, short term compensated absences (such as paid annual leave) where the absences are expected to occur within twelve months after the end of the period in which the employees render the related service, bonuses payable within twelve months after the end of the period in which the employees render the related services and non monetary benefits for current employees are estimated and measured on an undiscounted basis.
C197: Employee benefits include Employees Provident Fund, Gratuity Fund, compensated absences, long service awards and post-employment medical benefits.
A199: AS 15.45 | C199: b. Defined contribution plans
C200: The Company's contribution to provident fund and superannuation fund are considered as defined contribution plans and are charged as an expense as they fall due based on the amount of contribution required to be made.
C201: Company's contributions paid/payable during the year to Provident Fund and Employee State Insurance are recognised int the Statement of Profit and Loss.
A203: =$A$2 -> M/s. Sathiapal Engineers (India) Private Limited (Formerly known as M/S Sathiapal Engineers (India) Limited)
A204: =$A$3 -> New No. 57, Old No. 3, Canal Road, Kilpauk Garden Colony, Kilpauk, Chennai 600 010.
A205: =$A$4 -> Notes forming part of the financial statements | B205: Notes forming part of the financial statements
B207: Note 2 Significant accounting policies (contd.)
A209: Ref No. | B209: Note | C209: Particulars
A211: AS 15.10 AS 15.11 | C211: Short-term employee benefits
C212: The undiscounted amount of short-term employee benefits expected to be paid in exchange for the services rendered by employees are recognised during the year when the employees render the service. These benefits include performance incentive and compensated absences which are expected to occur within twelve months after the end of the period in which the employee renders the related service. The cost of such compensated absences is accounted as under : (a) in case of accumulated compensated absences, when employees render the services that increase their entitlement of future compensated absences; and (b) in case of non-accumulating compensated absences, when the absences occur.
A213: AS 15.129 | C213: Long-term employee benefits
C214: Compensated absences which are not expected to occur within twelve months after the end of the period in which the employee renders the related service are recognised as a liability at the present value of the defined benefit obligation as at the Balance Sheet date less the fair value of the plan assets out of which the obligations are expected to be settled. Long Service Awards are recognised as a liability at the present value of the defined benefit obligation as at the Balance Sheet date.
B216: =B194+0.01 -> 2.11 | C216: Employee share based payments
C218: The Company has formulated Employee Stock Option Schemes (ESOS) in accordance with the SEBI (Employee Stock Option Scheme and Employee Stock Purchase Scheme) Guidelines, 1999. The Schemes provide for grant of options to employees of the Company and its subsidiaries to acquire equity shares of the Company that vest in a graded manner and that are to be exercised within a specified period. In accordance with the SEBI Guidelines; the excess, if any, of the closing market price on the day prior to the grant of the options under ESOS over the exercise price is amortised on a straight-line basis over the vesting period. [OR]
C219: The Company has constituted an Employee Stock Option Plan - XXXX. Employee Stock Options granted on or after 1 April, 2005 are accounted under the ‘Intrinsic Value Method’ stated in the Guidance Note on Employee Share Based Payments issued by the Institute of Chartered Accountants of India.
B221: =B194+0.01 -> 2.11 | C221: Foreign currency transactions and translations
C223: Transactions in foreign currencies are recorded at the exchange rate prevailing on the date of the transaction. Current assets and liabilities denominated in foreign currency are translated at the rate of exchange as the Balance Sheet date. All resulting gains or losses are recognized in the statement of Profit and Loss.
B227: =B221+0.01 -> 2.12 | C227: Borrowing costs
A229: AS 16.6 AS 16.14 AS 16.17 AS 16.19 | C229: Borrowing costs include interest, amortisation of ancillary costs incurred and exchange differences arising from foreign currency borrowings to the extent they are regarded as an adjustment to the interest cost. Costs in connection with the borrowing of funds to the extent not directly related to the acquisition of qualifying assets are charged to the Statement of Profit and Loss over the tenure of the loan. Borrowing costs, allocated to and utilised for qualifying assets, pertaining to the period from commencement of activities relating to construction / development of the qualifying asset upto the date of capitalisation of such asset is added to the cost of the assets. Capitalisation of borrowing costs is suspended and charged to the Statement of Profit and Loss during extended periods when active development activity on the qualifying assets is interrupted.
...

Sheet Cash Flow
B2: =+PL!A2 -> M/s. Sathiapal Engineers (India) Private Limited (Formerly known as M/S Sathiapal Engineers (India) Limited)
C3: =BS!A3 -> CIN: U74210TN2002PLC048568
B4: =+PL!A4 -> New No. 57, Old No. 3, Canal Road, Kilpauk Garden Colony, Kilpauk, Chennai 600 010.
B6: CASH FLOW STATEMENT FOR THE YEAR ENDED 31ST MARCH, 2023
D7: (Rs.in 000's)
B8: Particulars | D8: For the year 2022-23 | F8: For the year 2021-22
D9: ₹ | E9: ₹ | F9: ₹ | G9: ₹ | I9: =D13/1000 -> 8219.8265
B10: A. Cash flow from operating activities
B11: Net Profit / (Loss) before extraordinary items and tax | E11: =+PL!C30 -> 43618707 | G11: =30083.6078004535*1000 -> 30083608 | H11: 1000
B12: Adjustments for: | H12: =D116 -> -5360596
B13: Depreciation and amortisation | D13: =Dep_Co!K26 -> 8219826.5 | F13: =9718.98258954644*1000 -> 9718982.6
B14: Interest | D14: =-Notes!J235 -> -3323836 | F14: =-4642.716*1000 -> -4642716
B15: Dividend
B16: Rent
B17: Amortisation of share issue expenses and discount on shares
B18: (Profit) / loss on sale of assets | D18: =(-'Audit entries FY 22-23'!D71) -> -216704 | H18: 1000
B19: Write off of assets | D19: =Dep_Co!H13 -> 868251
B20: Finance costs
B21: Interest income
B22: Prior period Adjustment | D22: =PL!C31 -> 2621516 | I22: =#REF!-#REF! -> #REF!
E23: =SUM(D13:D22) -> 8169053.5 | G23: =5076.26658954644*1000 -> 5076266.6
B24: Operating profit / (loss) before working capital changes | E24: =SUM(E11:E23) -> 51787761 | G24: =SUM(G11:G23) -> 35159874
B25: Changes in working capital:
B26: Adjustments for (increase) / decrease in operating assets:
B27: Inventories | D27: =+BS!E46-BS!C46 -> -51490000 | F27: 4160000
B28: Trade Receivables | D28: =+BS!E47-BS!C47 -> 47643265 | F28: 1872245.2
B29: Short-term loans and advances | D29: =BS!E49-BS!C49 -> -35103265 | F29: -6339202.2
B30: Long-term loans and advances | D30: =BS!E41-BS!C41 -> 1660362.8 | F30: 0
B31: Other current assets | D31: =BS!E50-BS!C50-BS!C40 -> 3935754 | F31: -719070
F32: 0 | J32: 27.10.2021
B33: Adjustments for increase / (decrease) in operating liabilities: | F33: 0
B34: Trade payables | D34: =BS!C25-BS!E25 -> 11210090 | F34: -7769310.4
B35: Other current liabilities | D35: =BS!C26-BS!E26 -> -18558220 | F35: 14132294
B36: Other long-term liabilities | F36: 0
B37: Short-term provisions | D37: 0 | F37: 0
B38: Short term borrowings | D38: =BS!C24-BS!E24+5 -> 8351507 | F38: -1431555
E39: =SUM(D27:D38) -> -32350507 | G39: =3905.40118084745*1000 -> 3905401.2
E40: =SUM(E24:E39) -> 19437253 | G40: =39065.2755708474*1000 -> 39065276
B41: Cash flow from extraordinary items | E41: 0 | G41: 0
B42: Cash generated from operations | E42: =E40-E41 -> 19437253 | G42: =G40-G41 -> 39065276
B43: Net income tax (paid) / refunds | E43: =-8443.336*1000 -> -8443336 | G43: =-4300.7544*1000 -> -4300754.4
B45: Net cash flow from / (used in) operating activities (A) | E45: =SUM(E42:E43) -> 10993917 | G45: =SUM(G42:G43) -> 34764521
B49: Particulars
B51: B. Cash flow from investing activities | I51: =1117960619-G127 -> 1.0844878e+09
B52: Capital expenditure on fixed assets, including capital advances | D52: =-Dep_Co!G26 -> -33034288 | F52: -14816175
B53: Proceeds from sale of fixed assets | D53: =('Audit entries FY 22-23'!C68) -> 260000 | F53: 0 | H53: 1000
B54: Inter-corporate deposits (net) | F54: 0
B55: Income from Investments | D55: 0 | F55: 0
B56: Interest | D56: =-D14 -> 3323836 | F56: 4642716
B57: Rent | D57: - | F57: -
B58: Dividend | D58: 0 | F58: 0
B59: Current investments not considered as Cash and cash equivalents | F59: 0
B60: - Purchased | F60: 0
B61: - Proceeds from sale | F61: 0
B62: Purchase of long-term investments | F62: 0 | J62: tax paid | K62: =+Notes!K110+PL!D40-BS!E27 -> 8443336.4
B63: - Subsidiaries | F63: 0
B64: - Associates | F64: 0
B65: - Joint ventures | F65: 0
B66: - Business units | F66: 0
B67: - Others | F67: 0
B68: Proceeds from sale of long-term investments | F68: 0
B69: - Subsidiaries | F69: 0
B70: - Associates | F70: 0
B71: - Joint ventures | F71: 0
B72: - Business units | F72: 0
B73: - Others | F73: 0
B74: Loans given | F74: 0
... B98: Amounts received from LLPs | F98: 0
B99: Net Proceeds from Term Deposits | D99: =Notes!K191-Notes!J191 -> 11575162 | F99: 13923085
B100: Long term loans and advances | F100: -13056751
E101: =SUM(D52:D100) -> -17875290 | G101: =-9307.12401881846*1000 -> -9307124
B102: Cash flow from extraordinary items | E102: 0 | G102: 0
G103: 0
E104: =SUM(E101:E103) -> -17875290 | G104: =-9307.12401881846*1000 -> -9307124
B105: Net income tax (paid) / refunds | E105: 0 | G105: 0
B107: Net cash flow from / (used in) investing activities (B) | E107: =SUM(E104:E105) -> -17875290 | G107: =-9307.12401881846*1000 -> -9307124
B111: Particulars
B114: C. Cash flow from financing activities
B115: Net Proceeds from Short-term borrowings | D115: 0 | F115: 0
B116: Dividends paid | D116: =Notes!J53 -> -5360596 | F116: =-7147.46*1000 -> -7147460 | G116: 0
B117: Tax on dividend | D117: 0 | F117: 0 | G117: 0
E118: =SUM(D115:D117) -> -5360596 | G118: =-7147.46*1000 -> -7147460
B119: Cash flow from extraordinary items | E119: 0 | G119: 0
G120: 0
B121: Net cash flow from / (used in) financing activities (C) | E121: =SUM(E118:E119) -> -5360596 | G121: =G118 -> -7147460
B123: Net increase / (decrease) in Cash and cash equivalents (A+B+C) | E123: =E45+E107+E121+0.5 -> -12241968 | G123: =G45+G107+G121+6 -> 18309943
B124: Cash and cash equivalents at the beginning of the year | E124: =(G145) -> 33472811 | G124: =15162.86767*1000 -> 15162868
B125: Prior period Adjustment | E125: 0 | G125: 0 | I125: =G127 -> 33472811
B126: Round Off Adjustments
B127: Cash and cash equivalents at the end of the year | E127: =E123+E124+E125+E126 -> 21230843 | G127: =G123+G124+G125+G126 -> 33472811 | I127: =Notes!K193 -> 1.0225936e+08
B128: Reconciliation of Cash and cash equivalents with the Balance Sheet: | I128: =I125-I127 -> -68786551
B129: Cash and cash equivalents as per Balance Sheet (Refer Note 15) | E129: =+Notes!J193 -> 78442232 | G129: =102259.3617*1000 -> 1.0225936e+08 | I129: =E127-E131 -> 21230843
B130: Less: Bank balances not considered as Cash and cash equivalents as defined in AS 3 Cash Flow Statements (give details) | E130: =-Notes!J191 -> -57211389 | G130: =-68786.551*1000 -> -68786551
B131: Net Cash and cash equivalents (as defined in AS 3 Cash Flow Statements) included in Note 16 | I131: =E127-E131 -> 21230843
B132: Add: Current investments considered as part of Cash and cash equivalents (as defined in AS 3 Cash Flow Statements) (Refer Note (ii) to Note 16 Current investments) | H132: =E133-E127 -> 0.22000004
B133: Cash and cash equivalents at the end of the year * | E133: =SUM(E129:E132) -> 21230843 | G133: =33472.8107*1000 -> 33472811 | H133: =E127-E133 -> -0.22000004 | I133: =I131/2 -> 10615421
B134: * Comprises: | G134: 0 | I134: =E133-E127 -> 0.22000004 | J134: -3549989
B135: (a) Cash on hand | E135: =SUM(Notes!J186:J187) -> 7137075.6 | G135: =7550.78354999995*1000 -> 7550783.5 | I135: =I134/2 -> 0.11000002
B136: (b) Cheques, drafts on hand | E136: 0 | G136: 0
B137: (b) Balances with banks | G137: 0
...

Sheet Audit entries FY 22-23
A1: S.No | B1: Particulars | C1: Dr | D1: Cr
A2: 1 | B2: Audit Fees | C2: 412000
B3: TDS Payable | C3: =C2*10% -> 41200
B4: A john moris & Co | D4: =C2-C3 -> 370800
B5: (Audit fees for the FY 22-23)
A7: 2 | B7: Interest on PF | C7: =718+125+13866 -> 14709
B8: To PF (Site) | D8: =C7 -> 14709
B9: (Interest on PF for delayed payment)
A12: =A7+1 -> 3 | B12: Princy land surveyors | C12: 18149.153
B13: Smart Exteriors | C13: 16200
B14: Sri Amman Lath works | C14: 11393.76 | E14: Trade payable
B15: BBR (India) pvt ltd | C15: 931.89576
B16: Shri Vishnu Refractories | C16: 5672.4305 | E16: Trade payable
B17: Steel Link | C17: 1913.5466 | E17: Trade advances
B18: Steel world | C18: 1006.4907 | E18: Trade payable
B19: Ajay Singh | C19: 5481.84 | E19: Trade advances
B20: Borana Engineers & Contractors | C20: 4240 | E20: Trade payable
B21: Elite Engineers | C21: 5959
B22: Gulam Nabi & Sons | C22: 62460
B23: Jai Biswas | C23: 14457.74
B24: Jitendra Kumar Carpentor | C24: 12616.11 | E24: Trade payable
B25: Mohammad Shahensha | C25: 534.43 | E25: Trade advances
B26: Narendhar Saw | C26: 8140.26
B27: Ram Sagar Singh | C27: 1992.17 | E27: Trade payable
B28: R.J. Enterprises | C28: 13996.322
B29: Sadanandakar | C29: 1606
B30: S.K. Steel | C30: 4333.6102 | E30: Trade payable
B31: Sushmaa Demolition work | C31: 851.54237 | E31: Trade payable
B32: Aarov Readymix | C32: 1077.6271
B33: Navkar Construction Company | C33: 2740.4576 | E33: Trade payable
B34: Sri Venkata Padmaja Ceramics | C34: 1682.3695 | E34: Trade advances
B35: To TDS Payable | D35: =SUM(C12:C34) -> 197436.75
A37: =A12+1 -> 4 | B37: TCS Receivable | C37: =SUM(D38:D40) -> 172218
B38: To Steel | D38: 10518 | E38: construction material consumed
B39: To RMC | D39: 22284 | E39: construction material consumed
B40: To planks runners & plywood | D40: 139416 | E40: construction material consumed
A42: =A37+1 -> 5 | B42: TDS Receivable
B43: To Contract advance | D43: =C42 -> 0
A45: 6 | B45: Staff welfare expenses | C45: 231886.25
B46: To ESI | D46: 231886.25
B48: ESI Payable | C48: 17120.75
B49: To Staff welfare payable | D49: 17120.75
A52: 7 | B52: FD | C52: 7010403 | F52: =3551493 -> 3551493
B53: To Interest Receivable | D53: =C52 -> 7010403
A55: =A52+1 -> 8 | B55: Interest received on FD | C55: 226153
B56: To Interest Receivable | D56: =C55 -> 226153 | F56: =C100 -> 2621516
F57: =F56-D56 -> 2395363
A58: =A55+1 -> 9 | B58: Prepaid Expenses | C58: =177551+105649 -> 283200
B59: To Insurance | D59: 177551
B60: To Group Gratuity | D60: 105649
A62: =A58+1 -> 10 | B62: Deferred Tax Expenses | C62: =Sheet10!B9 -> 742110.62
B63: Deferred Tax Liability | D63: =C62 -> 742110.62
A65: =A62+1 -> 11 | B65: Deferred Tax Income | C65: =Notes!J155 -> -742110.62
B66: To P&L | D66: =C65 -> -742110.62
H67: Nexagon | I67: 260000
C68: 260000 | H68: To vehicle | J68: =I67 -> 260000
A69: 13 | B69: Accumulated depreciation | C69: 822623.05 | J69: =D70-C69 -> 43295.95 | L69: Vehicle | M69: 216704
B70: To vehicle | D70: 865919 | L70: To Profit on sale of Asset | N70: =M69 -> 216704
B71: To profit on sale of asset | D71: 216704
A79: 14 | B79: Building write off expenses | C79: =D80 -> 868251
B80: To Building | D80: =Dep_Co!H13 -> 868251 | E80: =D80-C68 -> 608251
A82: 15 | B82: Purchase | C82: 141084.27
B83: Computer | C83: 8140.4407
B84: To Plant and Machinery | D84: 149224.71
A86: =A82+1 -> 16 | B86: Contract advance | C86: =800000+325000+500 -> 1125500
B87: Vishaka Structurrls (Ultratech Karnataka)S.Drs | D87: =C86 -> 1125500
A89: 17 | B89: Loans & Advances | C89: 5912325.9
B90: To Misc Expense | D90: =C89 -> 5912325.9
A93: 19 | B93: TDS Receivable | C93: 105799
B94: Thermax LTD | D94: =C93 -> 105799
A97: 20 | B97: Kec International ACC S.Drs(UP) | C97: 700000
B98: SD | D98: =C97 -> 700000
A100: 21 | B100: Interest Receivable | C100: 2621516
B101: Interest Income Written back | D101: =C100 -> 2621516
B105: 3092642
B106: 3134072
B107: 3112584
B108: 3163488
B109: 3753710
B110: 6131582
B111: =SUM(B105:B110) -> 22388078
A113: 21 | B113: Loans & Advances | C113: =B111 -> 22388078
B114: Steel | D114: =B105+B106+B107+B108 -> 12502786
B115: RMC | D115: =B109+B110 -> 9885292
A117: 22 | B117: Trade receivable | C117: 2545868
B118: Miscellaneous expenses | D118: =C117 -> 2545868
A120: 23 | B120: Construction work expenses | C120: 6534725
B121: To Staff welfare expenses | D121: =C120 -> 6534725
B123: Plant and Machinery | C123: ='Sheet1 (2)'!M38 -> 4927384.1
B124: Purchase | C124: =SUM(D125:D126)-C123 -> 1081620.9
B125: To Construction material consumed | D125: ='Sheet1 (2)'!K17 -> 4695237
B126: To Repairs and Maintenance | D126: ='Sheet1 (2)'!K38 -> 1313768

Sheet BS
A2: =IT!C2 -> M/s. Sathiapal Engineers (India) Private Limited (Formerly known as M/S Sathiapal Engineers (India) Limited)
A3: CIN: U74210TN2002PLC048568
A4: New No. 57, Old No. 3, Canal Road, Kilpauk Garden Colony, Kilpauk, Chennai 600 010.
A6: Balance Sheet as at 31st March 2023 as per schedule III of Companies Act 2013
A8: Particulars | B8: Notes | C8: As at 31.03.2023 | E8: As at 31.03.2022 | G8: As at 31.03.2019
G9: =PL!D9 -> 0
A10: I.EQUITY AND LIABILITIES
A12: (1)SHAREHOLDER'S FUND | J12: =1/1000 -> 0.001
A13: (a)Share Capital | B13: =Notes!B7 -> 3 | C13: =Notes!I16 -> 7147460 | E13: =7147.46*1000 -> 7147460 | G13: =Notes!K16 -> 7147460 | J13: =D15*1000 -> 3.2270884e+11
A14: (b)Reserves and Surplus | B14: =Notes!B41 -> 4 | C14: =+Notes!J59 -> 3.1556138e+08 | E14: =286389.161555591*1000 -> 2.8638916e+08 | G14: =Notes!#REF! -> #REF!
D15: =+C13+C14-0.3 -> 3.2270884e+08 | F15: =+E13+E14 -> 2.9353662e+08 | H15: =SUM(G13:G14) -> #REF! | I15: =D15-F15 -> 29172221 | J15: ='Cash Flow'!E11 -> 43618707 | K15: =J15-I15 -> 14446486 | L15: =PL!C34 -> 0 | M15: =K15-L15 -> 14446486
A16: (c)) Money received against share warrants
A17: (2)SHARE APPLICATION MONEY PENDING ALLOTMENT
A18: (3)NON-CURRENT LIABILITIES
A19: (a)Long Term Borrowings
A20: (b)Other long-term liabilities | B20: =+Notes!B62 -> 5 | C20: =Notes!J65 -> 32203.14 | E20: =32.20314*1000 -> 32203.14 | G20: =Notes!K65 -> 32203.14
A21: (c)Deferred Tax Liabilities | B21: =Notes!B139 -> 11 | C21: =-Notes!J156 -> 1615571.3 | E21: =-Notes!K156 -> 873452.38 | G21: =-Notes!K156 -> 873452.38 | H21: =G20+G21 -> 905655.52 | I21: =D21-F21 -> 0
A22: (c)Long term Provisions | D22: =C21+C20 -> 1647774.4 | F22: =E21+E20 -> 905655.52
A23: (4)CURRENT LIABILITIES
A24: (a)Short Term Borrowings | B24: =+Notes!B67 -> 6 | C24: =+Notes!J74 -> 11392871 | E24: =3041.369*1000 -> 3041369 | G24: =Notes!K74 -> 3041369 | I24: =C24-E24 -> 8351502 | L24: 74920
A25: (b)Trade Payables | B25: =Notes!B77 -> 7 | C25: =+Notes!J83 -> 17772800 | E25: =6562.70984*1000 -> 6562709.8 | G25: 7428819 | I25: =C25-E25 -> 11210090
A26: (c)Other Current Liabilities | B26: =Notes!B86 -> 8 | C26: =+Notes!J104 -> 22830334 | E26: =41388.55377*1000 -> 41388554 | G26: =+Notes!K104 -> 41388554 | I26: =C26-E26 -> -18558220 | L26: =SUM(L24:L25) -> 74920
A27: (d)Short Term Provisions | B27: =Notes!B107 -> 9 | C27: =+Notes!J111 -> 10965295 | E27: =8443.3364*1000 -> 8443336.4 | G27: =+Notes!K111 -> 8443336.4 | I27: =C27-E27 -> 2521958.6 | L27: 4500
D28: =+C24+C25+C26+C27 -> 62961299 | F28: =+E24+E25+E26+E27 -> 59435969 | H28: =SUM(G24:G27) -> 60302078 | L28: =SUM(L26:L27) -> 79420
A29: Total | D29: =D28+D20+D15+D22 -> 3.8731792e+08 | F29: =F28+F20+F15+F22 -> 3.5387825e+08 | H29: =SUM(H10:H28) -> #REF! | I29: =SUM(I15:I28) -> 32697551 | J29: =382773-D29 -> -3.8693514e+08 | K29: 4545.1735 | L29: 1564.472 | M29: -440 | N29: -432
A30: II.ASSETS | L30: =189563548/1000 -> 189563.55 | M30: =L30-L29 -> 187999.08 | N30: 114643 | O30: =M30-N30 -> 73356.076
A32: NON-CURRENT ASSETS | L32: =D29-D52 -> 0.68317133 | M32: =L32/2 -> 0.34158567
A33: Property,Plant & Equipment and Intangible Assets | I33: 11182296 | L33: 19277
I34: 5360596 | L34: =L33+L32 -> 19277.683 | M34: =L34 -> 19277.683
A35: (1)(a)Property,Plant and Equipments | B35: =Notes!B115 -> 10 | C35: =Dep_Co!N26 -> 79464956 | E35: =55562.0408502087*1000 -> 55562041 | H35: 45976627 | I35: -1516347 | J35: =E35-C35 -> -23902916 | K35: =C35-D15 -> -2.4324389e+08 | L35: =L32+4.2 -> 4.8831713 | M35: =L35/2 -> 2.4415857
A36: (ii)Intangible Assets | I36: 5912326
A37: (iii)Capital Work in Progress | I37: 20938871 | L37: 20938871
A38: (iv)Intangible Assets under development | K38: =E35-C35 -> -23902916 | L38: -5912326
A39: (b)Non-current Investments | C39: =+Notes!J135 -> 0 | E39: 0 | G39: =Notes!K135 -> 0 | L39: 1516347
A40: (c)Deferred Tax Assets | L40: -5360596
A41: (b)Long Term Loans and Advances | B41: =Notes!B159 -> 12 | C41: =+Notes!J165 -> 74626866 | E41: =76287.2285*1000 -> 76287228 | G41: =Notes!K165 -> 76287228
A42: (2) Deferred Tax Asset | B42: 11 | D42: =SUM(C35:C42) -> 1.5409182e+08 | F42: =E35+E41+E42 -> 1.3184927e+08 | H42: =SUM(G39:G41) -> 76287228 | I42: =F42-D42 -> -22242553
A43: (e)Other Non Current Assets
A44: (3)CURRENT ASSETS | L44: =L32*1000 -> 683.17133
A45: (a)Current Investments | L45: =L44/2 -> 341.58567
A46: (b)Inventories | B46: =Notes!B168 -> 13 | C46: =+Notes!J171 -> 77330000 | E46: =25840*1000 -> 25840000 | G46: =Notes!K172 -> 25840000 | I46: =E46-C46 -> -51490000
A47: (c)Trade Receivables | B47: =Notes!B175 -> 14 | C47: =+Notes!J181 -> 12929680 | E47: =60572.94484*1000 -> 60572945 | G47: =Notes!K181 -> 60572945 | I47: =E47-C47 -> 47643265 | K47: 12241975
A48: (d)Cash and Cash Equivalents | B48: =Notes!B184 -> 15 | C48: =+Notes!J193 -> 78442232 | E48: =102259.3617*1000 -> 1.0225936e+08 | G48: =Notes!K193 -> 1.0225936e+08 | I48: =E48-C48 -> 23817130 | J48: =Notes!K191-Notes!J191 -> 11575162 | K48: =K47-#REF!+I48 -> #REF! | L48: =Notes!N191-Notes!M191 -> 0
A49: (e)Short Term Loans and Advances | B49: =Notes!B201 -> 16 | C49: =+Notes!J212 -> 60409034 | E49: =25305.7682*1000 -> 25305768 | G49: =Notes!K212 -> 25305768 | I49: =E49-C49 -> -35103265
A50: (f)Other Current Assets | B50: =Notes!B216 -> 17 | C50: =+Notes!J222 -> 4115148 | E50: =8050.902*1000 -> 8050902 | G50: =Notes!K222 -> 8050902 | I50: =E50-C50 -> 3935754 | K50: =J48+I50 -> 15510916
D51: =+C46+C47+C48+C49+C50 -> 2.3322609e+08 | F51: =+E46+E47+E48+E49+E50-0.01 -> 2.2202898e+08 | H51: =SUM(G46:G50) -> 2.2202898e+08
A52: Total | D52: =D42+D51 -> 3.8731792e+08 | F52: =F42+F51 -> 3.5387825e+08 | H52: =SUM(H35:H51) -> 3.4429283e+08 | I52: =SUM(I42:I51) -> -33439670
A53: Significant Accounting Policies and Notes to Financial Statements form an integral part of the Balance Sheet | B53: 1 to 27 | K53: 44742397
A54: =PL!A54 -> In accordance with our Report of even date attached
A55: For A.JOHN MORIS & CO | D55: For and on behalf of the Board of Directors
A56: Chartered Accountants
A57: Registration No. 007220S
A60: =PL!A60 -> (CA A.JOHN MORIS)
A61: =PL!A61 -> Managing Partner | D61: (S. KUMARAN) | E61: ( K.VISALAKSHI)
A62: =PL!A62 -> M.No. 029424 | D62: Managing Director | E62: Director
A63: Place: Chennai | D63: DIN No.01926196 | E63: DIN No.01926144
A64: Date: 07-09-2023

Sheet Corporate & Acctg Policies
A2: M/s. Sathiapal Engineers (India)Private Limited Formerly known as M/S Sathiapal Engineers (India) Limited
A3: =PL!A4 -> New No. 57, Old No. 3, Canal Road, Kilpauk Garden Colony, Kilpauk, Chennai 600 010.
A4: Notes forming part of the financial statements
A6: Note | B6: Particulars
A8: 1 | B8: Corporate information
B9: M/s. Sathiapal Engineers (India) Private Limited formerly known as M/s. Sathiapal Engineers (India) Limitedis registered with the Chennai Registrar of Companies as a Public Limited Company on 07th March 2002 vide Registration no. U74210TN2002PLCO48568
B12: The registered office of the company is located at New No. 57, Old No. 3, Canal Road, Kilpauk Garden Colony, Kilpauk, Chennai 600 010.
B14: The Principal activities of the Company is to engage in microfinance activities with the ultimate objective of benefiting the poor and downtrodden, (organized in the form of Self Help Groups) for enhancement of their livelihoods in a financially viable manner. The Company generally provides small value collateral free loans upto Rs. 1,00,000 for a tenor of 20 months with monthly repayment.
B15: The Principal activities of the Company is undertaking Specialised Construction of Tall Structures like Silos for Cement Plants, RCC Chimneys for Power, Suger, Paper, Chemical, etc., thro Slip-Form Technology and also Construction of Educational Institutions.
B16: The Company was converted from Public Company to Private company with effect from 10th April 2019 and herein after called as M/s.Sathiapal Engineers (India) Private limited.
A18: 2 | B18: Significant accounting policies
B19: The significant accounting policies have been predominantly presented below in the order of the Accounting Standards notified under the Companies (Accounting Standards) Rules, 2006 (as amended). The order of presentation may be customised for each Company.
B20: The significant accounting policies would need to be customised for each Company based on its applicability and relevance. For example, in case of a Small and Medium Sized Company, it should state in its financial statements that "The Company is a Small and Medium Sized Company as defined in the General Instructions in respect of Accounting Standards notified under the Companies (Accounting Standards) Rules, 2006 (as amended). Accordingly, the Company has complied with the Accounting Standards as applicable to a Small and Medium Sized Company." and should also modify the accounting policies suitably. Similarly, companies that have not opted for the transition provisions in para 46 / 46A of AS 11 The Effects of Changes in Foreign Exchange Rates and companies that have not opted for Hedge Accounting should modify the accounting policies on Foreign Currency Transactions and Translations and Hedge Accounting, respectively.
A21: 2.1 | B21: Basis of accounting and preparation of financial statements
B23: The financial statements of the Company have been prepared in accordance with the Generally Accepted Accounting Principles in India (Indian GAAP). The Company has prepared these financials statements to comply in all material respects with the Accounting Standards notified under the Companies (Accounting Standards) Rules, 2014 (as amended) and the relevant provisions of the Companies Act, 2013. The financial statements have been prepared on accrual basis and the directions issued by the Reserve Bank of India to the extent applicable to the Company.
A25: =A21+0.1 -> 2.2 | B25: Use of estimates
B27: The preparation of the financial statements in conformity with Indian GAAP and that requires the Management to make estimates and assumptions that affect the reported amounts of assets and liabilities and disclosure of contingent assets and liabilities at the date of the financial statements and reported amounts of revenues and expenses during the reporting period. Although such estimates are made on a reasonable and prudent basis taking into account all available information, actual results could differ from those estimates.
A33: Notes forming part of the financial statements
A35: Note 2 Significant accounting policies (contd.)
A37: Note | B37: Particulars
A40: =2.3 -> 2.3 | B40: Cash and cash equivalents (for purposes of Cash Flow Statement)
B42: Cash comprises cash on hand and demand deposits with banks. Cash equivalents are short-term balances (with an original maturity of three months or less from the date of acquisition), highly liquid investments that are readily convertible into known amounts of cash and which are subject to insignificant risk of changes in value.
A44: =A40+0.1 -> 2.4 | B44: Cash flow statement
B46: Cash flows are prepared in accordance with the indirect method prescribed in Accounting Standard-3.
A48: 2.5 | B48: Net profit or loss for the period, Prior Period items and changes in accounting policies
B50: Net profit or loss for the period, Prior Period items and changes in accounting policies have been accounted as per the Accounting Standard 5.
A52: =A48+0.1 -> 2.6 | B52: Construction Contract
B54: Inventories has been valued as per AS 7 Construction contracts on completion of the physical proportion of contract work. Expenses incurred in respect of uncompleted projects have been valued as inventories in accordance with AS 7.
A56: =A52+0.1 -> 2.7 | B56: Property plant and equipement
B58: Property plant and equipment are stated at cost net of depreciation. The cost of an asset comprises its purchase price and any cost directly attributable for bringing the asset to its working condition and location for its intended use.
B59: Depreciable amount for assets is the cost of an asset, or other amount substituted for cost, less its estimated residual value. Depreciation on Property, Plant and Equipment has been provided on Straight Line value method as per the useful life prescribed in Schedule II to the Companies Act, 2013.
B60: Depreciation on additions is charged proportionately from the date of acquisition/installation.
B63: Individual assets costing less than Rs. 5000/- are depreciated in ful, in the year of acquisition.
A74: =#REF!+0.1 -> #REF! | B74: Receivables
B76: Receivables under Financing activity include Gold Loans, Mortgage Loans and Business Loans. Loans are classified into 'Performing and Non-Performing' assets in terms of the Non Banking Financial Companies Prudential Norms (Reserve Bank) Directions, 1998 issued by the Reserve Bank of India as amended from time to time.
A78: 2.8 | B78: Revenue recognition
B80: Revenues from Interest on loans financed by the company is recognized on accrual basis, considering the directions issued by the Reserve Bank of India from time to time in terms of the Non Banking Financial Companies Prudential Norms (Reserve Bank) Directions, 1998. Loans are classified into 'Performing and Non-Performing' assets in terms of the said Directions.
B81: Revenues from loan documentation and meeting charges are recognised as income on cash basis.
B82: Revenue is recognized to the extent that it is probable that the economic benefits will flow to the Company and the revenue can be reliably measured.
B83: Sale of goods
B84: Sales are recognised, net of returns and trade discounts, on transfer of significant risks and rewards of ownership to the buyer, which generally coincides with the delivery of goods to customers. Sales include excise duty but exclude sales tax and value added tax.
B85: Revenue from interest income on Fixed Deposits with Banks is recognized on time proportion basis taking into account the amount outstanding and the rate applicable.
B86: Sale of goods
B87: Sales are recognised, net of returns and trade discounts, on transfer of significant risks and rewards of ownership to the buyer, which generally coincides with the delivery of goods to customers. Sales include excise duty but exclude sales tax and value added tax.
B89: Income from services
B90: Revenues from contracts priced on a time and Material & Labour basis are recognised when services are rendered and related costs are incurred. Foreseeable losses on such contracts are recognised when probable.
B91: Interest Income on securitisation is recognized on accrual basis.
B93: Dividend Income is recognized when the right to receive is established.
A98: Notes forming part of the financial statements
A100: Note 2 Significant accounting policies (contd.)
A102: Note | B102: Particulars
A105: 2.9 | B105: Other income
B107: Interest income on Bank Deposit is accounted on accrual basis.
B108: Dividend income is accounted for when the right to receive it is established.
A110: =A105+0.1 -> 3 | B110: Tangible fixed assets
B112: Fixed assets, except __ and ___ are carried at cost less accumulated depreciation and impairment losses, if any. The cost of fixed assets includes interest on borrowings attributable to acquisition of qualifying fixed assets up to the date the asset is ready for its intended use and other incidental expenses incurred up to that date. Exchange differences arising on restatement / settlement of long-term foreign currency borrowings relating to acquisition of depreciable fixed assets are adjusted to the cost of the respective assets and depreciated over the remaining useful life of such assets. Machinery spares which can be used only in connection with an item of fixed asset and whose use is expected to be irregular are capitalised and depreciated over the useful life of the principal item of the relevant assets. Subsequent expenditure relating to fixed assets is capitalised only if such expenditure results in an increase in the future benefits from such asset beyond its previously assessed standard of performance. Fixed assets acquired and put to use for project purpose are capitalised and depreciation thereon is included in the project cost till commissioning of the project.
B114: Fixed assets acquired in full or part exchange for another asset are recorded at the fair market value or the net book value of the asset given up, adjusted for any balancing cash consideration. Fair market value is determined either for the assets acquired or asset given up, whichever is more clearly evident. Fixed assets acquired in exchange for securities of the Company are recorded at the fair market value of the assets or the fair market value of the securities issued, whichever is more clearly evident.
B116: The Company revalued all its ___ and ___ that existed on 1 April, 200X. The revalued assets are carried at the revalued amounts less accumulated depreciation and impairment losses, if any. Increase in the net book value on such revaluation is credited to "Revaluation reserve account" except to the extent such increase is related to and not greater than a decrease arising from a revaluation / impairment that was previously recognised in the Statement of Profit and Loss, in which case such amount is credited to the Statement of Profit and Loss. Decrease in book value on revaluation is charged to the Statement of Profit and Loss except where such decrease relates to a previously recognised increase that was credited to the Revaluation reserve, in which case the decrease is charged to the Revaluation reserve to the extent the reserve has not been subsequently reversed / utilised.
B118: Fixed assets retired from active use and held for sale are stated at the lower of their net book value and net realisable value and are disclosed separately in the Balance Sheet.
B120: Capital work-in-progress:
B121: Projects under which assets are not ready for their intended use and other capital work-in-progress are carried at cost, comprising direct cost, related incidental expenses and attributable interest.
A126: Notes forming part of the financial statements
A128: Note 2 Significant accounting policies (contd.)
A130: Note | B130: Particulars
A132: 2.1 | B132: Intangible assets
B134: Intangible assets are carried at cost less accumulated amortisation and impairment losses, if any. The cost of an intangible asset comprises its purchase price, including any import duties and other taxes (other than those subsequently recoverable from the taxing authorities), and any directly attributable expenditure on making the asset ready for its intended use and net of any trade discounts and rebates. Subsequent expenditure on an intangible asset after its purchase / completion is recognised as an expense when incurred unless it is probable that such expenditure will enable the asset to generate future economic benefits in excess of its originally assessed standards of performance and such expenditure can be measured and attributed to the asset reliably, in which case such expenditure is added to the cost of the asset. Refer Note 2.21 for accounting for Research and Development Expenses.
A188: ='[30]Addl Info to the FS'!#REF!+0.01 -> #REF! | B188: Government grants, subsidies and export incentives
B190: Government grants and subsidies are recognised when there is reasonable assurance that the Company will comply with the conditions attached to them and the grants / subsidy will be received. Government grants whose primary condition is that the Company should purchase, construct or otherwise acquire capital assets are presented by deducting them from the carrying value of the assets. The grant is recognised as income over the life of a depreciable asset by way of a reduced depreciation charge.
B191: Export benefits are accounted for in the year of exports based on eligibility and when there is no uncertainty in receiving the same.
B192: Government grants in the nature of promoters' contribution like investment subsidy, where no repayment is ordinarily expected in respect thereof, are treated as capital reserve. Government grants in the form of non-monetary assets, given at a concessional rate, are recorded on the basis of their acquisition cost. In case the non-monetary asset is given free of cost, the grant is recorded at a nominal value. Other government grants and subsidies are recognised as income over the periods necessary to match them with the costs for which they are intended to compensate, on a systematic basis.
A194: =A188+0.01 -> #REF! | B194: Investments
B196: Long-term investments (excluding investment properties), are carried individually at cost less provision for diminution, other than temporary, in the value of such investments. Current investments are carried individually, at the lower of cost and fair value. Cost of investments include acquisition charges such as brokerage, fees and duties. Investment properties are carried individually at cost less accumulated depreciation and impairment, if any. Investment properties are capitalised and depreciated (where applicable) in accordance with the policy stated for Tangible Fixed Assets. Impairment of investment property is determined in accordance with the policy stated for Impairment of Assets.
A198: =2.1 -> 2.1 | B198: Employee benefits
B200: a. Short term employee benefits including salaries, social security contributions, short term compensated absences (such as paid annual leave) where the absences are expected to occur within twelve months after the end of the period in which the employees render the related service, bonuses payable within twelve months after the end of the period in which the employees render the related services and non monetary benefits for current employees are estimated and measured on an undiscounted basis.
B201: Employee benefits include Employees Provident Fund, Gratuity Fund, compensated absences, long service awards and post-employment medical benefits.
B203: b. Defined contribution plans
B204: The Company's contribution to provident fund and superannuation fund are considered as defined contribution plans and are charged as an expense as they fall due based on the amount of contribution required to be made.
B205: Company's contributions paid/payable during the year to Provident Fund and Employee State Insurance are recognised int the Statement of Profit and Loss.
A209: Notes forming part of the financial statements
A211: Note 2 Significant accounting policies (contd.)
A213: Note | B213: Particulars
B215: Short-term employee benefits
B216: The undiscounted amount of short-term employee benefits expected to be paid in exchange for the services rendered by employees are recognised during the year when the employees render the service. These benefits include performance incentive and compensated absences which are expected to occur within twelve months after the end of the period in which the employee renders the related service. The cost of such compensated absences is accounted as under : (a) in case of accumulated compensated absences, when employees render the services that increase their entitlement of future compensated absences; and (b) in case of non-accumulating compensated absences, when the absences occur.
B217: Long-term employee benefits
B218: Compensated absences which are not expected to occur within twelve months after the end of the period in which the employee renders the related service are recognised as a liability at the present value of the defined benefit obligation as at the Balance Sheet date less the fair value of the plan assets out of which the obligations are expected to be settled. Long Service Awards are recognised as a liability at the present value of the defined benefit obligation as at the Balance Sheet date.
A220: =A198+0.01 -> 2.11 | B220: Employee share based payments
B222: The Company has formulated Employee Stock Option Schemes (ESOS) in accordance with the SEBI (Employee Stock Option Scheme and Employee Stock Purchase Scheme) Guidelines, 1999. The Schemes provide for grant of options to employees of the Company and its subsidiaries to acquire equity shares of the Company that vest in a graded manner and that are to be exercised within a specified period. In accordance with the SEBI Guidelines; the excess, if any, of the closing market price on the day prior to the grant of the options under ESOS over the exercise price is amortised on a straight-line basis over the vesting period. [OR]
B223: The Company has constituted an Employee Stock Option Plan - XXXX. Employee Stock Options granted on or after 1 April, 2005 are accounted under the ‘Intrinsic Value Method’ stated in the Guidance Note on Employee Share Based Payments issued by the Institute of Chartered Accountants of India.
A225: =A198+0.01 -> 2.11 | B225: Foreign currency transactions and translations
B227: Transactions in foreign currencies are recorded at the exchange rate prevailing on the date of the transaction. Current assets and liabilities denominated in foreign currency are translated at the rate of exchange as the Balance Sheet date. All resulting gains or losses are recognized in the statement of Profit and Loss.
A231: =A225+0.01 -> 2.12 | B231: Borrowing costs
B233: Borrowing costs include interest, amortisation of ancillary costs incurred and exchange differences arising from foreign currency borrowings to the extent they are regarded as an adjustment to the interest cost. Costs in connection with the borrowing of funds to the extent not directly related to the acquisition of qualifying assets are charged to the Statement of Profit and Loss over the tenure of the loan. Borrowing costs, allocated to and utilised for qualifying assets, pertaining to the period from commencement of activities relating to construction / development of the qualifying asset upto the date of capitalisation of such asset is added to the cost of the assets. Capitalisation of borrowing costs is suspended and charged to the Statement of Profit and Loss during extended periods when active development activity on the qualifying assets is interrupted.
A235: =A231+0.01 -> 2.13 | B235: Segment reporting
B237: The Company provides only Engineering & Constructin Services and does not have any other segment of business. So the Segmental reporting regulations are not applicable to the company.
B238: The Company identifies primary segments based on the dominant source, nature of risks and returns and the internal organisation and management structure. The operating segments are the segments for which separate financial information is available and for which operating profit/loss amounts are evaluated regularly by the executive Management in deciding how to allocate resources and in assessing performance.
A242: Notes forming part of the financial statements
A244: Note 2 Significant accounting policies (contd.)
A246: Note | B246: Particulars
B248: The accounting policies adopted for segment reporting are in line with the accounting policies of the Company. Segment revenue, segment expenses, segment assets and segment liabilities have been identified to segments on the basis of their relationship to the operating activities of the segment. Inter-segment revenue is accounted on the basis of transactions which are primarily determined based on market / fair value factors. Revenue, expenses, assets and liabilities which relate to the Company as a whole and are not allocable to segments on reasonable basis have been included under “unallocated revenue / expenses / assets / liabilities”.
A250: 2.18 | B250: Leases
...

Sheet Sheet5

Sheet bS TALLY
A1: SEIL 12TO19
A2: Balance Sheet
A3: 1-Apr-2020 to 31-Mar-2021
B4: SEIL 12TO19 | E4: SEIL 12TO19
A5: Liabilities | B5: as at 31-Mar-2021 | D5: Assets | E5: as at 31-Mar-2021
A6: Capital Account | C6: 7147460 | D6: Fixed Assets | F6: 54365518
A7: SHARE CAPITAL | B7: 7147460 | D7: BUILDINGS | E7: 868251
A8: Loans (Liability) | D8: Camera
A9: Current Liabilities | C9: 17134887 | D9: COMPUTER | E9: 882128.8
A10: Crs. for Other Liabilities | D10: FURNITURE AND FITTINGS | E10: 34086.35
A11: Service Tax Payable | D11: LAND
A12: STAFF DEPOSIT | D12: Plant & Machinery | E12: 48499895 | I12: =F6-Dep_Co!K26 -> 46145692
A13: Sundry Creditors | B13: 16729475 | D13: Vehicle | E13: 4081157.5
A14: Crs. for I.T | D14: Current Assets | F14: 95381639
A15: Apex Topomappers Pvt Ltd | D15: Closing Stock
A16: Audit Fees Payable | D16: Deposits (Asset)
A17: Dividend Payable | D17: Loans & Advances (Asset) | E17: 22168775
A18: Dividend Tax Payable | D18: Sundry Debtors | E18: 58880461
A19: Lakhdata SD | B19: 78862 | D19: Cash-in-hand | E19: 203185.75
A20: Loyyal Battery Service | D20: Bank Accounts | E20: 6855741.8
A21: Provision for Income Tax -II | D21: Interest Receivable | E21: 7273476
A22: SECURITY DEPOSIT | B22: 294347 | D22: Vijay Gowtham Mob.Adv
A23: Vijay Gowtham SD | B23: 32203.14 | D23: Branch / Divisions | F23: 7983555.9
A24: CONTRACT ADVANCE | C24: 10969671 | D24: 21 Sugar Site
A25: CHAITANESWAR SSK - CA | B25: 30000 | D25: Aarthi Indusries II Site
A26: CHITTOOR CO-OP C.ADV | B26: 230500 | D26: Aarthi Industries Site
A27: Contract Advance | B27: 10589171 | D27: ABG Site
A28: MRUDAGIRI SSK LTD C.ADV | B28: 120000 | D28: Abhijeet III Site
A29: DEFERRED TAX LIABILITY C.L | C29: 1517336.2 | D29: Abhijeet II Site | E29: -201
A30: DEFERRED TAX LIABILITY C.L | B30: 1517336.2 | D30: Abhijeet IV SITE
A31: DIRECTORS LOAN A/C | C31: 4389286 | D31: Abhijeet Site
A32: Kumaran.S Dir - Loan | B32: 4431105 | D32: Acon (Lokmaniya Sugar) Site | E32: -34050
A33: Niranjan - S.Holder | D33: Ala Dandapani Cement II Site | E33: -1544
A34: RAJATHILAGAM.S Dir.Loan | D34: Ala Dandapani Cement Site
A35: Ramalingam.V Dr. S.H | D35: Alagu Jothi Arch Work Site
A36: SATHIAPAL.S. D. LOAN | D36: Alagu Jothi Existing Work Site
A37: Sugunthakumari.R - S.Holder | D37: Alagu Jothi Foot Path Site | E37: -2
A38: Suhashini K -Dir Loan | B38: -4127 | D38: Alagu Jothi II Site
A39: Visalakshi .K- Dir Loan | B39: -37692 | D39: Ambuja Cement Site
A40: GST | C40: 7512923 | D40: Amirthakadeswarar Gurukkal Site
A41: Andra CGST | B41: 3735472 | D41: Anrak Aluminium II Site
A42: Andra SGST | B42: 1607210 | D42: Anrak Aluminium Site
A43: Chattishgarh CGST | B43: 345891.13 | D43: AP Bava (JK) Site | E43: 2500
A44: Chattishgarh SGST | B44: 262664.13 | D44: AP Bava (KCP) Site
A45: GST | B45: -41631236 | D45: A.R.S.Metal Site
A46: Gujarat CGST | B46: 4764980.5 | D46: ATC Tires Pvt Ltd Site | E46: 1300
A47: Gujarat SGST | B47: 4517586.8 | D47: ATC Tires Vizag (21-22) Site
A48: Haryana CGST | D48: ATG Site
A49: Haryana SGST | D49: Athani Sugars Site
A50: Jharkhand CGST | B50: 1591245.4 | D50: AVC ADD. CLASS ROOM SITE | E50: -800
A51: Jharkhand SGST | B51: 1725807.4 | D51: AVC Charities Site
A52: Karnataka CGST | B52: 1027159.7 | D52: AVC Commercial Building Site | E52: 23043
A53: Karnataka SGST | B53: 947299.67 | D53: AVC Diamond Jubliee Site
A54: Maharastra CGST | B54: 279269.47 | D54: AVC Kalyana Mandapam Site
A55: Maharastra SGST | B55: 165466.47 | D55: Avc Ladies Toilet Site
A56: MP CGST | B56: 872480.59 | D56: AVC MBA BLOCK SITE | E56: 2727
A57: MP SGST | B57: 621845.59 | D57: Avc Multi Purpose Hall Site
A58: Odisha CGST | B58: 372817.42 | D58: Avc NRI Student Room Site
A59: Odisha SGST | B59: 519470.42 | D59: Avc Polytechnic College Site
A60: Rajasthan CGST | B60: 307632.08 | D60: Avc Sports Gallery Site
A61: Rajasthan SGST | B61: 262850.08 | D61: Avc Toilet Block Site
A62: Telangana CGST | B62: 3446592.8 | D62: AVC Womens Hostel Site
A63: Telangana SGST | B63: 3232180.8 | D63: Axon Constructions (Rkm) Site
A64: TNCGST | B64: 8709091.2 | D64: Ayyakannu House Site
A65: TNSGST | B65: 9386743 | D65: Bajaj Hindusthan Site
A66: UP CGST | B66: 257645.64 | D66: Baliraja Site
A67: UP SGST | B67: 184756.64 | D67: Bhubaneshwar Power Site
A68: Uttarkhand CGST | D68: Bhubaneswar Silo Site | E68: 45000
A69: Uttarkhand SGST | D69: Birla Corporation Ltd Site
A70: West Bengal CGST | D70: Buildmet (Novoco) Site
A71: West Bengal SGST | D71: CCCL Dhachepalli Site
A72: RESERVES AND SURPLUS | C72: 2.5803356e+08 | D72: Cccl Kallur Site
A73: Dividend Paid - (11-12) | B73: -108998765 | D73: CCCL-Karikali Chimney II Site
A74: Dividend Tax Paid (11-12) | B74: -18382929 | D74: CCCL - Karikali Site
A75: GENERAL RESERVE | B75: 44374031 | D75: CCCL - SOLAPUR II SITE
A76: RESERVES & SURPLUS | B76: 3.4104122e+08 | D76: CCCL-Solapur Site
A77: SECURED LOAN | D77: CCCL-Vizag Site | E77: 579004.5
A78: UNSECURED LOAN | D78: CHENNAI OFFICE | E78: 9410.25
A79: Rent Advance - Coral | D79: Chidambaram Apartment Site
A80: Profit & Loss A/c | C80: 14513616 | D80: Coromandal (Ramco Ariyalur) Site
A81: Opening Balance | B81: 5.71 | D81: Coromandal (Ramco) Site
A82: Current Period | B82: 14513610 | D82: Coromandal Simon Site
D83: Coromandal Sugar Site
D84: Coromandal -Ultra Tech Site
D85: CREW Ltd Site
D86: Cvl - Abg Surat Site
D87: Cvl - Aryan Site
D88: CVL-Meghmani II Site
D89: Daac Addtional C.W. Site | E89: 5875
D90: DAAC Compound Wall Site | E90: 6924
D91: DAAC Cycle Stand Site | E91: -41010
D92: DAAC Site
D93: Dalmia Cement 2020 Site | E93: 312318
D94: Deepak Phenolics Ltd Site
D95: EID Parry Karnataka Site | E95: 278364
D96: EID Parry Site
D97: Electrotherm III Site
D98: ELECTRO THERM II SITE
D99: Enmas (ITC ) Site
D100: Essar NLC Site
...

Sheet PL TALLY
A1: SEIL 12TO19
A2: Profit & Loss A/c
A3: 1-Apr-2020 to 31-Mar-2021
B4: SEIL 12TO19 | E4: SEIL 12TO19
A5: Particulars | B5: 1-Apr-2020 to 31-Mar-2021 | D5: Particulars | E5: 1-Apr-2020 to 31-Mar-2021
A6: Purchase Accounts | C6: 81386421 | D6: Contracts | F6: 2.5646036e+08
A7: 10 MM CHIPS | B7: 963570 | D7: CONTRACT RECEIPTS
A8: 10 MM METAL | B8: 1850 | D8: Contract Receipts A/c | E8: 2.5646036e+08
A9: Asbestos Materials | B9: 777374 | D9: RMC Sales
A10: Aviation Lamp and Accessories | B10: 2012050 | D10: WIP | F10: 13800000
A11: BOLTS & NUTS | B11: 724656 | D11: WIP | E11: 13800000
A12: C.I CAP | B12: 1658846 | E12: 2.7026036e+08
A13: FIRE BRICKS | B13: 8355016 | D13: Gross Profit b/f | F13: 60277837
A14: G.I Materials | B14: 961150 | D14: Indirect Incomes | F14: 5656621
A15: Purchase | B15: -17000000 | D15: Divdend
A16: R.R. Stone | D16: Dividend
A17: Safety Materials | B17: 1702563.1 | D17: INTEREST RECEIVED on FD | E17: 5656621
A18: Soling Stone | D18: Misc.Income
A19: SS CONE | B19: 158686 | D19: Other Income
A20: Store Materials | D20: Rent Received
A21: Water for Construction
A22: Water for Contruction
A23: 12 MM Metal | B23: 1103189
A24: 20 MM METAL | B24: 3885646
A25: 40 MM METAL | B25: 45800
A26: 6 mm Metal | B26: 31385
A27: Binding Wire | B27: 831045
A28: BRICKS | B28: 625168
A29: CEMENT | B29: 5856138
A30: Consumables | B30: 4499387.9
A31: Electrical Materials | B31: 2677466.4
A32: Misc Materials | B32: 4390
A33: Painting Materials | B33: 3733599.7
A34: Petrol Diesel & Grease | B34: 363941.3
... A43: Windows & Doors | B43: 444871
A44: Direct Expenses | C44: 1.285961e+08
A45: WAGES | B45: 96190536
A46: WORKS EXPENSES | B46: 32405569
A47: Gross Profit c/o | C47: 60277837
B48: 2.7026036e+08
A49: DEFERRED TAX LIABILITY P.L
A50: DEFERRED TAX LIABILITY P.L
A51: DEPRECIATION
A52: DEPRECIATION
A53: Dividend Paid
A54: Dividend Tax
A55: Fringe Benefit Tax
A56: INCOME TAX | C56: 1680569
A57: INCOME TAX P.L | B57: 1680569
A58: Preliminary Expenses Written Off
A59: RESERVES & SURPLUS P&L
A60: RESERVES & SURPLUS P&L
A61: Short Provision Made
A62: Short Provision Made
A63: Indirect Expenses | C63: 49740279
A64: RATES & TAXES
A65: INTEREST PAID | B65: 30414
A66: ADVERTISMENT | B66: 23373
A67: AMC Charges | B67: 59870
A68: AUDIT FEES | B68: 632560
A69: BAD DEBTS
A70: Bonus | B70: 9350
A71: BOOKS & PERIODICALS | B71: 5720
A72: Building Maintenance
A73: CGST Late Fee& Interest | B73: 9255
A74: CONCRETE PUMP HIRE & MAINTENANCE
A75: CSR Donation
A76: D.G HIRE AND MAINTANANCE
A77: DIRECTORS REMUNERATION | B77: 3677400
A78: ELECTRICAL MAINTENANCE | B78: 1770
A79: Godown Rent | B79: 204000
A80: Group Gratuity Scheme
A81: GTA SERVICE TAX
A82: Incometax Exp
A83: I.T.Interest
A84: Labour Licence | B84: 35320
A85: Labour/staff Welfare (MVM) | B85: 15566
A86: Loss on Sale of Vehicle
A87: Marketing Expenses | B87: 35143
A88: MISC - EXPENSES H.O | B88: 78386
A89: Misc Expenses (MVM) | B89: 24105
A90: Professional Tax | B90: 7500
A91: Rates & Taxs
A92: Registrtion & Approval Exp
A93: Round Off A/c
A94: Salaries & Wages H.O | B94: 31121070
A95: SGST Late Fee& Interest | B95: 7755
A96: Sriram Safety @Quality Management Pvt Ltd
A97: STAFF WELFARE - H.O | B97: 43709
A98: TRAVELLING AND CONVEYANCE | B98: 1554027
A99: VEHICLE MAINTENANCE | B99: 758262
A100: W.C.TAX | B100: -85000
A101: BANK CHARGES | B101: 111110.01
A102: Donation | B102: 455351
A103: Electricity Charges | B103: 179942
A104: Insurance | B104: 1514584.6
A105: Local Conveyance | B105: 779650
A106: OFFICE MAINTENANCE | B106: 63496
A107: POOJA EXPENSES | B107: 333770
A108: Postage & Telephones | B108: 516304.27
...

Sheet TDS
A1: 194A | B1: =57686+63576+495539 -> 616801
A2: 194C | B2: =190527+37558+26000+25100+30560+156888+286644+1127939+33333+262987+166405+119680+225000+223860+215957+107525+82531+188700+52100+1973805.63 -> 5533099.6 | D2: AVC COLLEGE OF ENGINEERING
A3: 194IA | B3: =50749 -> 50749
B4: =SUM(B1:B3) -> 6200649.6 | C4: 6236242.6 | D4: =B4-C4 -> -35593 | E4: 6219807.6 | F4: =B4-E4 -> -19158 | H4: ICICI KILPAUK | I4: 140064.47
A5: ADVANCE TAX | B5: =1248000+832000+1101885+260000+1040000+572000+1040000+824000 -> 6917885 | H5: KELLYS I | I5: 24337.5
A6: SRR PROJECTS | H6: KELLYS II | I6: CLOSED | L6: gross
A7: TALLY | B7: 26AS | C7: DIFF | H7: SBI KILPAUK I | I7: 13975118 | J7: 26Q | K7: Q1 | L7: 902151 | M7: 182202 | N7: 24Q | O7: 184935
A8: =25463+53300+31182+12083+5475 -> 127503 | B8: 50749 | C8: =A8-B8 -> 76754 | H8: SBI KILPAUK II | I8: 2540565.2 | J8: 26Q | K8: Q2 | L8: 1123085 | M8: 47084
A9: HAJEE AP BAVA INFRA | H9: SBI KILPAUK III | I9: 2885227.5 | K9: Q3
A10: =25873+116137+7260+7751+7751+25755 -> 190527 | B10: =25873+116137+7751+7751+7260+25755 -> 190527
A11: MRN CANE POWER
A12: =13500+13500+6372+1000+3186 -> 37558 | B12: =1000+9558+27000 -> 37558
A13: SRI MARUTHI POWER GEN
A14: =20000+6000 -> 26000 | B14: =6000+20000 -> 26000
A15: ARTHI INDUSTRIES LIMITED
A16: =25100 -> 25100 | B16: =25100 -> 25100
A17: DEEPAK PHENOLICS
A18: 30560 | B18: =30560 -> 30560
A19: AVC COLLEGE OF ENGG
A20: =78706+16678+9856+8475+19830+6780+10169+20339+20102+9949+20339+19932+821+20339+820+20339+8475+28814+821+20000+24000 -> 365584 | B20: =78706+42289+10529+25364+286644 -> 443532 | C20: =A20-B20 -> -77948
A21: CHETTINAD CEMENT
A22: =107110+98111+47349+78318+93679+20980+11128+286350+91594+136037+78716+78567 -> 1127939 | B22: =107110+78567+98111+11128+47349+171997+20980+286350+78716+91594+136037 -> 1127939 | C22: =A22-B22 -> 0
A23: R VENKATESH
A24: =9217+7674+8816+7626 -> 33333 | B24: =9217+7674+8816+3626+4000 -> 33333
A25: COROMANDEL ENGINEERING
A26: =47657+33974+29755+77976+47919+25706 -> 262987 | B26: =262987 -> 262987
A27: JINDAL URBAN
A28: =80086+38750+23236+24333 -> 166405 | B28: =166405 -> 166405
A29: GODAVARI POLYMERS
A30: =29920+29920+59840 -> 119680 | B30: =119680 -> 119680
A31: SAGAR CEMENTS
A32: =37500+25000+25000+25000+12500+12500+12500+12500+12500+12500+37500 -> 225000 | B32: =225000 -> 225000 | C32: =B32-A32 -> 0
A33: INDIA CEMENTS
A34: =73860+150000 -> 223860 | B34: =223860 -> 223860
A35: GOEL
A36: =43259+30000+15129+31692+43991+15144+20643+16099 -> 215957 | B36: =215957 -> 215957
A37: ATC TYRES
A38: =12650+12650+25300+25300+31625 -> 107525 | B38: 107525
A39: RAY ENGG
A40: =30786+32345+19400 -> 82531 | B40: 82531
A41: 21 SUGARS
A42: =44400+44400+33300+44400+22200 -> 188700 | B42: =188700 -> 188700
A43: KHATAV
A44: =13030+6128 -> 19158 | B44: =52100 -> 52100 | C44: =A44-B44 -> -32942
A45: SANGHII
A46: =73233+25639+324338+535748+69729+231018+205529+202139+13938.6+174682+54853+132688 -> 2043534.6 | B46: 1973805 | C46: =A46-B46 -> 69729.6 | D46: 43476
A49: =SUM(A8:A46) -> 5619441.6 | B49: =SUM(B8:B46) -> 5583848 | C49: =SUM(C8:C46) -> 35593.6

Sheet consolidated tb 18-19
A1: Trial Balance
B2: Debit | C2: Credit | D2: Debit | E2: Credit
A3: Capital Account | E3: 7147460
A4: Share Capital | E4: 7147460
A5: Current Liabilities | B5: 737524 | C5: 2055676.5 | D5: 9078788.5 | E5: 11063897
A6: Sundry Creditors | B6: 737524 | C6: 2055676.5 | D6: 4825462.5 | E6: 10658485 | F6: =E6+C6-D6-B6 -> 7151174.6
A7: Crs.for Expenses | C7: 162950 | D7: 1125045 | E7: 4555540.9 | F7: =E7+C7-D7 -> 3593445.9
A8: A John Moris & Co | E8: 938288.93 | F8: =B8+C8+D8+E8 -> 938288.93 | G8: cr
A9: Aurobindo Business Machines | E9: 12154 | F9: =B9+C9+D9+E9 -> 12154 | G9: cr
A10: BUSINESS ACCOUNTING SOLUTION | E10: 8000 | F10: =B10+C10+D10+E10 -> 8000 | G10: cr
A11: HARIPRASAD ASSOCIATES | D11: 500045 | F11: =B11+C11+D11+E11 -> 500045 | G11: dr
A12: Janu Engg Works | C12: 144197 | F12: =B12+C12+D12+E12 -> 144197 | G12: cr
A13: J.S.Metal Graft (Jeevanatham) | C13: 3845 | F13: =B13+C13+D13+E13 -> 3845 | G13: dr
A14: KB Mehta Construction Pvt Ltd | D14: 100000 | F14: =B14+C14+D14+E14 -> 100000 | G14: dr
A15: Mesha | E15: 21700 | F15: =B15+C15+D15+E15 -> 21700 | G15: cr
A16: N.K.BHANSALI & CO | D16: 525000 | F16: =B16+C16+D16+E16 -> 525000 | G16: dr | H16: =39821-14815-14820 -> 10186
A17: OUTSTANDING DIRECTORS REMUNERATION | E17: 300647 | F17: =B17+C17+D17+E17 -> 300647 | G17: cr
A18: P.F.PAYABLE | E18: 393093 | F18: =B18+C18+D18+E18 -> 393093 | G18: cr
A19: Print Park | E19: 9924 | F19: =B19+C19+D19+E19 -> 9924 | G19: cr
A20: RENT PAYABLE | E20: 107343 | F20: =B20+C20+D20+E20 -> 107343 | G20: cr
A21: SALARY PAYABLE | E21: 2196990 | F21: =B21+C21+D21+E21 -> 2196990 | G21: cr
A22: Sri Amman Lath Works | E22: 40260 | F22: =B22+C22+D22+E22 -> 40260 | G22: cr
A23: TDS PAYABLE | C23: 14908 | E23: 527141 | F23: =B23+C23+D23+E23 -> 542049 | G23: cr
A24: Crs.for Purchase | B24: 498136 | C24: 1091393.5 | D24: 675527.7 | E24: 3004364.3 | F24: =E24+C24-D24-B24 -> 2922094.1
A25: Abirami Electricals | C25: 145553 | E25: 52435 | F25: =B25+C25+D25+E25 -> 197988 | G25: cr
A26: Acme Safetywears Ltd | E26: 79379 | F26: =B26+C26+D26+E26 -> 79379 | G26: cr
A27: Agar Engineers Pvt Ltd | E27: 74222 | F27: =B27+C27+D27+E27 -> 74222 | G27: cr
A28: Ambika Enterprises | B28: 240000 | F28: =B28+C28+D28+E28 -> 240000 | G28: dr
A29: Amman Motor Pipes | C29: 120354 | E29: 53650 | F29: =B29+C29+D29+E29 -> 174004 | G29: cr
A30: Bapu's Autotrade | D30: 9399 | F30: =B30+C30+D30+E30 -> 9399 | G30: dr
A31: B.Mangatram & Co | D31: 7727 | F31: =B31+C31+D31+E31 -> 7727 | G31: dr
A32: Chennai Steeel Company | E32: 386073 | F32: =B32+C32+D32+E32 -> 386073 | G32: cr
A33: Chennai Steel Company | C33: 7610 | F33: =B33+C33+D33+E33 -> 7610 | G33: cr
A34: Chettinad Cement Corpn Pvt Ltd | B34: 37250 | F34: =B34+C34+D34+E34 -> 37250 | G34: dr
A35: Chinnappa Chettiar & Sons | E35: 23128 | F35: =B35+C35+D35+E35 -> 23128 | G35: cr
A36: Delton Pneumatics | E36: 107676 | F36: =B36+C36+D36+E36 -> 107676 | G36: cr
A37: Dharani Hi Tech Project Pvt Ltd | B37: 31100 | F37: =B37+C37+D37+E37 -> 31100 | G37: dr
A38: Dynamic Prestress (I) Pvt Ltd Plant III | D38: 28642 | F38: =B38+C38+D38+E38 -> 28642 | G38: dr
A39: Fakhri Fasteners | E39: 46263 | F39: =B39+C39+D39+E39 -> 46263 | G39: cr
A40: Forestree India Pvt Ltd. | E40: 187186 | F40: =B40+C40+D40+E40 -> 187186 | G40: cr
A41: Fortune Building System (P) Ltd | C41: 81788 | F41: =B41+C41+D41+E41 -> 81788 | G41: cr
A42: Hogg Hydraulics | E42: 754278.5 | F42: =B42+C42+D42+E42 -> 754278.5 | G42: cr
A43: Hyderi Enterprises | E43: 300 | F43: =B43+C43+D43+E43 -> 300 | G43: cr
A44: Indian Trading Company | E44: 468104.5 | F44: =B44+C44+D44+E44 -> 468104.5 | G44: cr
A45: Krishna Sales Corporation | E45: 79364 | F45: =B45+C45+D45+E45 -> 79364 | G45: cr
A46: Lawrence & Mayo India Pvt Ltd | E46: 3245 | F46: =B46+C46+D46+E46 -> 3245 | G46: cr
A47: Maniam Traders | D47: 1175 | F47: =B47+C47+D47+E47 -> 1175 | G47: dr
A48: MSR | C48: 39750.53 | E48: 19148.35 | F48: =B48+C48+D48+E48 -> 58898.88 | G48: cr
A49: Navkar Plyhome | C49: 20810 | F49: =B49+C49+D49+E49 -> 20810 | G49: dr
A50: NKM AGENCIES | D50: 2200 | F50: =B50+C50+D50+E50 -> 2200 | G50: dr
A51: N.MOHAMED KASIM (HO) | E51: 196558 | F51: =B51+C51+D51+E51 -> 196558 | G51: cr
A52: Om Enterprises | E52: 3200 | F52: =B52+C52+D52+E52 -> 3200 | G52: cr
A53: Prasad Multi Service Pvt Ltd | E53: 58399 | F53: =B53+C53+D53+E53 -> 58399 | G53: cr
A54: PSR Tiles Park | C54: 15495 | F54: =B54+C54+D54+E54 -> 15495 | G54: cr
A55: Rangoli Multi Stores | E55: 30444 | F55: =B55+C55+D55+E55 -> 30444 | G55: cr
A56: R & R Paints | E56: 57328 | F56: =B56+C56+D56+E56 -> 57328 | G56: cr
A57: R.S.Paints & Hardwares | C57: 35130 | E57: 22226 | F57: =B57+C57+D57+E57 -> 57356 | G57: cr
A58: SAKTHI ENGINEERS | D58: 6866.7 | F58: =B58+C58+D58+E58 -> 6866.7 | G58: dr
A59: Santhi Plylam & Decors | D59: 7000 | F59: =B59+C59+D59+E59 -> 7000 | G59: dr
A60: Santlal Balkishan Dass (Madras) | E60: 11875 | F60: =B60+C60+D60+E60 -> 11875 | G60: cr
A61: Schwing Stetter India Pvt Ltd | E61: 293 | F61: =B61+C61+D61+E61 -> 293 | G61: cr
A62: Senthil Traders | C62: 5700 | F62: =B62+C62+D62+E62 -> 5700 | G62: cr
A63: Shanmugam & Co | B63: 105236 | F63: =B63+C63+D63+E63 -> 105236 | G63: dr
A64: Sri Jayadurga Power Tools | E64: 8860 | F64: =B64+C64+D64+E64 -> 8860 | G64: cr
A65: Srinivash Timbers | C65: 1959 | F65: =B65+C65+D65+E65 -> 1959 | G65: cr
A66: Sri Vardaman Tiles | C66: 5030 | F66: =B66+C66+D66+E66 -> 5030 | G66: cr
A67: Stroke Equipments India Pvt Ltd | E67: 11211 | F67: =B67+C67+D67+E67 -> 11211 | G67: cr
A68: Suryadev Alloys & Power Pvt Ltd | C68: 566851 | D68: 612518 | F68: =D68-C68 -> 45667 | G68: dr
A69: Surya Tiles & Granities | B69: 84550 | F69: =B69+C69+D69+E69 -> 84550 | G69: dr
A70: Thermal Scientific Works | E70: 861.15 | F70: =B70+C70+D70+E70 -> 861.15 | G70: cr
A71: TIRUSUL WIRE ROPE & LIFTING GEARS PVT LTD | E71: 151411 | F71: =B71+C71+D71+E71 -> 151411 | G71: cr
A72: Universal Sales Corporation AHM | E72: 12390 | F72: =B72+C72+D72+E72 -> 12390 | G72: cr
A73: Vaigai Sanitation | C73: 45363 | F73: =B73+C73+D73+E73 -> 45363 | G73: cr
A74: Veena Electricals | E74: 15486 | F74: =B74+C74+D74+E74 -> 15486 | G74: cr
A75: Vijay Enterprise | E75: 89369.8 | F75: =B75+C75+D75+E75 -> 89369.8 | G75: cr
A76: Crs.for Sub Contractors | B76: 239388 | C76: 580936 | D76: 3024889.8 | E76: 982354.93 | F76: =D76+B76-E76-C76 -> 1700986.9 | G76: dr | H76: 1700986.9
A77: AKILESH - SUB | D77: 80376 | F77: =B77+C77+D77+E77 -> 80376 | G77: dr
A78: Anbuchezhian - Sub | C78: 26927 | F78: =B78+C78+D78+E78 -> 26927 | G78: cr
A79: Anil Singh - Mason | D79: 115613 | F79: =B79+C79+D79+E79 -> 115613 | G79: dr
A80: AVS Buildheight Pvt Ltd | D80: 252828 | F80: =B80+C80+D80+E80 -> 252828 | G80: dr
A81: Awadesh Kumar - Sub | E81: 28377 | F81: =B81+C81+D81+E81 -> 28377 | G81: cr
A82: Balu Carp | C82: 12448 | F82: =B82+C82+D82+E82 -> 12448 | G82: cr
A83: Baskar - Mason | C83: 65063 | F83: =B83+C83+D83+E83 -> 65063 | G83: cr
A84: CHUNI LAL -SUB SANGHI.II | D84: 6260 | F84: =B84+C84+D84+E84 -> 6260 | G84: dr
A85: Damodar Dalai - Sub | D85: 4760 | F85: =B85+C85+D85+E85 -> 4760 | G85: dr
A86: Dynamic Prestress Projects & Service Pvt Ltd | D86: 405106.3 | F86: =B86+C86+D86+E86 -> 405106.3 | G86: dr
A87: Elayaraja - Sub | C87: 5785 | F87: =B87+C87+D87+E87 -> 5785 | G87: cr
A88: Gopal Kannan-Sub | E88: 3114 | F88: =B88+C88+D88+E88 -> 3114 | G88: cr
A89: Gyani Prasad - Sub | D89: 5480 | F89: =B89+C89+D89+E89 -> 5480 | G89: dr
A90: Haresh Sankarlal Joshi - Sub | D90: 191700 | F90: =B90+C90+D90+E90 -> 191700 | G90: dr
A91: Jayakumar - Sub | C91: 28778 | F91: =B91+C91+D91+E91 -> 28778 | G91: cr
A92: Karunanidi - Sub | C92: 28091 | F92: =B92+C92+D92+E92 -> 28091 | G92: cr
A93: Krishnasamy.M - Sub | E93: 8965 | F93: =B93+C93+D93+E93 -> 8965 | G93: cr
A94: Kumaresan - Sub | B94: 16590 | F94: =B94+C94+D94+E94 -> 16590 | G94: dr
A95: Kumar - Painter | C95: 2857 | F95: =B95+C95+D95+E95 -> 2857 | G95: cr
A96: Linga Reddy T.V. - Sub | D96: 292419 | F96: =B96+C96+D96+E96 -> 292419 | G96: dr
A97: Mahendra Bari-Sub | E97: 7808 | F97: =B97+C97+D97+E97 -> 7808 | G97: cr
A98: Manickam.K - Fitter | C98: 18445 | F98: =B98+C98+D98+E98 -> 18445 | G98: cr
A99: MANI-PAINTER | C99: 135879 | F99: =B99+C99+D99+E99 -> 135879 | G99: cr
A100: Mohan - Tile Layer | C100: 34896 | F100: =B100+C100+D100+E100 -> 34896 | G100: cr
...

Sheet Sheet3
B1: SEIL 12TO19
B2: Trial Balance
B3: 1-Apr-2017 to 31-Mar-2018
C4: SEIL 12TO19
B5: Particulars | C5: 1-Apr-2017 to 31-Mar-2018
C6: Closing Balance
C7: Debit | D7: Credit | M7: depreciation
B8: Capital Account | D8: 7147460 | M8: audit fees payable
B9: SHARE CAPITAL | D9: 7147460 | M9: Bhansali TDS
B10: Current Liabilities | C10: 7242945 | D10: 12860905 | M10: lic
B11: Crs. for Other Liabilities | M11: Nandakumar -Suspense
B12: Sundry Creditors | C12: 7242945 | D12: 12455493 | M12: Contract receipt-AVC and tirunandal
B13: CRS FOR EXPENSES | C13: 889138 | D13: 4263548.9
A14: OCL EXPPAY | B14: Air Tours & Travels | D14: 16 | E14: =-D14 -> -16 | F14: Other current liabilities-Expenses payable
A15: AFPAY | B15: AJOHN MORIS & CO | D15: =468288.93+412000 -> 880288.93 | E15: =-D15 -> -880288.93 | F15: Audit fees payable
A16: OCL EXPPAY | B16: Amman Earth Movers (MVM) | D16: 4202 | E16: =-D16 -> -4202 | F16: Other current liabilities-Expenses payable
A17: OCL EXPPAY | B17: G.L.Associate | D17: 900 | E17: =-D17 -> -900 | F17: Other current liabilities-Expenses payable
A18: OCL EXPPAY | B18: Hi-Tech Calibration Services | D18: 24150 | E18: =-D18 -> -24150 | F18: Other current liabilities-Expenses payable
A19: OCL EXPPAY | B19: Hitech Concrete Solution Chennai Pvt Ltd | D19: 46383 | E19: =-D19 -> -46383 | F19: Other current liabilities-Expenses payable
A20: OCL EXPPAY | B20: Interest Payable | D20: 12864 | E20: =-D20 -> -12864 | F20: Other current liabilities-Expenses payable
A21: STLA OADV | B21: JANNU ENGG.WORKS | C21: 47780 | E21: =C21 -> 47780 | F21: Short Term Loans and Advances - Other Advance
A22: OCL EXPPAY | B22: Janu Engg Works | D22: 5439 | E22: =-D22 -> -5439 | F22: Other current liabilities-Expenses payable
A23: OCL EXPPAY | B23: Jayam Engineering Works | D23: 1330 | E23: =-D23 -> -1330 | F23: Other current liabilities-Expenses payable
A24: OCL EXPPAY | B24: K K Enterprises | D24: 182380 | E24: =-D24 -> -182380 | F24: Other current liabilities-Expenses payable
A25: OCL EXPPAY | B25: KSR Generators | D25: 35000 | E25: =-D25 -> -35000 | F25: Other current liabilities-Expenses payable
A26: OCL EXPPAY | B26: LIC | D26: 252786 | E26: =-D26 -> -252786 | F26: Other current liabilities-Expenses payable
A27: OCL EXPPAY | B27: Manish Srivastava | D27: 17000 | E27: =-D27 -> -17000 | F27: Other current liabilities-Expenses payable
A28: OCL EXPPAY | B28: Mesha | D28: 111200 | E28: =-D28 -> -111200 | F28: Other current liabilities-Expenses payable
A29: STLA OADV | B29: N.K.BHANSALI & CO | C29: 450000 | E29: =C29 -> 450000 | F29: Short Term Loans and Advances - Other Advance
A30: OCL EXPPAY | B30: OUTSTANDING DIRECTORS REMUNERATION | D30: 404615 | E30: =-D30 -> -404615 | F30: Other current liabilities-Expenses payable
A31: OCL PFPAY | B31: P.F.PAYABLE | D31: 340410 | E31: =-D31 -> -340410 | F31: Other current liabilities-Expenses payable
A32: OCL EXPPAY | B32: Print Park | D32: 19833 | E32: =-D32 -> -19833 | F32: Other current liabilities-Expenses payable
A33: OCL EXPPAY | B33: Raghubhai D Chomal | D33: 20000 | E33: =-D33 -> -20000 | F33: Other current liabilities-Expenses payable
A34: STLA OADV | B34: Ramana M-CCCL Dhachepalli | C34: 300000 | E34: =C34 -> 300000 | F34: Short Term Loans and Advances - Other Advance
A35: OCL EXPPAY | B35: RENT PAYABLE | D35: 48834 | E35: =-D35 -> -48834 | F35: Other current liabilities-Expenses payable
A36: STLA OADV | B36: Sakthi Engineering Services | C36: 38738 | E36: =C36 -> 38738 | F36: Short Term Loans and Advances - Other Advance
A37: OCL EXPPAY | B37: SALARY PAYABLE | D37: 1835922 | E37: =-D37 -> -1835922 | F37: Other current liabilities-Expenses payable
A38: OCL EXPPAY | B38: Shri Electricals | D38: 19815 | E38: =-D38 -> -19815 | F38: Other current liabilities-Expenses payable
A39: OCL EXPPAY | B39: S.N.Mittal & Associates | D39: 5700 | E39: =-D39 -> -5700 | F39: Other current liabilities-Expenses payable
A40: STLA OADV | B40: S.R.COMPUTERS | C40: 13000 | E40: =C40 -> 13000 | F40: Short Term Loans and Advances - Other Advance
A41: STLA OADV | B41: Sri Amman Lath Works | C41: 39620 | E41: =C41 -> 39620 | F41: Short Term Loans and Advances - Other Advance
A42: OCL EXPPAY | B42: SS Earth Movers | D42: 1550 | E42: =-D42 -> -1550 | F42: Other current liabilities-Expenses payable
A43: OCL EXPPAY | B43: Vinayaga Earth Movers (Jcb) | D43: 3204 | E43: =-D43 -> -3204 | F43: Other current liabilities-Expenses payable
A44: OCL TDSPAY | B44: TDS PAYABLE | D44: 389624 | E44: =-D44 -> -389624 | F44: Other Current Liabilities - Trade Payables
A45: OCL EXPPAY | B45: VIJAY ELECTRICALS | D45: 12103 | E45: =-D45 -> -12103 | F45: Other current liabilities-Expenses payable
B46: CRS. FOR PURCHASE | C46: 1319289 | D46: 3865271.5
A47: SC | B47: ACME Safety Wears Ltd | D47: 43181 | E47: =-D47 -> -43181 | F47: Trade Payables
A48: SC | B48: Agar Engineers Pvt Ltd | D48: 16283.5 | E48: =-D48 -> -16283.5 | F48: Trade Payables
A49: SC | B49: Ambika Trading Company | D49: 54253 | E49: =-D49 -> -54253 | F49: Trade Payables
A50: SC | B50: Amman Pipes | D50: 45656 | E50: =-D50 -> -45656 | F50: Trade Payables
A51: SC | B51: Ashish Carting | D51: 21898 | E51: =-D51 -> -21898 | F51: Trade Payables
A52: STLA TADV | B52: Ashish Steel Traders | C52: 1742 | E52: =C52 -> 1742 | F52: Short Term Loans and Advances - Trade Advance
A53: SC | B53: Ashish Suppliers | D53: 12126 | E53: =-D53 -> -12126 | F53: Trade Payables
A54: STLA TADV | B54: Balaji Industrial Suppliers | C54: 6 | E54: =C54 -> 6 | F54: Short Term Loans and Advances - Trade Advance
A55: SC | B55: CHENNAI HYDRAULICS & ENGG | D55: 7290 | E55: =-D55 -> -7290 | F55: Trade Payables
A56: SC | B56: Chennai Steeel Company | D56: 23209 | E56: =-D56 -> -23209 | F56: Trade Payables
A57: SC | B57: Chennai Steel Company | D57: 94274 | E57: =-D57 -> -94274 | F57: Trade Payables | I57: =3295359-3865271 -> -569912 | J57: =3295359-3865271 -> -569912
A58: STLA TADV | B58: Chettinad Cement Corpn Pvt Ltd | C58: 36000 | E58: =C58 -> 36000 | F58: Short Term Loans and Advances - Trade Advance
A59: SC | B59: Dandapani & Co | D59: 150683 | E59: =-D59 -> -150683 | F59: Trade Payables
A60: SC | B60: Darshana Enterprises | D60: 31643 | E60: =-D60 -> -31643 | F60: Trade Payables
A61: SC | B61: Delton Pneumatics | D61: 107676 | E61: =-D61 -> -107676 | F61: Trade Payables
A62: SC | B62: Deva Agencies | D62: 70388 | E62: =-D62 -> -70388 | F62: Trade Payables
A63: SC | B63: Dhandapani Cement (P)Ltd | D63: 16800 | E63: =-D63 -> -16800 | F63: Trade Payables
A64: SC | B64: Dhandapani & Co | D64: 200 | E64: =-D64 -> -200 | F64: Trade Payables
A65: SC | B65: Dharani Hi Tech Project Pvt Ltd | D65: 71000 | E65: =-D65 -> -71000 | F65: Trade Payables
A66: STLA TADV | B66: Dynamic Prestress (I) Pvt Ltd Plant III | C66: 188443 | E66: =C66 -> 188443 | F66: Short Term Loans and Advances - Trade Advance
A67: SC | B67: East India Company | D67: 66513 | E67: =-D67 -> -66513 | F67: Trade Payables
A68: SC | B68: Fakhri Fasteners | D68: 75523 | E68: =-D68 -> -75523 | F68: Trade Payables
A69: SC | B69: Gandhi Industrial Electricals | D69: 28452 | E69: =-D69 -> -28452 | F69: Trade Payables
A70: STLA TADV | B70: Ganesh Electricals | C70: 64600 | E70: =C70 -> 64600 | F70: Short Term Loans and Advances - Trade Advance
A71: SC | B71: G K S Industries | D71: 25218 | E71: =-D71 -> -25218 | F71: Trade Payables
A72: SC | B72: Green Fos Pumps | D72: 5205 | E72: =-D72 -> -5205 | F72: Trade Payables
A73: STLA TADV | B73: Hilti India Pvt Ltd | C73: 2807 | E73: =C73 -> 2807 | F73: Short Term Loans and Advances - Trade Advance
A74: SC | B74: Hogg Hydraulics | D74: 842755.5 | E74: =-D74 -> -842755.5 | F74: Trade Payables
A75: SC | B75: Jalaram Hardware Stores | D75: 1794 | E75: =-D75 -> -1794 | F75: Trade Payables
A76: SC | B76: JBS Engineering | D76: 26111 | E76: =-D76 -> -26111 | F76: Trade Payables
A77: SC | B77: JK Industries | D77: 51 | E77: =-D77 -> -51 | F77: Trade Payables
A78: STLA TADV | B78: J.S. Interior & Exteriors | C78: 3740 | E78: =C78 -> 3740 | F78: Short Term Loans and Advances - Trade Advance
A79: SC | B79: Krishna Sales | D79: 106 | E79: =-D79 -> -106 | F79: Trade Payables
A80: SC | B80: Lakshmi Electrical & Hardwares | D80: 31120 | E80: =-D80 -> -31120 | F80: Trade Payables
A81: SC | B81: Lakshmi Electricals & Hardwares | D81: 230 | E81: =-D81 -> -230 | F81: Trade Payables
A82: SC | B82: Laxmi Spares | D82: 7110 | E82: =-D82 -> -7110 | F82: Trade Payables
A83: SC | B83: Madras Cement Ltd | D83: 60100 | E83: =-D83 -> -60100 | F83: Trade Payables
A84: SC | B84: Maha Marbles | D84: 5400 | E84: =-D84 -> -5400 | F84: Trade Payables
A85: STLA TADV | B85: Mehta Plywood | C85: 93562 | E85: =C85 -> 93562 | F85: Short Term Loans and Advances - Trade Advance
A86: STLA TADV | B86: Metro Steel Mart | C86: 69795 | E86: =C86 -> 69795 | F86: Short Term Loans and Advances - Trade Advance
A87: SC | B87: Mittal Refractories | D87: 1210 | E87: =-D87 -> -1210 | F87: Trade Payables
A88: SC | B88: Navkar Plyfort | D88: 18900 | E88: =-D88 -> -18900 | F88: Trade Payables
A89: SC | B89: Navkar Ply Port | D89: 4753 | E89: =-D89 -> -4753 | F89: Trade Payables
A90: SC | B90: New Shanteri Saw Mill | D90: 45 | E90: =-D90 -> -45 | F90: Trade Payables
A91: SC | B91: N.Mohamed Kasim | D91: 42700 | E91: =-D91 -> -42700 | F91: Trade Payables
A92: SC | B92: N.MOHAMED KASIM (HO) | D92: 196558 | E92: =-D92 -> -196558 | F92: Trade Payables
A93: SC | B93: Offers Kraft | D93: 5250 | E93: =-D93 -> -5250 | F93: Trade Payables
A94: STLA TADV | B94: PMG Containers (P) Ltd | C94: 2750 | E94: =C94 -> 2750 | F94: Short Term Loans and Advances - Trade Advance
A95: STLA TADV | B95: Pooja Enterprise | C95: 849 | E95: =C95 -> 849 | F95: Short Term Loans and Advances - Trade Advance
A96: SC | B96: Prasad Multi Service Pvt Ltd | D96: 645 | E96: =-D96 -> -645 | F96: Trade Payables
A97: SC | B97: Premier Agencies | D97: 2560 | E97: =-D97 -> -2560 | F97: Trade Payables
A98: SC | B98: Ramtec | D98: 9086 | E98: =-D98 -> -9086 | F98: Trade Payables
A99: SC | B99: SAKTHI ENGINEERS | D99: 1032.5 | E99: =-D99 -> -1032.5 | F99: Trade Payables
A100: STLA TADV | B100: Sanjay Engineering Co | C100: 2977 | E100: =C100 -> 2977 | F100: Short Term Loans and Advances - Trade Advance
...

Sheet PL
A2: =BS!A2 -> M/s. Sathiapal Engineers (India) Private Limited (Formerly known as M/S Sathiapal Engineers (India) Limited)
A3: =BS!A3 -> CIN: U74210TN2002PLC048568
A4: =+BS!A4 -> New No. 57, Old No. 3, Canal Road, Kilpauk Garden Colony, Kilpauk, Chennai 600 010.
A6: STATEMENT OF PROFIT AND LOSS FOR THE YEAR ENDED 31st MARCH 2023
A8: Particulars | B8: Notes | C8: For the year 2022-23 | D8: For the year 2021-22
E9: =1000 -> 1000 | G9: =D11-D19-D20 -> 1.0609185e+08 | H9: =C11-C19-C20 -> 1.3005356e+08
A10: INCOME | F10: =1/1000 -> 0.001
A11: I.Revenue from Operations | B11: =Notes!B225 -> 18 | C11: =+Notes!J230 -> 4.1577423e+08 | D11: =351687.70804*1000 -> 3.5168771e+08
A12: II.Other Income | B12: =Notes!B233 -> 19 | C12: =+Notes!J239 -> 4701233.2 | D12: =8171.03452*1000 -> 8171034.5
G13: Year | H13: Value
A14: III.Total Revenue | C14: =C11+C12 -> 4.2047546e+08 | D14: =D11+D12 -> 3.5985874e+08 | E14: =C14*1000 -> 420475459260 | G14: 17-18 | H14: 35571205
G15: 18-19 | H15: 43435129
A16: IV.EXPENSES | G16: 20-21 | H16: 52056151
A17: Cost of Material Consumed | E17: =C19-E18 -> 1.0571339e+08
A18: Purchases of stock in trade | E18: =C19*F19 -> 2.3149728e+08 | G18: Total | H18: =H14+H15+H16 -> 1.3106249e+08
A19: Construction and Operating Expenses | B19: =Notes!B242 -> 20 | C19: =+Notes!J247 -> 3.3721067e+08 | D19: =241435.86174*(1000) -> 2.4143586e+08 | E19: =C19/C11 -> 0.81104274 | F19: =D19/D11 -> 0.6865064 | G19: Average | H19: =AVERAGE(H14:H16) -> 43687495
A20: Changes in Inventories of Finished Goods, Work in Progress and Stock in Trade | B20: =Notes!B250 -> 21 | C20: =+Notes!J260 -> -51490000 | D20: =4160*(1000) -> 4160000 | E20: =+C20+C19 -> 2.8572067e+08 | F20: =+D20+D19 -> 2.4559586e+08 | H20: 0.02
A21: Employee benefits expense | B21: =Notes!B263 -> 22 | C21: =+Notes!J271 -> 57635484 | D21: =51828.88898*(1000) -> 51828889 | E21: =+E20/C11 -> 0.68720149 | F21: =+F20/D11 -> 0.69833507 | G21: CSR | H21: =H19*H20 -> 873749.9
A22: Administrative and Other expenses | B22: =Notes!B274 -> 23 | C22: =+Notes!J307 -> 24412525 | D22: =22631.40145*(1000) -> 22631401 | E22: =+E21-1 -> -0.31279851 | F22: =+F21-1 -> -0.30166493
A23: Finance costs | B23: =Notes!#REF! -> #REF! | D23: =0*(1000) -> 0
A24: Write off of Assets | C24: =('Audit entries FY 22-23'!C79) -> 868251 | D24: =0*(1000) -> 0 | H24: =C24*2 -> 1736502
A25: Depreciation and Amortization | B25: 10 | C25: =Dep_Co!K26 -> 8219826.5 | D25: =9718.98258954644*(1000) -> 9718982.6 | E25: % | G25: =12765-C25 -> -8207061.5
A27: Total Expenses | C27: =SUM(C19:C25) -> 3.7685675e+08 | D27: =SUM(D19:D25) -> 3.2977513e+08
F28: -40008739 | G28: =F28-C30 -> -83627446 | H28: -1.15105e+08
G29: =262643608 -> 262643608 | H29: =C30-G29 -> -2.190249e+08
A30: (V)Profit / (Loss) Before Prior Period Items | C30: =C14-C27 -> 43618707 | D30: =30083.6078004535*1000 -> 30083608 | E30: =+C30/C11 -> 0.1049096 | F30: =1/1000 -> 0.001
A31: (VI)Prior period item: | C31: =('Audit entries FY 22-23'!D101) -> 2621516 | F31: 13245738 | G31: =F31-C30 -> -30372969 | H31: =1/1000 -> 0.001
D32: 0 | H32: =C30/C11 -> 0.1049096 | I32: =D30/D11 -> 0.085540686
A33: Profit / (Loss) Before Extraordinary Items & Tax
D34: 0
A35: (VII)Profit / (Loss) Before Extraordinary Items ,Exceptional Items and Tax | C35: =C30+C31 -> 46240223 | D35: =D30+D32-D34 -> 30083608 | F35: =C35/C11 -> 0.11121474
A36: (VIII)Extraordinary Items
A37: (VII)Profit / (Loss) Before Exceptional Items and Tax
A38: (VIII)Exceptional Items
A39: (IX)Profit before Tax
A40: (X)Less: Tax Expense | C40: =IT!E46 -> 10965295 | D40: =8443.3364*1000 -> 8443336.4 | G40: =C45-#REF! -> #REF!
A41: Current Tax | B41: 11 | C41: 0 | D41: 0
A42: Deferred Tax | B42: =+Notes!B139 -> 11 | C42: ='Audit entries FY 22-23'!D63 -> 742110.62 | D42: =-2016.03983785948*1000 -> -2016039.8 | F42: =C40-D40 -> 2521958.6
A45: Total Tax Expenses | C45: =C40+C42+C43 -> 11707406 | D45: =D40+D42+D43 -> 6427296.6
A47: (XI)Profit / (Loss) for the year | C47: =(C35-C45) -> 34532817 | D47: =D35-D45 -> 23656311 | E47: =C47/C11 -> 0.083056657 | F47: =D47/D11 -> 0.067265107 | G47: =C47-#REF! -> #REF! | H47: =1/1000 -> 0.001
A50: Earnings per share (of ` 10/- each): | B50: =Notes!B314 -> 25 | C50: =+Notes!J319 -> 48.31481 | D50: =Notes!K319 -> 33.097508 | F50: -174830584
A51: (a) Basic & Diluted | B51: =+B50 -> 25
A52: (b) Basic Diluted
A53: Significant Accounting Policies and Notes to Financial Statements form an integral part of the Balance Sheet | B53: 1 to 27 | F53: =F50-C47 -> -2.093634e+08 | G53: =41260-C47 -> -34491557
A54: In accordance with our Report of even date attached | D54: For and on behalf of the Board of Directors
A55: For A.JOHN MORIS & CO
A56: Chartered Accountants
A57: Registration No. 007220S
A60: (CA A.JOHN MORIS) | B60: (S. KUMARAN) | D60: (K. VISALAKSHI)
A61: Managing Partner | B61: Managing Director | D61: Director
A62: M.No. 029424 | B62: =BS!D63 -> DIN No.01926196 | D62: =BS!E63 -> DIN No.01926144
A63: =BS!A63 -> Place: Chennai
A64: =BS!A64 -> Date: 07-09-2023
A66: CSR TO BE SHOWN IN P& L

Sheet Dep_Co
D3: M/S Sathiapal Engineers (India) Private Limited
D4: Formerly Known as M/S Sathiapal Engineers (India) Limited
H5: =BS!A3 -> CIN: U74210TN2002PLC048568
D6: =+Notes!B4 -> New No. 57, Old No. 3, Canal Road, Kilpauk Garden Colony, Kilpauk, Chennai 600 010.
D8: Note No:10 PROPERTY PLANT & EQUIPMENT: (AS PER COMPANIES ACT, 2013) | S8: 537374.21
S9: 1131993.8
D10: S. No. | E10: Name of the Block | F10: Gross Block | J10: DEPRECIATION | N10: Net Block | Q10: =1/1000 -> 0.001 | S10: 3298952
F11: As on 01.04.2022 | G11: Additions | H11: Deletion | I11: As on 31.03.2023 | J11: As on 01.04.2022 | K11: For the Period | L11: Deletion | M11: =I11 -> As on 31.03.2023 | N11: =I11 -> As on 31.03.2023 | O11: =F11 -> As on 01.04.2022
R12: Depreciation -IT | S12: =+Dep_IT!I23 -> 11820033
D13: 1 | E13: Building - WIP | F13: =868.251*1000 -> 868251 | G13: 0 | H13: =F13 -> 868251 | I13: =F13+G13-H13 -> 0 | J13: 0 | K13: =0 -> 0 | M13: =J13+K13 -> 0 | N13: =+I13-M13 -> 0 | R13: Depreciation-Co. | S13: =+K26 -> 8219826.5 | U13: 26312008 | V13: =U13-G15 -> -4778159.4
O14: =F14-J14 -> 0
D15: 2 | E15: Plant & Machinary | F15: =132856.773*1000 -> 1.3285677e+08 | G15: =(Sheet9!B21+Sheet9!B22)*1000 -> 31090167 | H15: 0 | I15: =F15+G15-H15 -> 1.6394694e+08 | J15: =88256.709*1000 -> 88256709 | K15: =(SUM('FA Register Final'!L169:L178)+SUM('FA Register Final'!L206:L242)+SUM('FA Register Final'!L10:L113)+SUM('FA Register Final'!L114:L143)) -> 4968320 | M15: =J15+K15 -> 93225029 | N15: =+I15-M15 -> 70721911 | O15: =F15-J15 -> 44600064 | P15: =K15-(F15/#REF!) -> #REF! | R15: Deferred Tax Asset | S15: =+S14*26% -> 0
D17: 3 | E17: Computers | F17: =4247.175*1000 -> 4247175 | G17: =(Sheet9!B18+Sheet9!B19)*1000 -> 247236.44 | H17: 0 | I17: =F17+G17-H17 -> 4494411.4 | J17: =3434.687*1000 -> 3434687 | K17: =(SUM('FA Register Final'!L159:L167)+SUM('FA Register Final'!L190:L197)+SUM('FA Register Final'!L3:L8)) -> 290888.03 | M17: =J17+K17 -> 3725575 | N17: =I17-M17 -> 768836.41 | O17: =F17-J17 -> 812488 | P17: =K17-(F17/#REF!) -> #REF! | S17: =+S16+S15 -> 0
D19: =D17+1 -> 4 | E19: Furnitures & Fixtures | F19: =950.451*(1000) -> 950451 | G19: 0 | H19: 0 | I19: =F19+G19-H19 -> 950451 | J19: =652.763*1000 -> 652763 | K19: 0 | M19: =J19+K19 -> 652763 | N19: =I19-M19 -> 297688 | O19: =F19-J19 -> 297688 | P19: =K19-(F19/#REF!) -> #REF!
F20: =0*(1000) -> 0
D21: =+D19+1 -> 5 | E21: Vehicles | F21: =19219.29*(1000) -> 19219290 | G21: =(Sheet9!B24)*1000 -> 1696884 | H21: =('Audit entries FY 22-23'!D70) -> 865919 | I21: =F21+G21-H21 -> 20050255 | J21: =10335.411*1000 -> 10335411 | K21: =(SUM('FA Register Final'!L182)+SUM('FA Register Final'!L245:L246)+SUM('FA Register Final'!I148:I150)) -> 2937535.4 | L21: =('Audit entries FY 22-23'!C69) -> 822623.05 | M21: =J21+K21-L21 -> 12450323 | N21: =I21-M21 -> 7599931.7 | O21: =F21-J21 -> 8883879 | P21: =K21-(F21/#REF!) -> #REF! | Q21: =H21-L21 -> 43295.95 | R21: 3474505 | S21: =O21-R21 -> 5409374
F22: =0*(1000) -> 0
D23: 6 | E23: Office Equipments | F23: =121.49*(1000) -> 121490 | G23: 0 | H23: 0 | I23: =F23+G23-H23 -> 121490 | J23: =21.818*1000 -> 21818 | K23: =('FA Register Final'!L188) -> 23083.1 | M23: =J23+K23 -> 44901.1 | N23: =I23-M23 -> 76588.9 | O23: =F23-J23 -> 99672
R25: 49451812 | S25: 6839713 | T25: =J19-N19 -> 355075
E26: TOTAL | F26: =SUM(F13:F23) -> 158263430 | G26: =SUM(G13:G23) -> 33034288 | H26: =SUM(H13:H23) -> 1734170 | I26: =SUM(I13:I23) -> 1.8956355e+08 | J26: =SUM(J13:J23) -> 102701388 | K26: =SUM(K13:K23) -> 8219826.5 | L26: =SUM(L13:L23) -> 822623.05 | M26: =SUM(M13:M23) -> 1.1009859e+08 | ... O26: =SUM(O13:O23) -> 54693791 | P26: =O26-N26 -> -24771165 | R26: 42612099 | S26: =R25-S25 -> 42612099
C27: =C28-G26 -> -4786299.8 | E27: =1000 -> 1000 | G27: =33034-G26 -> -33001254 | I27: =189563548/1000 -> 189563.55 | J27: =H21-L21 -> 43295.95 | K27: =I27-J27 -> 146267.6 | M27: =I26-M26 -> 79464956 | N27: =N26*1000 -> 7.9464956e+10 | O27: =K26-Dep_IT!I23*26% -> 5146617.9
C28: 28247988 | G28: 16072619 | I28: =I27-I26 -> -1.8937398e+08 | J28: =I26-M26 -> 79464956 | M28: =I26-M26 -> 79464956 | P28: 55562042
B44: 0 | C44: 1550
C51: 709574
C52: 20202
G141: =G28-G26 -> -16961669 | H141: 42094 | J141: 365 | M141: =78054+30601 -> 108655 | P141: =+G26-H26 -> 31300118 | Q141: =P141+L26 -> 32122741
N142: =565147/F21*H21 -> 25462.518 | P142: =K26 -> 8219826.5 | R142: =P141-P142+L26 -> 23902914
E143: Assets | F143: Date of Purchase | G143: Amount | H143: No. of Days till 31 mar 2014 | I143: Depreciation for the year | J143: Depreciation Rate | M143: >180 days | N143: =I19-J19 -> 297688 | O143: =I19*5% -> 47522.55 | P143: =P28+P141-P142 -> 78642333
E144: Plant & Machinery | N144: =N143-K19 -> 297688 | O144: =I19*5% -> 47522.55 | P144: =P143+L26 -> 79464956
E145: P & M 1 | F145: 41736 | G145: 70350 | H145: =$H$141-F145 -> 358 | I145: =G145*J145/$J$141*H145 -> 7134.685 | J145: 0.1034 | M145: =IF(H145>180,G145,0) -> 70350 | N145: =N143-N144 -> 0 | O145: =O143-O144 -> 0
E146: P & M 2 | F146: 41737 | G146: 77260 | H146: =$H$141-F146 -> 357 | I146: =G146*J146/$J$141*H146 -> 7813.5896 | J146: 0.1034 | M146: =IF(H146>180,G146,0) -> 77260
E147: P & M 3 | F147: 41747 | G147: 112931 | H147: =$H$141-F147 -> 347 | I147: =G147*J147/$J$141*H147 -> 11101.21 | J147: 0.1034 | M147: =IF(H147>180,G147,0) -> 112931
E148: P & M 4 | F148: 41747 | G148: 1318125 | H148: =$H$141-F148 -> 347 | I148: =G148*J148/$J$141*H148 -> 129572.77 | J148: 0.1034 | M148: =IF(H148>180,G148,0) -> 1318125
E149: P & M 5 | F149: 41834 | G149: 70350 | H149: =$H$141-F149 -> 260 | I149: =G149*J149/$J$141*H149 -> 5181.6148 | J149: 0.1034 | M149: =IF(H149>180,G149,0) -> 70350
E150: P & M 6 | F150: 41837 | G150: 113355 | H150: =$H$141-F150 -> 257 | I150: =G150*J150/$J$141*H150 -> 8252.803 | J150: 0.1034 | M150: =IF(H150>180,G150,0) -> 113355
E151: P & M 7 | F151: 41897 | G151: 7875 | H151: =$H$141-F151 -> 197 | I151: =G151*J151/$J$141*H151 -> 439.48541 | J151: 0.1034 | M151: =IF(H151>180,G151,0) -> 7875
E152: P & M 8 | F152: 41921 | G152: 4351 | H152: =$H$141-F152 -> 173 | I152: =G152*J152/$J$141*H152 -> 213.23715 | J152: 0.1034 | M152: =IF(H152>180,G152,0) -> 0
G153: =SUM(G145:G152) -> 1774597 | I153: =SUM(I145:I152) -> 169709.4
M154: =SUM(M145:M152) -> 1770246
E155: Computers
E156: Computer 1 | F156: 41835 | G156: 27500 | H156: =$H$141-F156 -> 259 | I156: =G156*J156/$J$141*H156 -> 3163.1705 | J156: 0.1621 | M156: =IF(H156>180,G156,0) -> 27500
E157: Computer 2 | F157: 42046 | G157: =33800+8000 -> 41800 | H157: =$H$141-F157 -> 48 | I157: =G157*J157/$J$141*H157 -> 891.06148 | J157: 0.1621 | M157: =IF(H157>180,G157,0) -> 0
G158: =SUM(G156:G157) -> 69300 | I158: =SUM(I156:I157) -> 4054.232 | M158: =SUM(M156:M157) -> 27500
E160: TOTAL
G164: =+G153+G158 -> 1843897 | M164: =+#REF!+#REF! -> #REF! | N164: =+M158+M154 -> 1797746
F175: 10000 | G175: =10*365 -> 3650 | H175: 365 | I175: =+G175-H175 -> 3285
F177: =+F175*5/100 -> 500
F178: =+F175-F177 -> 9500 | G178: =+F178*H175/G175 -> 950 | H178: =+F178-G178 -> 8550
H179: =+H178*H175/G175 -> 855

Sheet Dep_IT
B1: =+Dep_Co!D3 -> M/S Sathiapal Engineers (India) Private Limited
F2: =BS!A3 -> CIN: U74210TN2002PLC048568
B3: =+Dep_Co!D6 -> New No. 57, Old No. 3, Canal Road, Kilpauk Garden Colony, Kilpauk, Chennai 600 010.
M4: 194449 | N4: 118176
B5: ANNEXURE :FIXED ASSETS : (AS PER INCOME TAX ACT)
N6: 9777794
B7: S. No. | C7: Name of the Block | D7: Net Block | I7: Depreciation For the Year | J7: Net Block | L7: WDV
D8: WDV as on 01.04.2022 | E8: I Half Additions | F8: II Half Additions | G8: Deletion out of additions | H8: Value as on 31.03.2023 | N8: =1834000-260000 -> 1574000 | O8: 20506020 | P8: 10103870
J9: WDV as on 31.03.2023 | K9: WDV as on 31.03.2022 | L9: Dep Rate | M9: 1000
B11: 1 | C11: Building - WIP | D11: =868.251*1000 -> 868251 | E11: 0 | F11: 0 | H11: =D11+E11+F11-G11 -> 868251 | I11: 0 | J11: =H11-I11 -> 868251 | K11: =868.251*1000 -> 868251 | N11: =1/1000 -> 0.001
D12: 0 | K12: 0
B13: 2 | C13: Plant & Machinery | D13: =40521.164*1000 -> 40521164 | E13: =(Sheet9!B22)*1000 -> 20215118 | F13: =(Sheet9!B21)*1000 -> 10875050 | H13: =D13+E13+F13-G13 -> 71611331 | I13: =ROUND((D13-G13+E13)*L13+(F13*L13/2),0) -> 9926071 | J13: =H13-I13 -> 61685260 | K13: =40521.164*1000 -> 40521164 | L13: 0.15 | N13: =+(D13+E13)*L13+(F13*L13/2) -> 9926071
D14: 0 | E14: 0 | F14: 0 | K14: 0
B15: 3 | C15: Computers | D15: =562.447*1000 -> 562447 | E15: =(Sheet9!B19)*1000 -> 148587.29 | F15: =(Sheet9!B18)*1000 -> 98649.153 | H15: =D15+E15+F15-G15 -> 809683.44 | I15: =ROUND((D15+E15)*L15+(F15*L15/2),0) -> 304144 | J15: =H15-I15 -> 505539.44 | K15: =562.447*1000 -> 562447 | L15: 0.4 | M15: =10545099-E13 -> -9670018.7 | N15: =+(D15+E15)*L15+(F15*L15/2) -> 304143.55
D16: 0 | E16: 0 | F16: 0 | K16: 0
B17: 4 | C17: Furnitures & Fixtures | D17: =388.047*1000 -> 388047 | E17: 0 | F17: 0 | H17: =D17+E17+F17-G17 -> 388047 | I17: =ROUND((D17+E17)*L17+(F17*L17/2),0) -> 38805 | J17: =H17-I17 -> 349242 | K17: =388.047*1000 -> 388047 | L17: 0.1 | N17: =+(D17+E17)*L17+(F17*L17/2) -> 38804.7
D18: 0 | E18: 0 | F18: 0 | K18: 0 | O18: 8305309 | P18: 2828449
B19: 5 | C19: Motor Vehicles | D19: =9648.378*1000 -> 9648378 | E19: 0 | F19: =(Sheet9!B24)*1000 -> 1696884 | G19: =260*1000 -> 260000 | H19: =D19+E19+F19-G19 -> 11085262 | I19: =ROUND((D19+E19)*L19-F27+(F19*L19/2),0) -> 1535523 | J19: =H19-I19 -> 9549739 | K19: =9648.378*1000 -> 9648378 | L19: 0.15 | N19: =+(D19+E19)*L19+(F19*L19/2) -> 1574523 | O19: =E23+F23 -> 33034288 | P19: 4935867
D20: 0 | E20: 0 | F20: 0 | K20: 0
B21: 6 | C21: Office Equipments | D21: =103.266*1000 -> 103266 | F21: 0 | G21: 0 | H21: =D21+E21+F21-G21 -> 103266 | I21: =ROUND((D21+E21)*L21+(F21*L21/2),0) -> 15490 | J21: =H21-I21 -> 87776 | K21: =103.266*1000 -> 103266 | L21: 0.15
O22: =O18-O19 -> -24728979 | P22: =SUM(P18:P19) -> 7764316
C23: TOTAL | D23: =SUM(D11:D21) -> 52091553 | E23: =SUM(E11:E21) -> 20363705 | F23: =SUM(F11:F21) -> 12670583 | G23: =SUM(G11:G21) -> 260000 | H23: =SUM(H11:H21) -> 84865841 | I23: =SUM(I11:I21) -> 11820033 | J23: =SUM(J11:J21) -> 73045808 | K23: =SUM(K11:K21) -> 52091553 | N23: =I23-[31]Dep_IT!$J$24 -> 8053001
A24: 7164105 | N24: 1000
E25: 17826565 | N25: 17757
E26: 8335907 | F26: 260000 | I26: 853465 | M26: 2955480 | N26: 29662
F27: =F26*15% -> 39000 | G27: =F27/2 -> 19500 | I27: =I26-I19 -> -682058 | J27: =+F13*L13 -> 1631257.4 | M27: 1491627
K28: =I23 -> 11820033 | L28: =K29-K28 -> -3600206.5 | M28: 4297882
C29: Fixed Asset Additions | G29: Fixed Asset Deletions | K29: =Dep_Co!K26 -> 8219826.5 | L29: =L28*0.26 -> -936053.69 | M29: =SUM(M26:M27) -> 4447107
M30: =M29-M28 -> 149225
C31: Date | D31: Particulars | E31: Iind half | G31: Date | H31: Particulars | I31: Amount | M31: =M30/2 -> 74612.5
C32: 42460 | D32: Building | E32: 868251 | G32: 42275 | H32: Vehicle | I32: 560000
C33: 42334 | D33: Computers | E33: 61500 | G33: 42312 | H33: Vehicle | I33: 190000
C34: 42460 | D34: Computers | E34: 65000
C35: 42268 | D35: Plant & Machinary | E35: 0 | L35: 52643
C36: 42374 | D36: Plant & Machinary | E36: 143800 | L36: 47419
C37: 42431 | D37: Plant & Machinary | E37: 239400 | J37: =J23-Dep_Co!N26 -> -6419148.5 | L37: =L35-L36 -> 5224
C38: 42434 | D38: Plant & Machinary | E38: 39525 | J38: =J37*25.168% -> -1615571.3
C39: 42438 | D39: Plant & Machinary | E39: 80150
C40: 42439 | D40: Plant & Machinary | E40: 15000
C41: 42439 | D41: Plant & Machinary | E41: 11550
C42: 42430 | D42: Vehicle | E42: 806617

Sheet Additional Disclosures
A2: M/s. Sathiapal Engineers (India) Private Limited (Formerly known as M/S Sathiapal Engineers (India) Limited)
A3: New No. 57, Old No. 3, Canal Road, Kilpauk Garden Colony, Kilpauk, Chennai 600 010.
A4: CIN: U74210TN2002PLC048568
A5: In exercise of the powers conferred by sub-section (1) of section 467 of the Companies Act, 2013 (18 of 2013), the Central Government hereby has made the following further amendments in Schedule III to the said Act with effect from 1st day of April, 2021.
A7: 1. Promoter’s Shareholding.
A8: As per amendment, the company shall disclose the shareholding pattern of promoters at the end of the year as follows:
A9: Sl.No | B9: Promoter Name | E9: Number of Shares held (in no's) | G9: Percentage of Total Shares | I9: Percentage change during the year
A12: 1 | B12: Mr.S.Kumaran | E12: 580331 | G12: =E12/$E$19 -> 0.81194019 | I12: 0
A13: 2 | B13: Mrs.S.Rajathilagam | E13: 66455 | G13: =E13/$E$19 -> 0.092977086 | I13: 0
A14: 3 | B14: Mrs.K.Visalakshi | E14: 500 | G14: =E14/$E$19 -> 0.00069954921 | I14: 0
A15: 4 | B15: Mr.V.Ramalingam | E15: 500 | G15: =E15/$E$19 -> 0.00069954921 | I15: 0
A16: 5 | B16: Mr.R.Suganthakumari | E16: 500 | G16: =E16/$E$19 -> 0.00069954921 | I16: 0
A17: 6 | B17: Ms.K.Suhasini | E17: 33230 | G17: =E17/$E$19 -> 0.046492041 | I17: 0
A18: 7 | B18: Ms.K.Harshini | E18: 33230 | G18: =E18/$E$19 -> 0.046492041 | I18: 0
A19: Total holding by promoter | E19: =SUM(E12:F18) -> 714746 | G19: =SUM(G12:H18) -> 1 | I19: 0
A21: 2. Trade Receivables
A22: The amendment brought in schedule 3 requires extensive additional categorization of trade receivables and also requires the ageing of trade receivable in 5 different categories.
A23: As per the amendment, following additional categorization needs to be done apart from the sub-classification done currently. As at the end of 31-03-2022 no trade receivable exist.
A24: Particulars | D24: Outstanding for following periods from due date of payment
D25: Amount
D26: Less than 6 months | E26: 6 months-1year | F26: 1-2 years | G26: 2-3 years | H26: More than 3 years | I26: Total
A27: (i) Undisputed Trade Receivables – considered good | E27: =(Notes!J178)/1000 -> 12929.68 | I27: =SUM(D27:H27) -> 12929.68
A28: (ii) Undisputed Trade Receivables – considered doubtful | E28: 0 | I28: =SUM(D28:H28) -> 0 | L28: 1000
A29: (iii) Disputed Trade Receivables considered good | E29: 0 | I29: =SUM(D29:H29) -> 0
A30: (iv) Disputed Trade Receivables considered doubtful | E30: 0 | I30: =SUM(D30:H30) -> 0
A32: 3. Other Financial Assets:
A33: The amendment requires that other financial assets shall include: (i) Security deposits. (ii) Bank deposits with more than 12 months maturity. (iii) Others
A34: S.No | C34: Particulars | H34: Amount
A35: (i) | C35: Bank Deposit | E35: Deposit with banks | H35: =Notes!J191/1000 -> 57211.389
A36: (ii) | C36: Security Deposit | E36: Security deposit with various pesons | H36: =Notes!J162/1000 -> 74626.866
A37: (iii) | C37: Others | E37: Mutual Fund, Cash and cash equivalent | H37: =Notes!J198/1000 -> 21230.843
A39: 4. Trade payables :
A40: Trade payables were required to be segregated into dues of micro enterprises and small enterprises (MSME) and other than micro enterprises and small enterprises. Schedule III also required disclosure of specific details which are mandated as per the MSMED Act, 2006.As per Amendment, additional classification of the above are to be given and also the ageing of the same into 4 categories.
A41: Particulars | C41: Outstanding for following periods from due date of payment
C42: Amount
C43: Less than 1 year | E43: 1-2 years | F43: 2-3 years | G43: More than 3 years | H43: Total
A44: (i)MSME | C44: =(Notes!J80-Notes!K80)/1000 -> 11210.09 | E44: =Notes!K80/1000 -> 6562.7098 | F44: 0 | G44: 0 | H44: =SUM(C44:G44) -> 17772.8
A45: (ii)Others | E45: 0 | F45: 0 | G45: 0 | H45: =SUM(C45:G45) -> 0
A46: (iii) Disputed dues – MSME | C46: 0 | E46: 0 | F46: 0 | G46: 0 | H46: =SUM(C46:G46) -> 0
A47: (iv) Disputed dues – Others | C47: 0 | E47: 0 | F47: 0 | G47: 0 | H47: =SUM(C47:G47) -> 0
A49: 5. Title Deed of Immovable Property not held in the name of company :
A51: All the Immovable property is held in the name of the company during the financial year.
A53: 6. Disclosure of Revaluation of Assets :
A54: The company has not revalued any of it's Property Plant and Equipment during the Financial year.
A56: 7. Disclosure on Loans /Advance to Directors /KMP / Related Parties :
A57: The company has not granted any Loans and Advances to promoters, directors, KMP's and other related parties
A59: 8. Capital Work -in progress (CWIP) :
A61: CWIP | B61: To be completed in
B62: Less than 1 year | D62: 1-2 Years | F62: 2-3 Years | H62: More than 3 Years
A64: NIL | B64: NIL | D64: NIL | E64: NIL | F64: NIL | G64: NIL | H64: NIL
A67: 9. Intangible Asset under development :
A69: Intangible Assets | B69: To be completed in
B70: Less than 1 year | D70: 1-2 Years | F70: 2-3 Years | H70: More than 3 Years
A72: NIL | B72: NIL | D72: NIL | E72: NIL | F72: NIL | G72: NIL | H72: NIL
A76: 10. Details of Benami Property held :
A77: The company has hot held any Benami Property and no proceedings have been initiated or pending against the company for holding any benami property under the Benami Transactions (Prohibition) Act, 1988 (45 of 1988) and rules made thereunder.
A80: 11. Wilful Defaulter and End use of Funds :
A81: The company has not been declared as a wilful defaulter by any bank or financial institution or any other lender for the current financial year.
A83: 12. Details in respect of Borrowing funds and share premium from any person(s) or entity(s) :
A85: Lendor of Loan | B85: Nature of Loan | E85: Schedule of Interest payment | G85: Balance as on 31st March,2023
A89: 13. Relationship with struck off companies :
A90: The company has no transactions with companies struck off under section 248 of the Companies Act, 2013 or section 560 of the Companies Act, 1956.
A92: 14. Compliance with number of Layers :
A93: The company has complied with the number of layers persribed under clause (87) of section 2 of the Act read with Companies (Restriction on number of Layers) Rules, 2017.
A96: 15. Corporate Social Responsibility :
A97: Corporate social responsibilty Provisions are not applicable for this currengt Financial Year.
A99: 16. Crypto Currency or Virtual Currency :
A100: The Company has not traded or invested or involved in Crypto Currency or Virtual Currency transactions during the financial year.

Sheet Ratio
A2: M/s. Sathiapal Engineers (India) Private Limited (Formerly known as M/S Sathiapal Engineers (India) Limited)
A3: ='Additional Disclosures'!A3:J3 -> New No. 57, Old No. 3, Canal Road, Kilpauk Garden Colony, Kilpauk, Chennai 600 010.
A4: ='Additional Disclosures'!A4:J4 -> CIN: U74210TN2002PLC048568
A5: Key Ratios Analysis
A6: In exercise of the powers conferred by sub-section (1) of section 467 of the Companies Act, 2013 (18 of 2013), the Central Government hereby has made the following further amendments in Schedule III to the said Act with effect from 1st day of April, 2021
A7: Ratio | B7: Numerator | C7: Denominator | D7: Year ended March 31, 2023 | E7: Year ended March 31, 2022 | F7: Variance % | G7: Remarks
A9: LIQUIDITY RATIOS
A11: Current Ratio | B11: Total current assets | C11: Total current liabilities | D11: =(B56/B57) -> 3.704277 | E11: =(C56/C57) -> 3.7355995 | F11: =(D11-E11)/E11 -> -0.0083848656
A13: SOLVENCY RATIOS
A15: Debt-Equity Ratio | B15: Total Debt | C15: Total Equity | D15: =(B58/B59) -> 0.20020856 | E15: =C58/C59 -> 0.20556762 | F15: =(D15-E15)/E15 -> -0.026069554
A16: Debt Service Coverage Ratio | B16: Earnings available for Debt services | C16: Interest + Installment | D16: 0 | E16: 0
A18: TURNOVER RATIOS (in times)
A20: Inventory turnover ratio | B20: Cost of Goods sold | C20: Average value of inventory | D20: =(B78/B83) -> 5.5388323 | E20: 8.8 | F20: =(D20-E20)/E20 -> -0.37058723
A21: Trade Receivables turnover ratio | B21: Turnover | C21: Average Trade receivables | D21: =(B61/B81) -> 11.31318 | E21: 5.72 | F21: =(D21-E21)/E21 -> 0.97782873
A22: Trade payables turnover ratio | B22: Turnover | C22: Average Trade payables | D22: =(B61/B82) -> 34.170168 | E22: 8.42 | F22: =(D22-E22)/E22 -> 3.0582147
A23: Net capital turnover ratio | B23: Total Equity | C23: Revenue from Operations | D23: =(B59/B61) -> 0.77616365 | E23: 2.16 | F23: =(D23-E23)/E23 -> -0.64066497
A25: OPERATING RATIOS (in %)
A27: Net profit ratio | B27: Profit After Tax | C27: Revenue from Operations | D27: =(B64/B61) -> 0.083056657 | E27: =C64/C61 -> 0.067265107 | F27: =(D27-E27)/E27 -> 0.23476586
A28: Return on Equity Ratio | B28: Profit After Tax | C28: Total Equity | D28: =B64/B59 -> 0.10700921 | E28: =C64/C59 -> 0.080590664 | F28: =(D28-E28)/E28 -> 0.32781146
A29: Return on Capital employed | B29: Profit Before Tax | C29: Total Equity | D29: =B63/B59 -> 0.14328775 | E29: =C63/C59 -> 0.10248673 | F29: =(D29-E29)/E29 -> 0.39811028
A30: Return on investment | B30: Other Income | C30: Average cash, cash equivalents & Other Marketable securities | D30: =B66/B84 -> 0.17188004 | E30: 0.05 | F30: =(D30-E30)/E30 -> 2.4376009
A32: In Accordance with our Report attached | D32: =PL!D54 -> For and on behalf of the Board of Directors
A33: For A JOHN MORIS & Co.,
A34: Chartered Accountants
A35: FRN No. 007220S
A40: =PL!A60 -> (CA A.JOHN MORIS) | D40: =PL!B60 -> (S. KUMARAN) | G40: (K. VISALAKSHI)
A41: =PL!A61 -> Managing Partner | D41: =PL!B61 -> Managing Director | G41: Director
A42: =PL!A62 -> M.No. 029424 | D42: =PL!B62 -> DIN No.01926196 | G42: DIN No.01926144
A43: =PL!A63 -> Place: Chennai
A44: =PL!A64 -> Date: 07-09-2023
A54: Workings | B54: 2022-23 | C54: 2021-22 | D54: 2019-20
A56: Current Asset | B56: =SUM(BS!C46:C50) -> 2.3322609e+08 | C56: =SUM(BS!E46:E50) -> 2.2202898e+08
A57: Current Liability | B57: =SUM(BS!C24:C27) -> 62961299 | C57: =SUM(BS!E24:E27) -> 59435969
A58: Total Debt | B58: =SUM(BS!D20:D28) -> 64609074 | C58: =SUM(BS!F20:F28) -> 60341625
A59: Total Equity | B59: =SUM(BS!D13:D15) -> 3.2270884e+08 | C59: =SUM(BS!F13:F15) -> 2.9353662e+08
A60: Trade receivables | B60: =BS!C47 -> 12929680 | C60: =BS!E47 -> 60572945 | D60: 47729964
A61: Revenue from operations | B61: =PL!C11 -> 4.1577423e+08 | C61: =PL!D11 -> 3.5168771e+08
A62: Trade payable | B62: =BS!C25 -> 17772800 | C62: =BS!E25 -> 6562709.8 | D62: 8874142.9
A63: Profit Before tax | B63: =PL!C35 -> 46240223 | C63: =PL!D35 -> 30083608
A64: Profit afret tax | B64: =PL!C47 -> 34532817 | C64: =PL!D47 -> 23656311
A65: Share capital | B65: =BS!C13 -> 7147460 | C65: 7147460
A66: Other income | B66: =Notes!J239 -> 4701233.2
A67: Principal+Interest
A68: Car loan repayment- Principle
A69: Car loan repayment- Interest
A70: Housing loan
A71: Principal
A72: Interest
A73: Director loan- Principle
A75: Total Principle + Interest
A76: Net Operating Income
A78: COGS | B78: =PL!C19+PL!C20 -> 2.8572067e+08 | C78: =PL!D19+PL!D20 -> 2.4559586e+08
A79: Value of Inventory | B79: =BS!C46 -> 77330000 | C79: =BS!E46 -> 25840000 | D79: 11200000
A81: Average trade receivables | B81: =(B60+C60)/2 -> 36751312 | C81: =(C60+D60)/2 -> 54151454
A82: Average Trade payables | B82: =(B62+C62)/2 -> 12167755 | C82: =(C62+D62)/2 -> 7718426.4
A83: Avg Value of Inventory | B83: =(B79+C79)/2 -> 51585000 | C83: =(C79+D79)/2 -> 18520000
A84: Average cash and cash equivalent | B84: =(Notes!K198+Notes!J198)/2 -> 27351827

Sheet Notes
B2: =PL!A2 -> M/s. Sathiapal Engineers (India) Private Limited (Formerly known as M/S Sathiapal Engineers (India) Limited)
B3: =BS!A3 -> CIN: U74210TN2002PLC048568
B4: =+PL!A4 -> New No. 57, Old No. 3, Canal Road, Kilpauk Garden Colony, Kilpauk, Chennai 600 010.
B6: Note No. | C6: NOTES TO THE FINANCIAL STATEMENTS
B7: 3 | C7: SHARE CAPITAL | K7: (Rs. in '000)
C8: Particulars | H8: Year ended 31st March, 2023 | J8: Year ended 31st March, 2022
H9: Number of Shares | I9: Rs. | J9: Number of Shares | K9: Rs.
C10: Authorized :
C11: Equity shares of Rs.10/- each | H11: 750000 | I11: =(H11*10) -> 7500000 | J11: =H11 -> 750000 | K11: =I11 -> 7500000 | M11: =1/1000 -> 0.001
I12: 0 | K12: 0
C13: Issued, subscribed and fully paid up Equity shares of Rs.10/- each | I13: 0 | K13: 0
C14: Equity Shares of Rs.10/-, each, fully paid up | H14: 714746 | I14: =7147.46*1000 -> 7147460 | J14: 714746 | K14: =I14 -> 7147460
C16: Total | H16: =+H14 -> 714746 | I16: =+I14 -> 7147460 | J16: =+J14 -> 714746 | K16: =+K14 -> 7147460
C18: Other Information :
C20: The Company has only one class of equity shares having par value of Rs.10/- each. Each holder of equity shares is entitled to one vote per share. The shareholders have the right to receive interim dividends declared by the Board of Directors and final dividend proposed by the Board of Directors and approved by the shareholders.
C22: The shareholders have all other rights as available to equity shareholders as per the provisions of the Companies Act, 2013, read together with the Memorandum of Association and Articles of Association of the Company, as applicable.
C24: The reconciliation of the number of shares outstanding and the amount of share capital as at 31st March, 2022 and 31st March, 2023 is set out below.
C25: Particulars | H25: As at 31st March, 2023 | J25: As at 31st March, 2022 | M25: =1/1000 -> 0.001
H26: No. of Shares | I26: Amount in Rs | J26: No. of Shares | K26: Amount in Rs
C28: Balance at the beginning of the year | H28: =+J30 -> 714746 | I28: =(H28*10) -> 7147460 | J28: =J14 -> 714746 | K28: =K14 -> 7147460
C29: Add: Shares issued during the year | H29: 0 | I29: 0 | J29: 0 | K29: 0
C30: Balance at the close of the year | H30: =+H28+H29 -> 714746 | I30: =+I28+I29 -> 7147460 | J30: =+J28+J29 -> 714746 | K30: =+K28+K29 -> 7147460
C32: Particulars of Shareholders holding more than 5% share in the Company
C33: Particulars | H33: As at 31st March, 2023 | J33: As at 31st March, 2022
H34: % | I34: No. of Shares | J34: % | K34: No. of Shares
C36: Mr.S.Kumaran | H36: =I36/$H$30 -> 0.81194019 | I36: 580331 | J36: =K36/$J$30 -> 0.81194019 | K36: 580331 | M36: 1000
C37: Mrs.S.Rajathilagam | H37: =I37/$H$30 -> 0.092977086 | I37: 66455 | J37: =K37/$J$30 -> 0.092977086 | K37: 66455
C38: Other Shareholders | H38: =I38/$H$30 -> 0.095082729 | I38: 67960 | J38: =K38/$J$30 -> 0.095082729 | K38: 67960
B41: =B7+1 -> 4 | C41: RESERVES AND SURPLUS
C42: Particulars | J42: As at 31st March 2023 | K42: As at 31st March 2022 | L42: =1000 -> 1000
C43: General Reserve
C44: As per beginning of reporting period | J44: =K47 -> 57181439 | K44: =55167.6599717278*1000 -> 55167660
C45: Add: Transferred from Statement of Profit and Loss | J45: =-J56 -> 3453281.7 | K45: =2365.6311238313*1000 -> 2365631.1 | M45: =1/1000 -> 0.001 | O45: =1/1000 -> 0.001
C46: Less: Short Provision of Income Tax for the A.Y 2021-22 | J46: 0 | K46: =-351.8524*1000 -> -351852.4
C47: As per the end of the reporting period | J47: =SUM(J44:J46) -> 60634720 | K47: =SUM(K44:K46) -> 57181439
C49: Surplus in Statement of Profit & Loss
C50: As per beginning of reporting period | J50: =K57 -> 2.2920772e+08 | K50: =215064.50274555*1000 -> 2.150645e+08
C51: Add: Transferred from Statement of Profit and Loss Account | J51: =PL!C47 -> 34532817 | K51: =23656.311238313*1000 -> 23656311 | L51: ='Cash Flow'!E11 -> 43618707 | M51: =L59 -> 29172221
C52: Add: Prior period item
C53: Less: Interim dividend | J53: =(-'Trial Balance FY 22-23'!C19) -> -5360596 | K53: =-7147.46*1000 -> -7147460 | M53: 5360596
C54: Proposed dividend | M54: -1516347
C55: Dividend distribution tax Paid on Interim dividend | M55: 5912326
C56: Transferred to General Reserve | J56: =-J51*10% -> -3453281.7 | K56: =-K51*10% -> -2365631.1 | M56: =SUM(M51:M55) -> 38928796
C57: As per the end of the reporting period | J57: =SUM(J50:J56) -> 2.5492666e+08 | K57: =SUM(K50:K56) -> 2.2920772e+08
C59: Closing Balance | F59: Total | J59: =J47+J57 -> 3.1556138e+08 | K59: =K47+K57 -> 2.8638916e+08 | L59: =J59-K59 -> 29172221 | M59: =L51-L59 -> 14446486
M60: =M59+J53 -> 9085889.7
M61: =M60+PL!C34 -> 9085889.7
B62: =+B41+1 -> 5 | C62: OTHER LONG TERM LIABILITIES
C63: Particulars | J63: As at 31st March 2023 | K63: As at 31st March 2022
A64: OLTL RENT | C64: Retention Money | J64: =('Trial Balance FY 22-23'!E21) -> 32203.14 | K64: =32.20314*1000 -> 32203.14 | M64: =1/1000 -> 0.001
A65: OLTL SD | H65: Total | J65: =SUM(J64:J64) -> 32203.14 | K65: =SUM(K64:K64) -> 32203.14
B67: =+B62+1 -> 6 | C67: SHORT TERM BORROWINGS
C68: Particulars | J68: =J63 -> As at 31st March 2023 | K68: =K63 -> As at 31st March 2022
C69: (a) Loans and advances from related parties
C70: Secured | J70: =(SUMIF('Final TB for Finan'!$I$7:$I$901,Notes!$C70,'Final TB for Finan'!$G$7:$G$901)-SUMIF('Final TB for Finan'!$I$7:$I$901,Notes!$C70,'Final TB for Finan'!$F$7:$F$901)) -> 0 | K70: 0
C71: Unsecured (from Directors) | J71: =('Trial Balance FY 22-23'!E323+'Trial Balance FY 22-23'!E324) -> 11392871 | K71: =3041.369*1000 -> 3041369
A72: STB - LFD | C72: Relatives of Directors | J72: 0 | K72: 0 | N72: =+'TB2021(SEIL)'!F660 -> 4127
M73: =1/1000 -> 0.001
H74: Total | J74: =SUM(J70:J73) -> 11392871 | K74: =SUM(K70:K73) -> 3041369
B77: =B67+1 -> 7 | C77: TRADE PAYABLES
C78: Particulars | J78: =J63 -> As at 31st March 2023 | K78: =K63 -> As at 31st March 2022
L79: SUNDRY CREDITORS
C80: Micro,Small and Medium Enterprises and Others | J80: =(SUMIF('Sundry Creditors FY 22-23'!G28:G335,'Sundry Creditors FY 22-23'!G28,'Sundry Creditors FY 22-23'!E28:E335)-'Audit entries FY 22-23'!C14-'Audit entries FY 22-23'!C16-'Audit entries FY 22-23'!C18-'Audit entries FY 22-23'!C20-'Audit entries FY 22-23'!C24-'Audit entries FY 22-23'!C27-'Audit entries FY 22-23'!C30-'Audit entries FY 22-23'!C31-'Audit entries FY 22-23'!C33) -> 17772800 | K80: =6562.70984*1000 -> 6562709.8 | L80: CRS FOR PURCHSE | M80: 4952153.6 | N80: Previous year everything in msme
C81: & Others | J81: =(SUMIF('Final TB for Finan'!$I$7:$I$901,Notes!$C81,'Final TB for Finan'!$G$7:$G$901)-SUMIF('Final TB for Finan'!$I$7:$I$901,Notes!$C81,'Final TB for Finan'!$F$7:$F$901)) -> 0 | L81: CRS FOR SUBCONTRACTORS | M81: 1861912.9
L82: CRS FOR SUPPLIERS | M82: 2060076.4
H83: Total | J83: =SUM(J80:J82) -> 17772800 | K83: =SUM(K80:K82) -> 6562709.8 | M83: =SUM(M80:M82) -> 8874142.9
B86: =B77+1 -> 8 | C86: OTHER CURRENT LIABILITIES | L86: ='TB2021(SEIL)'!I41 -> cr for expenses | M86: ='TB2021(SEIL)'!J41 -> 372200 | N86: ='TB2021(SEIL)'!K41 -> 0 | O86: ='TB2021(SEIL)'!L41 -> 0 | P86: ='TB2021(SEIL)'!M41 -> 0 | Q86: ='TB2021(SEIL)'!N41 -> 0
C87: Particulars | J87: =J63 -> As at 31st March 2023 | K87: =K63 -> As at 31st March 2022 | L87: ='TB2021(SEIL)'!I44 -> crs for purchase | M87: ='TB2021(SEIL)'!J44 -> 5625490 | N87: ='TB2021(SEIL)'!K44 -> 4300342.6 | O87: ='TB2021(SEIL)'!L44 -> 4952153.6 | P87: ='TB2021(SEIL)'!M44 -> 651811 | Q87: ='TB2021(SEIL)'!N44 -> 0
C88: Payables - | L88: ='TB2021(SEIL)'!I45 -> 0 | M88: ='TB2021(SEIL)'!J45 -> 0 | N88: ='TB2021(SEIL)'!K45 -> 0 | O88: ='TB2021(SEIL)'!L45 -> 0 | P88: ='TB2021(SEIL)'!M45 -> 0 | Q88: ='TB2021(SEIL)'!N45 -> 0
C89: (i) Statutory remittances | L89: ='TB2021(SEIL)'!I46 -> crs for sub contract | M89: ='TB2021(SEIL)'!J46 -> 1887247 | N89: ='TB2021(SEIL)'!K46 -> 1861913 | O89: ='TB2021(SEIL)'!L46 -> 1861912.9 | P89: ='TB2021(SEIL)'!M46 -> 0 | Q89: ='TB2021(SEIL)'!N46 -> 0
C90: GST Payable | J90: =(-'Trial Balance FY 22-23'!E327+'Audit entries FY 22-23'!D74+'Audit entries FY 22-23'!D75+'Audit entries FY 22-23'!D76) -> -2730398.8 | K90: =6514.27159999999*1000 -> 6514271.6 | L90: ='TB2021(SEIL)'!I47 -> crs for supplier | M90: ='TB2021(SEIL)'!J47 -> 7048830.2 | N90: ='TB2021(SEIL)'!K47 -> 2060076.4 | O90: ='TB2021(SEIL)'!L47 -> 2060076.4 | P90: ='TB2021(SEIL)'!M47 -> 0 | Q90: ='TB2021(SEIL)'!N47 -> 0
A91: OCL STAX | C91: PF payable | J91: =('Sundry Creditors FY 22-23'!E39+'Sundry Creditors FY 22-23'!E40) -> 941907 | K91: =421.387*1000 -> 421387 | M91: =M92 -> 14933767
A92: OCL PFPAY | C92: TDS payable | J92: =('Sundry Creditors FY 22-23'!E55+'Sundry Creditors FY 22-23'!E56+'Audit entries FY 22-23'!D35+'Audit entries FY 22-23'!C3) -> 908499.75 | K92: =143.155*1000 -> 143155 | M92: =M87+M89+M90+M86 -> 14933767
C93: ESI Payable | J93: =('Sundry Creditors FY 22-23'!E22-'Audit entries FY 22-23'!C48) -> 51362.25 | K93: -
M94: =1/1000 -> 0.001
A95: OCL TDSPAY | C95: (ii)Rent Payable | J95: =('Sundry Creditors FY 22-23'!E44+'Sundry Creditors FY 22-23'!E48) -> 269694 | K95: =188.694*1000 -> 188694
C96: (iii)Salary Payable | J96: =('Sundry Creditors FY 22-23'!E37+'Sundry Creditors FY 22-23'!E46) -> 3600750 | K96: =6275.19*1000 -> 6275190 | M96: 1000
C97: (iv)Staff welfare payable | J97: =('Audit entries FY 22-23'!D49) -> 17120.75 | K97: 0
C98: (v) Audit Fees Payable | J98: =('Sundry Creditors FY 22-23'!E15+'Audit entries FY 22-23'!D4) -> 2914648.9 | K98: =2543.84893*1000 -> 2543848.9
A99: AFPAY | C99: (vi) Expenses Payable | J99: =('Trial Balance FY 22-23'!E151) -> 29611.5 | K99: =39.08*1000 -> 39080
A101: OCL EXPPAY
C102: Contract Advance | J102: =(SUM('Trial Balance FY 22-23'!E314:E317)-'Audit entries FY 22-23'!C86+'Audit entries FY 22-23'!D43) -> 16827138 | K102: =25262.92724*1000 -> 25262927 | L102: Previous year value to be changed
A103: OCL CADV | C103: Customer Advance | J103: 0
A104: OCL CUSADV | H104: Total | J104: =SUM(J90:J103) -> 22830334 | K104: =SUM(K90:K103) -> 41388554
B107: =B86+1 -> 9 | C107: SHORT TERM PROVISIONS
C108: Particulars | J108: =J63 -> As at 31st March 2023 | K108: =K63 -> As at 31st March 2022 | M108: 873749.9
C110: Provision for Income Tax | J110: =(IT!E46) -> 10965295 | K110: =8443.3364*1000 -> 8443336.4 | M110: =1/1000 -> 0.001
H111: Total | J111: =J110+J109 -> 10965295 | K111: =K110+K109 -> 8443336.4
B115: =B107+1 -> 10 | C115: Property, Plant and Equipments | L115: current tax exp
D116: Annexure - Note No.10 | L116: to proviison of income tax
B119: =B115+1 -> 11 | C119: NON-CURRENT INVESTMENTS
C120: Particulars | H120: No of Shares | I120: Face Value | J120: =J63 -> As at 31st March 2023 | K120: =K63 -> As at 31st March 2022
C121: 1. Quoted
C122: a) Investment in equity instruments
C123: (a) Tan India Ltd | H123: 250 | I123: 10 | J123: 0 | K123: 0
C124: (b) Rajapalayam Cement & Chemicals Limited | H124: 2500 | I124: 10 | J124: 0 | K124: 0
C125: (c) IOB | H125: 100 | I125: 24 | J125: 0 | K125: 0
C127: b) Investment in preference shares
C128: Ceat Financial Service Limited | H128: 50 | I128: 100 | J128: 0 | K128: 0
C129: 2. Unquoted
...

Sheet Trial Balance FY 22-23
A1: SATHIAPAL ENGINEERS (INDIA) PRIVATE LIMITED
A2: 57, 1ST Floor, Canal Road, Kilpauk Garden Colony
A3: Kilpauk,
A4: Chennai - 600 010
A5: CIN: U74210TN2002PLC048568
A6: Trial Balance
A7: 1-Apr-22 to 31-Mar-23 | F7: -1 | H7: CHAITANESWAR SSK - CA
B8: SATHIAPAL ENGINEERS (INDIA) PRIVATE LIMITED | H8: CHITTOOR CO-OP C.ADV
A9: Particulars | B9: 1-Apr-22 to 31-Mar-23 | H9: Contract Advance
B10: Opening | C10: Transactions | E10: Closing | H10: MRUDAGIRI SSK LTD C.ADV
B11: Balance | C11: Debit | D11: Credit | E11: Balance | G11: Schedule No | H11: Head for grouping
A12: Capital Account | B12: 7147460 | E12: 7147460
A13: SHARE CAPITAL | B13: 7147460 | E13: 7147460
A14: Current Liabilities | B14: 19664663 | C14: 3.8533943e+08 | D14: 3.7808403e+08 | E14: 12409265
A15: Crs. for Other Liabilities | C15: 99750 | D15: 99750
A16: Sathiapal Charitable Trust | C16: 99750 | D16: 99750
A17: Sundry Creditors | B17: 10777124 | C17: 3.6834093e+08 | D17: 3.6994087e+08 | E17: 12377062
A18: Audit Fees Payable | B18: 412000 | C18: 412000
A19: Dividend Payable | C19: 5360596 | D19: 5360596
A20: Provision for Income Tax -II | B20: 8443336 | C20: 11126150 | D20: 2682814 | G20: Provision for income tax
A21: Vijay Gowtham SD | B21: 32203.14 | E21: 32203.14 | G21: Retention Money
A22: Fixed Assets | B22: 55562041 | C22: 32735629 | D22: 14466624 | E22: 73831046
A23: BUILDINGS | B23: 868251 | E23: 868251
A24: Camera | B24: 121490 | E24: 121490
A25: COMPUTER | B25: 812487.8 | C25: 291739 | D25: 229185 | E25: 875041.8
A26: FURNITURE AND FITTINGS | B26: 275865.35 | D26: 26861 | E26: 249004.35
A27: PLANT & MACHINERY | B27: 44600067 | C27: 30609890 | D27: 12491543 | E27: 62718414
A28: VEHICLE | B28: 8883880.5 | C28: 1834000 | D28: 1719035 | E28: 8998845.5
A29: Current Assets | B29: 1.1698579e+08 | C29: 1.4358088e+09 | D29: 1.4967248e+09 | E29: 56069853
A30: Opening Stock
A31: Opening WIP
A32: Loans & Advances (Asset) | B32: 23379207 | E32: 23379207 | M32: 32735629 | N32: 32737399 | O32: =M32-N32 -> -1770
A33: GST Opening Balance Diff A/c | B33: 1210432 | E33: 1210432 | G33: (b) Other Current Assets | M33: -32756515
A34: Mrs. Rekha Bhansali A/c | B34: 1718775 | E34: 1718775 | G34: Other Advances
A35: SBI | B35: 20450000 | E35: 20450000 | G35: (ii) Deposits with banks
A36: Sundry Debtors | B36: 60572945 | C36: 4.9368072e+08 | D36: 5.4333855e+08 | E36: 10915111 | G36: Trade receivable
A37: Cash-in-Hand | B37: 271137.75 | C37: 13197136 | D37: 13023062 | E37: 445211.75
A38: CASH CHENNAI | B38: 3763 | C38: 4370911 | D38: 4365891 | E38: 8783 | G38: (a) Cash in hand at H.O
A39: Mvm Cash | B39: 267374.75 | C39: 8826225 | D39: 8657171 | E39: 436428.75 | G39: (a) Cash in hand at H.O
A40: Bank Accounts | B40: 25922027 | C40: 9.2538098e+08 | D40: 9.3720924e+08 | E40: 14093767
A41: CHENNAI BANKS | B41: 25815431 | C41: 9.1208611e+08 | D41: 9.2391704e+08 | E41: 13984501
A42: IB - CHETPET [SIL] | B42: 12797.11 | E42: 12797.11 | G42: (i) Current accounts
A43: ICICI - KILPAUK | B43: 67390.39 | C43: 3920000 | D43: 3987390.4 | G43: (i) Current accounts
A44: ICICI KILPAUK - SEIPL A/C | C44: 1068410.7 | D44: 984352 | E44: 84058.71 | G44: (i) Current accounts
A45: PNB - TAYLORS ROAD | B45: 102970.16 | C45: 5716113 | D45: 5787402.6 | E45: 31680.57 | G45: (i) Current accounts
A46: SBI - KILPAUK - I | B46: 14081256 | C46: 6.0346505e+08 | D46: 6.1033364e+08 | E46: 7212668.7 | G46: (i) Current accounts
A47: SBI - KILPAUK - II | B47: 5118782.4 | C47: 1.4188983e+08 | D47: 1.4588494e+08 | E47: 1123677.4 | G47: (i) Current accounts
A48: SBI - KILPAUK - III | B48: 5117221.1 | C48: 90158280 | D48: 90230973 | E48: 5044528.1 | G48: (i) Current accounts
A49: SBI Kilpauk SEIPL A/c | B49: 28464.52 | C49: 30589331 | D49: 30366834 | E49: 250961.62 | G49: (i) Current accounts
A50: SBI - KILPAUK [SIL] | B50: 21297.87 | E50: 21297.87 | G50: (i) Current accounts
A51: SBI - MAYILADUTHURAI | B51: 31547.18 | C51: 8400347 | D51: 8247509.5 | E51: 184384.66 | G51: (i) Current accounts
A52: SBI - New Avadi Road | B52: 1219586.3 | C52: 26878748 | D52: 28094006 | E52: 4328.24 | G52: (i) Current accounts
A53: South Indian Bank | B53: 14118 | E53: 14118 | G53: (i) Current accounts
A54: MVM BANK | B54: 106596.4 | C54: 13294864 | D54: 13292194 | E54: 109266.36
A55: IB - MYM [SIL] | B55: 11681.17 | E55: 11681.17 | G55: (i) Current accounts
A56: ICICI - Mayiladuthurai | B56: 27862.32 | D56: 27862.32 | G56: (i) Current accounts
A57: INDIAN BANK MVM | B57: 37007.77 | C57: 13294864 | D57: 13264332 | E57: 67540.05 | G57: (i) Current accounts
A58: INDIAN BANK MVM II A/C | B58: 18839.75 | E58: 18839.75 | G58: (i) Current accounts
A59: IOB MYM [S&C] | B59: 11037.14 | E59: 11037.14 | G59: (i) Current accounts
A60: L.V.B THIRUKADIYUR | B60: 168.25 | E60: 168.25 | G60: (i) Current accounts
A61: Interest Receivable | B61: 6840470 | C61: 3549989 | D61: 3153903 | E61: 7236556 | G61: (i) Interest accrued on deposits
A62: Branch / Divisions | B62: 2.7853075e+08 | C62: 1.5190258e+08 | D62: 152490371 | E62: 2.7794296e+08 | G62: =B62-B390 -> 7299639.5
A63: Abhijeet II Site | B63: 201 | E63: -201
A64: Acon (Lokmaniya Sugar) Site | B64: 34050 | E64: -34050
A65: AGA Infra Project Site 2022 | B65: 13505 | C65: 34594057 | D65: 34154560 | E65: 453002
A66: Ala Dandapani Cement II Site | B66: 1544 | E66: -1544
A67: AP Bava (JK) Site | B67: 2500 | E67: 2500
A68: ATC Tires Pvt Ltd Site | B68: 1300 | E68: 1300
A69: ATC Tires Vizag (21-22) Site | B69: 15866 | C69: 34425 | D69: 50291
A70: AVC ADD. CLASS ROOM SITE | B70: 800 | E70: -800
A71: AVC MBA BLOCK SITE | B71: 2727 | E71: 2727
A72: Bhubaneswar Silo Site | B72: 45000 | E72: 45000
A73: Boudh Distillery (Odisha) Site | B73: 79213 | C73: 1052704 | D73: 1131917
A74: CCCL Kallur Site - 2023 | C74: 343500 | D74: 222039 | E74: 121461
A75: CCCL-Vizag Site | B75: 66072 | C75: 136183 | D75: 200755 | E75: 1500
A76: CHENNAI OFFICE | B76: 18245.75 | C76: 1816396 | D76: 1855993 | E76: 57842.75
A77: Dalmia Ariyalur Site - 2023 | C77: 45500 | D77: 45500
A78: Dalmia Cement 2020 Site | B78: 330487 | C78: 115160 | D78: 244260 | E78: 201387
A79: Dalmia - Sattur Site (TN) | B79: 199744 | C79: 16690303 | D79: 16402133 | E79: 487914.36
A80: Girija Silo Site | B80: 2000 | E80: -2000
A81: Goel Construction II Site | B81: 65855 | E81: -65855
A82: Gujarat Ambuja Kolkatta Site | B82: 9355 | C82: 18741 | D82: 28096
A83: HRRL SITE | C83: 2279900 | D83: 1839233 | E83: 440667
A84: India Cement Andra Site | B84: 9995 | C84: 7000 | D84: 16995
A85: Indian Oil Corporation Ltd Site | B85: 445328 | C85: 2289458 | D85: 2734786
A86: ITC Bhadrachalam Telangana 2019 Site | B86: 13000 | E86: 13000
A87: ITC IV SITE | B87: 88647 | E87: 88647
A88: ITC Sarapakka II Site | B88: 32269 | E88: 32269
A89: Jindal Steel (Odisha 2021) Site | B89: 846985 | C89: 6783611 | D89: 7588084 | E89: 42512
A90: Jindal Urban Site | B90: 3000 | E90: -3000
A91: J.P.Balaji Chimney Site | B91: 75 | E91: 75
A92: J.P. Balaji II Silo Site | B92: 5578 | E92: 5578
A93: J.P.Cement Nalia Site | B93: 22244 | E93: 22244
A94: J.P.Cement Sidhi Chimney Site | B94: 18095 | E94: 18095
A95: J.P.Cement Sidhi Site | B95: 31056 | E95: 31056
A96: J.P. CEMENT WANAKBORI SITE | B96: 27512 | E96: 27512
A97: J.P. Jetty Site | B97: 2000 | E97: -2000
A98: Kamal Ultratech Tadipatri A.P Site | C98: 879585 | D98: 639418 | E98: 240167
A99: KEC - ACC CEMENT SITE | B99: 30323 | C99: 293788 | D99: 324111
A100: KEC(Balco) Chattishgarh Site | C100: 650743 | D100: 646743 | E100: 4000
...

Sheet FA Register Final
M1: 45016 | P1: 44832 | Q1: More than 180 Days | R1: less than 180 Days
B2: Class of Asset | C2: Asset Name | D2: A | E2: Date of Addition | F2: Amount as per Tally | G2: Useful Life | H2: Scrap Value | I2: Depreciable Amonunt | J2: Rate of Depreciation | K2: No of Days used in the F.Y | L2: Depreciation amount | M2: Closing WDV | N2: Accumulated Depreciation | O2: WDV As on 01-04-2022 | P2: Whether 1st Half or Second Half
C3: Computer 9 | D3: c | E3: 44652 | F3: 25000 | G3: 3 | H3: =F3*5% -> 1250 | I3: =F3-H3 -> 23750 | J3: 0.3167 | K3: =$M$1-E3 -> 364 | L3: =F3*J3*K3/365 -> 7895.8082 | M3: =F3-L3 -> 17104.192 | P3: More than 180 Days | S3: 4500
C4: Computer 10 | D4: c | E4: 44655 | F4: 43711.864 | G4: 3 | H4: =F4*5% -> 2185.5932 | I4: =F4-H4 -> 41526.271 | J4: 0.3167 | K4: =$M$1-E4 -> 361 | L4: =F4*J4*K4/365 -> 13691.837 | M4: =F4-L4 -> 30020.027 | P4: More than 180 Days | S4: 7868.1356
C5: Computer 12 | D5: c | E5: 44692 | F5: 29027.966 | G5: 3 | H5: =F5*5% -> 1451.3983 | I5: =F5-H5 -> 27576.568 | J5: 0.3167 | K5: =$M$1-E5 -> 324 | L5: =F5*J5*K5/365 -> 8160.5009 | M5: =F5-L5 -> 20867.465 | P5: More than 180 Days | S5: 5225.0339
C6: Computer 13 | D6: c | E6: 44803 | F6: 50847.458 | G6: 3 | H6: =F6*5% -> 2542.3729 | I6: =F6-H6 -> 48305.085 | J6: 0.3167 | K6: =$M$1-E6 -> 213 | L6: =F6*J6*K6/365 -> 9397.3206 | M6: =F6-L6 -> 41450.137 | P6: More than 180 Days | S6: 9152.5424
C7: Computer 14 | D7: c | E7: 44882 | F7: 41445.763 | G7: 3 | H7: =F7*5% -> 2072.2881 | I7: =F7-H7 -> 39373.475 | J7: 0.3167 | K7: =$M$1-E7 -> 134 | L7: =F7*J7*K7/365 -> 4818.8137 | M7: =F7-L7 -> 36626.949 | P7: less than 180 Days | S7: 7460.2373
C8: Computer 16 | D8: c | E8: 44947 | F8: 57203.39 | G8: 3 | H8: =F8*5% -> 2860.1695 | I8: =F8-H8 -> 54343.22 | J8: 0.3167 | K8: =$M$1-E8 -> 69 | L8: =F8*J8*K8/365 -> 3424.7278 | M8: =F8-L8 -> 53778.662 | P8: less than 180 Days | S8: 10296.61 | T8: =SUM(S3:S8) -> 44502.559 | U8: 291739 | V8: 247236.44 | W8: =U8-V8 -> 44502.56
C10: Plant & Machinery 38 | D10: p | E10: 44656 | F10: 369100 | G10: 15 | H10: =F10*5% -> 18455 | I10: =F10-H10 -> 350645 | J10: 0.0633 | K10: =$M$1-E10 -> 360 | L10: =F10*J10*K10/365 -> 23043.975 | M10: =F10-L10 -> 346056.03 | P10: More than 180 Days | S10: 66438
C11: Plant & Machinery 39 | D11: p | E11: 44659 | F11: 40500 | G11: 15 | H11: =F11*5% -> 2025 | I11: =F11-H11 -> 38475 | J11: 0.0633 | K11: =$M$1-E11 -> 357 | L11: =F11*J11*K11/365 -> 2507.4604 | M11: =F11-L11 -> 37992.54 | P11: More than 180 Days | S11: 7290
C12: Plant & Machinery 40 | D12: p | E12: 44662 | F12: 580226.27 | G12: 15 | H12: =F12*5% -> 29011.314 | I12: =F12-H12 -> 551214.96 | J12: 0.0633 | K12: =$M$1-E12 -> 354 | L12: =F12*J12*K12/365 -> 35621.442 | M12: =F12-L12 -> 544604.83 | P12: More than 180 Days | S12: 104440.73
C13: Plant & Machinery 41 | D13: p | E13: 44663 | F13: 215000 | G13: 15 | H13: =F13*5% -> 10750 | I13: =F13-H13 -> 204250 | J13: 0.0633 | K13: =$M$1-E13 -> 353 | L13: =F13*J13*K13/365 -> 13162.064 | M13: =F13-L13 -> 201837.94 | P13: More than 180 Days | S13: 38700
C14: Plant & Machinery 42 | D14: p | E14: 44664 | F14: 172870.34 | G14: 15 | H14: =F14*5% -> 8643.5169 | I14: =F14-H14 -> 164226.82 | J14: 0.0633 | K14: =$M$1-E14 -> 352 | L14: =F14*J14*K14/365 -> 10552.953 | M14: =F14-L14 -> 162317.39 | P14: More than 180 Days | S14: 31116.661
C15: Plant & Machinery 43 | D15: p | E15: 44666 | F15: 385858.47 | G15: 15 | H15: =F15*5% -> 19292.924 | I15: =F15-H15 -> 366565.55 | J15: 0.0633 | K15: =$M$1-E15 -> 350 | L15: =F15*J15*K15/365 -> 23421.081 | M15: =F15-L15 -> 362437.39 | P15: More than 180 Days | S15: 69454.525
C16: Plant & Machinery 44 | D16: p | E16: 44666 | F16: 1853980.5 | G16: 15 | H16: =F16*5% -> 92699.025 | I16: =F16-H16 -> 1761281.5 | J16: 0.0633 | K16: =$M$1-E16 -> 350 | L16: =F16*J16*K16/365 -> 112534.08 | M16: =F16-L16 -> 1741446.4 | P16: More than 180 Days | S16: 333716.49
C17: Plant & Machinery 45 | D17: p | E17: 44669 | F17: 176453.39 | G17: 15 | H17: =F17*5% -> 8822.6695 | I17: =F17-H17 -> 167630.72 | J17: 0.0633 | K17: =$M$1-E17 -> 347 | L17: =F17*J17*K17/365 -> 10618.675 | M17: =F17-L17 -> 165834.71 | P17: More than 180 Days | S17: 31761.61
C18: Plant & Machinery 46 | D18: p | E18: 44672 | F18: 1215244.9 | G18: 15 | H18: =F18*5% -> 60762.246 | I18: =F18-H18 -> 1154482.7 | J18: 0.0633 | K18: =$M$1-E18 -> 344 | L18: =F18*J18*K18/365 -> 72499.181 | M18: =F18-L18 -> 1142745.7 | P18: More than 180 Days | S18: 218744.08
C19: Plant & Machinery 47 | D19: p | E19: 44672 | F19: 240130.51 | G19: 15 | H19: =F19*5% -> 12006.525 | I19: =F19-H19 -> 228123.98 | J19: 0.0633 | K19: =$M$1-E19 -> 344 | L19: =F19*J19*K19/365 -> 14325.726 | M19: =F19-L19 -> 225804.78 | P19: More than 180 Days | S19: 43223.492
C20: Plant & Machinery 48 | D20: p | E20: 44673 | F20: 67500 | G20: 15 | H20: =F20*5% -> 3375 | I20: =F20-H20 -> 64125 | J20: 0.0633 | K20: =$M$1-E20 -> 343 | L20: =F20*J20*K20/365 -> 4015.2144 | M20: =F20-L20 -> 63484.786 | P20: More than 180 Days | S20: 12150
C21: Plant & Machinery 49 | D21: p | E21: 44674 | F21: 165000 | G21: 15 | H21: =F21*5% -> 8250 | I21: =F21-H21 -> 156750 | J21: 0.0633 | K21: =$M$1-E21 -> 342 | L21: =F21*J21*K21/365 -> 9786.3534 | M21: =F21-L21 -> 155213.65 | P21: More than 180 Days | S21: 29700
... C112: Plant & Machinery 140 | D112: p | E112: 44975 | F112: 280000 | G112: 15 | H112: =F112*5% -> 14000 | I112: =F112-H112 -> 266000 | J112: 0.0633 | K112: =$M$1-E112 -> 41 | L112: =F112*J112*K112/365 -> 1990.9151 | M112: =F112-L112 -> 278009.08 | P112: less than 180 Days | S112: 50400
C113: Plant & Machinery 141 | D113: p | E113: 44999 | F113: 121000 | G113: 15 | H113: =F113*5% -> 6050 | I113: =F113-H113 -> 114950 | J113: 0.0633 | K113: =$M$1-E113 -> 17 | L113: =F113*J113*K113/365 -> 356.73452 | M113: =F113-L113 -> 120643.27 | P113: less than 180 Days | S113: 21780 | T113: =SUM(S10:S113) -> 4447106.7 | U113: 30609890 | V113: 26162783 | W113: =U113-V113 -> 4447106.7
C114: Plant & Machinery | D114: p | E114: 44990 | F114: ='Sheet1 (2)'!M5 -> 361397.78 | G114: 15 | H114: =F114*5% -> 18069.889 | I114: =F114-H114 -> 343327.89 | J114: 0.0633 | K114: =$M$1-E114 -> 26 | L114: =F114*J114*K114/365 -> 1629.5574 | M114: =F114-L114 -> 359768.22 | P114: less than 180 Days
C115: Plant & Machinery | D115: p | E115: 44988 | F115: ='Sheet1 (2)'!M6 -> 437556.1 | G115: 15 | H115: =F115*5% -> 21877.805 | I115: =F115-H115 -> 415678.29 | J115: 0.0633 | K115: =$M$1-E115 -> 28 | L115: =F115*J115*K115/365 -> 2124.7245 | M115: =F115-L115 -> 435431.38 | P115: less than 180 Days
C116: Plant & Machinery | D116: p | E116: 44979 | F116: ='Sheet1 (2)'!M7 -> 99589 | G116: 15 | H116: =F116*5% -> 4979.45 | I116: =F116-H116 -> 94609.55 | J116: 0.0633 | K116: =$M$1-E116 -> 37 | L116: =F116*J116*K116/365 -> 639.03396 | M116: =F116-L116 -> 98949.966 | P116: less than 180 Days
C117: Plant & Machinery | D117: p | E117: 44950 | F117: ='Sheet1 (2)'!M8 -> 209912.62 | G117: 15 | H117: =F117*5% -> 10495.631 | I117: =F117-H117 -> 199416.99 | J117: 0.0633 | K117: =$M$1-E117 -> 66 | L117: =F117*J117*K117/365 -> 2402.6656 | M117: =F117-L117 -> 207509.95 | P117: less than 180 Days
C118: Plant & Machinery | D118: p | E118: 44939 | F118: ='Sheet1 (2)'!M9 -> 150083.78 | G118: 15 | H118: =F118*5% -> 7504.189 | I118: =F118-H118 -> 142579.59 | J118: 0.0633 | K118: =$M$1-E118 -> 77 | L118: =F118*J118*K118/365 -> 2004.1736 | M118: =F118-L118 -> 148079.61 | P118: less than 180 Days
C119: Plant & Machinery | D119: p | E119: 44912 | F119: ='Sheet1 (2)'!M10 -> 276562.22 | G119: 15 | H119: =F119*5% -> 13828.111 | I119: =F119-H119 -> 262734.11 | J119: 0.0633 | K119: =$M$1-E119 -> 104 | L119: =F119*J119*K119/365 -> 4988.1217 | M119: =F119-L119 -> 271574.1 | P119: less than 180 Days
C120: Plant & Machinery | D120: p | E120: 44855 | F120: ='Sheet1 (2)'!M11 -> 124148 | G120: 15 | H120: =F120*5% -> 6207.4 | I120: =F120-H120 -> 117940.6 | J120: 0.0633 | K120: =$M$1-E120 -> 161 | L120: =F120*J120*K120/365 -> 3466.3822 | M120: =F120-L120 -> 120681.62 | P120: less than 180 Days
C121: Plant & Machinery | D121: p | E121: 44854 | F121: ='Sheet1 (2)'!M12 -> 462841.62 | G121: 15 | H121: =F121*5% -> 23142.081 | I121: =F121-H121 -> 439699.54 | J121: 0.0633 | K121: =$M$1-E121 -> 162 | L121: =F121*J121*K121/365 -> 13003.44 | M121: =F121-L121 -> 449838.18 | P121: less than 180 Days
C122: Plant & Machinery | D122: p | E122: 44811 | F122: ='Sheet1 (2)'!M13 -> 420914.2 | G122: 15 | H122: =F122*5% -> 21045.71 | I122: =F122-H122 -> 399868.49 | J122: 0.0633 | K122: =$M$1-E122 -> 205 | L122: =F122*J122*K122/365 -> 14964.365 | M122: =F122-L122 -> 405949.84 | P122: More than 180 Days
C123: Plant & Machinery | D123: p | E123: 44751 | F123: ='Sheet1 (2)'!M14 -> 597253.56 | G123: 15 | H123: =F123*5% -> 29862.678 | I123: =F123-H123 -> 567390.88 | J123: 0.0633 | K123: =$M$1-E123 -> 265 | L123: =F123*J123*K123/365 -> 27448.301 | M123: =F123-L123 -> 569805.26 | P123: More than 180 Days
C124: Plant & Machinery | D124: p | E124: 44767 | F124: ='Sheet1 (2)'!M15 -> 548668.56 | G124: 15 | H124: =F124*5% -> 27433.428 | I124: =F124-H124 -> 521235.13 | J124: 0.0633 | K124: =$M$1-E124 -> 249 | L124: =F124*J124*K124/365 -> 23693.012 | M124: =F124-L124 -> 524975.55 | P124: More than 180 Days
C125: Plant & Machinery | D125: p | E125: 44652 | F125: ='Sheet1 (2)'!M16 -> 161166.9 | G125: 15 | H125: =F125*5% -> 8058.345 | I125: =F125-H125 -> 153108.55 | J125: 0.0633 | K125: =$M$1-E125 -> 364 | L125: =F125*J125*K125/365 -> 10173.914 | M125: =F125-L125 -> 150992.99 | P125: More than 180 Days
C126: Plant & Machinery | D126: p | E126: 44666 | F126: ='Sheet1 (2)'!M20 -> 21006.76 | G126: 15 | H126: =F126*5% -> 1050.338 | I126: =F126-H126 -> 19956.422 | J126: 0.0633 | K126: =$M$1-E126 -> 350 | L126: =F126*J126*K126/365 -> 1275.0816 | M126: =F126-L126 -> 19731.678 | P126: More than 180 Days
C127: Plant & Machinery | D127: p | E127: 44695 | F127: ='Sheet1 (2)'!M21 -> 13794.04 | G127: 15 | H127: =F127*5% -> 689.702 | I127: =F127-H127 -> 13104.338 | J127: 0.0633 | K127: =$M$1-E127 -> 321 | L127: =F127*J127*K127/365 -> 767.90476 | M127: =F127-L127 -> 13026.135 | P127: More than 180 Days
C128: Plant & Machinery | D128: p | E128: 44704 | F128: ='Sheet1 (2)'!M22 -> 66991.54 | G128: 15 | H128: =F128*5% -> 3349.577 | I128: =F128-H128 -> 63641.963 | J128: 0.0633 | K128: =$M$1-E128 -> 312 | L128: =F128*J128*K128/365 -> 3624.8113 | M128: =F128-L128 -> 63366.729 | P128: More than 180 Days
C129: Plant & Machinery | D129: p | E129: 44794 | F129: ='Sheet1 (2)'!M23 -> 39446.1 | G129: 15 | H129: =F129*5% -> 1972.305 | I129: =F129-H129 -> 37473.795 | J129: 0.0633 | K129: =$M$1-E129 -> 222 | L129: =F129*J129*K129/365 -> 1518.6857 | M129: =F129-L129 -> 37927.414 | P129: More than 180 Days
C130: Plant & Machinery | D130: p | E130: 44830 | F130: ='Sheet1 (2)'!M24 -> 94993.72 | G130: 15 | H130: =F130*5% -> 4749.686 | I130: =F130-H130 -> 90244.034 | J130: 0.0633 | K130: =$M$1-E130 -> 186 | L130: =F130*J130*K130/365 -> 3064.2111 | M130: =F130-L130 -> 91929.509 | P130: More than 180 Days
C131: Plant & Machinery | D131: p | E131: 44926 | F131: ='Sheet1 (2)'!M25 -> 24688.56 | G131: 15 | H131: =F131*5% -> 1234.428 | I131: =F131-H131 -> 23454.132 | J131: 0.0633 | K131: =$M$1-E131 -> 90 | L131: =F131*J131*K131/365 -> 385.34446 | M131: =F131-L131 -> 24303.216 | P131: less than 180 Days
C132: Plant & Machinery | D132: p | E132: 44926 | F132: ='Sheet1 (2)'!M26 -> 6637.9 | G132: 15 | H132: =F132*5% -> 331.895 | I132: =F132-H132 -> 6306.005 | J132: 0.0633 | K132: =$M$1-E132 -> 90 | L132: =F132*J132*K132/365 -> 103.6058 | M132: =F132-L132 -> 6534.2942 | P132: less than 180 Days
C133: Plant & Machinery | D133: p | E133: 44931 | F133: ='Sheet1 (2)'!M27 -> 59023.6 | G133: 15 | H133: =F133*5% -> 2951.18 | I133: =F133-H133 -> 56072.42 | J133: 0.0633 | K133: =$M$1-E133 -> 85 | L133: =F133*J133*K133/365 -> 870.07255 | M133: =F133-L133 -> 58153.527 | P133: less than 180 Days
C134: Plant & Machinery | D134: p | E134: 44945 | F134: ='Sheet1 (2)'!M28 -> 44658.02 | G134: 15 | H134: =F134*5% -> 2232.901 | I134: =F134-H134 -> 42425.119 | J134: 0.0633 | K134: =$M$1-E134 -> 71 | L134: =F134*J134*K134/365 -> 549.88093 | M134: =F134-L134 -> 44108.139 | P134: less than 180 Days
C135: Plant & Machinery | D135: p | E135: 44946 | F135: ='Sheet1 (2)'!M29 -> 56261.02 | G135: 15 | H135: =F135*5% -> 2813.051 | I135: =F135-H135 -> 53447.969 | J135: 0.0633 | K135: =$M$1-E135 -> 70 | L135: =F135*J135*K135/365 -> 682.99337 | M135: =F135-L135 -> 55578.027 | P135: less than 180 Days
C136: Plant & Machinery | D136: p | E136: 44974 | F136: ='Sheet1 (2)'!M30 -> 28444.16 | G136: 15 | H136: =F136*5% -> 1422.208 | I136: =F136-H136 -> 27021.952 | J136: 0.0633 | K136: =$M$1-E136 -> 42 | L136: =F136*J136*K136/365 -> 207.18259 | M136: =F136-L136 -> 28236.977 | P136: less than 180 Days
C137: Plant & Machinery | D137: p | E137: 44982 | F137: ='Sheet1 (2)'!M31 -> 53313.12 | G137: 15 | H137: =F137*5% -> 2665.656 | I137: =F137-H137 -> 50647.464 | J137: 0.0633 | K137: =$M$1-E137 -> 34 | L137: =F137*J137*K137/365 -> 314.35753 | M137: =F137-L137 -> 52998.762 | P137: less than 180 Days
... C143: Plant & Machinery | D143: p | E143: 44991 | F143: ='Sheet1 (2)'!M37 -> 81994.26 | G143: 15 | H143: =F143*5% -> 4099.713 | I143: =F143-H143 -> 77894.547 | J143: 0.0633 | K143: =$M$1-E143 -> 25 | L143: =F143*J143*K143/365 -> 355.49566 | M143: =F143-L143 -> 81638.764 | P143: less than 180 Days
C148: Vehicle 3 | D148: v | E148: 44841 | F148: 1050000 | G148: 8 | H148: =F148*5% -> 52500 | I148: =F148-H148 -> 997500 | J148: 0.1188 | K148: =$M$1-E148 -> 175 | L148: =F148*J148*K148/365 -> 59806.849 | M148: =F148-L148 -> 990193.15 | P148: less than 180 Days | S148: 0
C149: Vehicle 4 | D149: v | E149: 44883 | F149: 491884 | G149: 8 | H149: =F149*5% -> 24594.2 | I149: =F149-H149 -> 467289.8 | J149: 0.1188 | K149: =$M$1-E149 -> 133 | L149: =F149*J149*K149/365 -> 21293.052 | M149: =F149-L149 -> 470590.95 | P149: less than 180 Days | S149: 137116 | U149: 137116 | V149: =U149-S149 -> 0
C150: Vehicle 5 | D150: v | E150: 44900 | F150: 155000 | G150: 8 | H150: =F150*5% -> 7750 | I150: =F150-H150 -> 147250 | J150: 0.1188 | K150: =$M$1-E150 -> 116 | L150: =F150*J150*K150/365 -> 5852.1205 | M150: =F150-L150 -> 149147.88 | P150: less than 180 Days | S150: 0 | T150: =SUM(S148:S150) -> 137116
A157: For Original Assets | M157: 45016
B158: Class of Asset | C158: Asset Name | E158: Date of Addition | F158: Amount as per Tally | G158: Useful Life | H158: Scrap Value | I158: Depreciable Amonunt | J158: Rate of Depreciation | K158: No of Days used in the F.Y | L158: Depreciation amount | M158: Closing WDV | N158: Accumulated Depreciation | O158: WDV As on 01-04-2022
B159: OG | C159: Computers | E159: 43922 | F159: 1366433.6 | G159: 3 | H159: =F159*5% -> 68321.678 | I159: =F159-H159 -> 1298111.9 | J159: 0.3167 | K159: =365 -> 365 | L159: 13690.417 | M159: =O159-L159 -> 68321.678 | N159: =505953.75266+L159 -> 519644.17 | O159: 82012.095
B160: Additions in F.Y 2020-21 | C160: Computers | E160: 44092 | F160: 31750 | G160: 3 | H160: =F160*5% -> 1587.5 | I160: =F160-H160 -> 30162.5 | J160: 0.3167 | K160: =365 -> 365 | L160: =F160*J160*K160/365 -> 10055.225 | M160: =O160-L160 -> 6562.8845 | N160: =5076.66552511415+M160 -> 11639.55 | O160: 16618.109
B161: Additions in F.Y 2020-21 | C161: Computers | E161: 44094 | F161: 26400 | G161: 3 | H161: =F161*5% -> 1320 | I161: =F161-H161 -> 25080 | J161: 0.3167 | K161: =365 -> 365 | L161: =F161*J161*K161/365 -> 8360.88 | M161: =O161-L161 -> 5500.5304 | N161: =4177.70958904109+M161 -> 9678.24 | O161: 13861.41
B162: Additions in F.Y 2020-21 | C162: Computers | E162: 44190 | F162: 88800 | G162: 3 | H162: =F162*5% -> 4440 | I162: =F162-H162 -> 84360 | J162: 0.3167 | K162: =365 -> 365 | L162: =F162*J162*K162/365 -> 28122.96 | M162: =O162-L162 -> 25527.932 | N162: =7026.14794520548+M162 -> 32554.08 | O162: 53650.892
B163: Additions in F.Y 2020-21 | C163: Computers | E163: 44232 | F163: 29000 | G163: 3 | H163: =F163*5% -> 1450 | I163: =F163-H163 -> 27550 | J163: 0.3167 | K163: =365 -> 365 | L163: =F163*J163*K163/365 -> 9184.3 | M163: =O163-L163 -> 9340.7014 | N163: =1290.69863013699+L163 -> 10474.999 | O163: 18525.001
B164: Additions in F.Y 2020-21 | C164: Computers | E164: 44245 | F164: 30400 | G164: 3 | H164: =F164*5% -> 1520 | I164: =F164-H164 -> 28880 | J164: 0.3167 | K164: =365 -> 365 | L164: =F164*J164*K164/365 -> 9627.68 | M164: =O164-L164 -> 10117.356 | N164: =1027.28401826484+L164 -> 10654.964 | O164: 19745.036
B165: Additions in F.Y 2020-21 | C165: Computers | E165: 44259 | F165: 19470 | G165: 3 | H165: =F165*5% -> 973.5 | I165: =F165-H165 -> 18496.5 | J165: 0.3167 | K165: =365 -> 365 | L165: =F165*J165*K165/365 -> 6166.149 | M165: =O165-L165 -> 6704.4278 | N165: =433.274178082192+L165 -> 6599.4232 | O165: 12870.577
B166: Additions in F.Y 2020-21 | C166: Computers | E166: 44264 | F166: 15989 | G166: 3 | H166: =F166*5% -> 799.45 | I166: =F166-H166 -> 15189.55 | J166: 0.3167 | K166: =365 -> 365 | L166: =F166*J166*K166/365 -> 5063.7163 | M166: =O166-L166 -> 5571.65 | N166: =289.917356167525+L166 -> 5353.6337 | O166: 10635.366
B167: Additions in F.Y 2020-21 | C167: Computers | E167: 44286 | F167: 13280 | G167: 3 | H167: =F167*5% -> 664 | I167: =F167-H167 -> 12616 | J167: 0.3167 | K167: =365 -> 365 | L167: =F167*J167*K167/365 -> 4205.776 | M167: =O167-L167 -> 4868.448 | N167: 0 | O167: 9074.224
B169: OG | C169: Plant and machinery | E169: 43922 | F169: 48260368 | G169: 15 | H169: =F169*5% -> 2413018.4 | I169: =F169-H169 -> 45847349 | J169: 0.0633 | K169: =365 -> 365 | L169: =F169*J169*K169/365 -> 3054881.3 | M169: =O169-L169 -> 35754443 | N169: =3302608.55654645+L169 -> 6357489.8 | O169: 38809324
B170: Additions in F.Y 2020-21 | C170: Plant and machinery | E170: 44020 | F170: 1062000 | G170: 15 | H170: =F170*5% -> 53100 | I170: =F170-H170 -> 1008900 | J170: 0.0633 | K170: =365 -> 365 | L170: =F170*J170*K170/365 -> 67224.6 | M170: =O170-L170 -> 813760.17 | N170: =46566.0328767123+L170 -> 113790.63 | O170: 880984.77
B171: Additions in F.Y 2020-21 | C171: Plant and machinery | E171: 44072 | F171: 22267 | G171: 15 | H171: =F171*5% -> 1113.35 | I171: =F171-H171 -> 21153.65 | J171: 0.0633 | K171: =365 -> 365 | L171: =F171*J171*K171/365 -> 1409.5011 | M171: =O171-L171 -> 17253.014 | N171: =785.482505027219+L171 -> 2194.9836 | O171: 18662.515
B172: Additions in F.Y 2020-21 | C172: Plant and machinery | E172: 44095 | F172: 5048 | G172: 15 | H172: =F172*5% -> 252.4 | I172: =F172-H172 -> 4795.6 | J172: 0.0633 | K172: =365 -> 365 | L172: =F172*J172*K172/365 -> 319.5384 | M172: =O172-L172 -> 3930.4512 | N172: =158.933629223744+L172 -> 478.47203 | O172: 4249.9896
B173: Additions in F.Y 2020-21 | C173: Plant and machinery | E173: 44111 | F173: 224200 | G173: 15 | H173: =F173*5% -> 11210 | I173: =F173-H173 -> 212990 | J173: 0.0633 | K173: =365 -> 365 | L173: =F173*J173*K173/365 -> 14191.86 | M173: =O173-L173 -> 175156.92 | N173: =6467.50456621005+L173 -> 20659.365 | O173: 189348.78
B174: Additions in F.Y 2020-21 | C174: Plant and machinery | E174: 44140 | F174: 224200 | G174: 15 | H174: =F174*5% -> 11210 | I174: =F174-H174 -> 212990 | J174: 0.0633 | K174: =365 -> 365 | L174: =F174*J174*K174/365 -> 14191.86 | M174: =O174-L174 -> 176228.67 | N174: =5395.74666666667+L174 -> 19587.607 | O174: 190420.53
B175: Additions in F.Y 2020-21 | C175: Plant and machinery | E175: 44194 | F175: 555190 | G175: 15 | H175: =F175*5% -> 27759.5 | I175: =F175-H175 -> 527430.5 | J175: 0.0633 | K175: =365 -> 365 | L175: =F175*J175*K175/365 -> 35143.527 | M175: =O175-L175 -> 441339.8 | N175: =8419.62113242009+L175 -> 43563.148 | O175: 476483.32
B176: Additions in F.Y 2020-21 | C176: Plant and machinery | E176: 44272 | F176: 359900 | G176: 15 | H176: =F176*5% -> 17995 | I176: =F176-H176 -> 341905 | J176: 0.0633 | K176: =365 -> 365 | L176: =F176*J176*K176/365 -> 22781.67 | M176: =O176-L176 -> 290724.43 | N176: =830.563744292238+L176 -> 23612.234 | O176: 313506.1
B177: Additions in F.Y 2020-21 | C177: Plant and machinery | E177: 44276 | F177: 7000 | G177: 15 | H177: =F177*5% -> 350 | I177: =F177-H177 -> 6650 | J177: 0.0633 | K177: =365 -> 365 | L177: =F177*J177*K177/365 -> 443.1 | M177: =O177-L177 -> 5659.1612 | N177: =11.5388127853881+L177 -> 454.63881 | O177: 6102.2612
B178: Additions in F.Y 2020-21 | C178: Plant and machinery | E178: 44279 | F178: 1395972 | G178: 15 | H178: =F178*5% -> 69798.6 | I178: =F178-H178 -> 1326173.4 | J178: 0.0633 | K178: =365 -> 365 | L178: =F178*J178*K178/365 -> 88365.028 | M178: =O178-L178 -> 1129266.1 | N178: =1610.78595616438+L178 -> 89975.814 | O178: 1217631.2
B180: OG | C180: Furniture | E180: 43922 | F180: 681807 | G180: 10 | H180: =F180*5% -> 34090.35 | I180: =F180-H180 -> 647716.65 | J180: 0.095 | K180: =365 -> 365 | L180: 0 | M180: =O180-L180 -> 34090 | N180: 647717 | O180: =F180-N180 -> 34090
B182: OG | C182: Motor Vehicle | E182: 43922 | F182: 4630774.8 | G182: 8 | H182: =F182*5% -> 231538.74 | I182: =F182-H182 -> 4399236 | J182: 0.1155 | K182: 365 | L182: =F182*J182*K182/365 -> 534854.48 | M182: =O182-L182 -> 2525309.2 | N182: =549618.753024+L182 -> 1084473.2 | O182: 3060163.7
C183: Sale as on 18-11-2022 | F183: 865919 | G183: 8 | H183: =F183*5% -> 43295.95 | I183: =F183-H183 -> 822623.05 | J183: 0.1155 | K183: 365 | L183: 0 | M183: 43295 | N183: =I183 -> 822623.05 | O183: =N183 -> 822623.05
C184: Motor Vehicle | F184: =F182-F183 -> 3764855.8 | H184: =H182-H183 -> 188242.79 | I184: =I182-I183 -> 3576613 | M184: =M182-M183 -> 2482014.2 | N184: =N182-N183 -> 261850.19
B186: Class of Asset | C186: Asset Name | E186: Date of Addition | F186: Amount as per Tally | G186: Useful Life | H186: Scrap Value | I186: Depreciable Amonunt | J186: Rate of Depreciation | K186: No of Days used in the F.Y | L186: Depreciation amount | M186: Previous year dep | N186: Accumulated Depreciation | O186: WDV As on 01-04-2022 | P186: Closing WDV
B187: ADDITIONS IN FY 21-22
B188: Office Equipments | C188: Camera | E188: 44307 | F188: 121490 | G188: 5 | H188: =F188*5% -> 6074.5 | I188: =F188-H188 -> 115415.5 | J188: 0.19 | K188: 365 | L188: =F188*J188*K188/365 -> 23083.1 | M188: 21818.273 | N188: =L188+M188 -> 44901.373 | O188: 99671.727 | P188: =F188-N188 -> 76588.627
P189: =F189-N189 -> 0
B190: Computers | C190: Computer 1 | E190: 44445 | F190: 60250 | G190: 3 | H190: =F190*5% -> 3012.5 | I190: =F190-H190 -> 57237.5 | J190: 0.3167 | K190: 365 | L190: =F190*J190*K190/365 -> 19081.175 | M190: 10821.379 | N190: =L190+M190 -> 29902.554 | O190: 49428.621 | P190: =F190-N190 -> 30347.446
C191: Computer 2 | E191: 44572 | F191: 44800 | G191: 3 | H191: =F191*5% -> 2240 | I191: =F191-H191 -> 42560 | J191: 0.3167 | K191: 365 | L191: =F191*J191*K191/365 -> 14188.16 | M191: 3109.7337 | N191: =L191+M191 -> 17297.894 | O191: 41690.266 | P191: =F191-N191 -> 27502.106
C192: Computer 3 | E192: 44572 | F192: 48800 | G192: 3 | H192: =F192*5% -> 2440 | I192: =F192-H192 -> 46360 | J192: 0.3167 | K192: 365 | L192: =F192*J192*K192/365 -> 15454.96 | M192: 3387.3885 | N192: =L192+M192 -> 18842.348 | O192: 45412.612 | P192: =F192-N192 -> 29957.652
C193: Computer 4 | E193: 44590 | F193: 92520 | G193: 3 | H193: =F193*5% -> 4626 | I193: =F193-H193 -> 87894 | J193: 0.3167 | K193: 365 | L193: =F193*J193*K193/365 -> 29301.084 | M193: 4977.1704 | N193: =L193+M193 -> 34278.254 | O193: 87542.83 | P193: =F193-N193 -> 58241.746
C194: Computer 5 | E194: 44590 | F194: 11977 | G194: 3 | H194: =F194*5% -> 598.85 | I194: =F194-H194 -> 11378.15 | J194: 0.3167 | K194: 365 | L194: =F194*J194*K194/365 -> 3793.1159 | M194: 644.3101 | N194: =L194+M194 -> 4437.426 | O194: 11332.69 | P194: =F194-N194 -> 7539.574
C195: Computer 6 | E195: 44600 | F195: 144430 | G195: 3 | H195: =F195*5% -> 7221.5 | I195: =F195-H195 -> 137208.5 | J195: 0.3167 | K195: 365 | L195: =F195*J195*K195/365 -> 45740.981 | M195: 6516.5233 | N195: =L195+M195 -> 52257.504 | O195: 137913.48 | P195: =F195-N195 -> 92172.496
C196: Computer 7 | E196: 44616 | F196: 59969 | G196: 3 | H196: =F196*5% -> 2998.45 | I196: =F196-H196 -> 56970.55 | J196: 0.3167 | K196: 365 | L196: =F196*J196*K196/365 -> 18992.182 | M196: 1873.2015 | N196: =L196+M196 -> 20865.384 | O196: 58095.798 | P196: =F196-N196 -> 39103.616
C197: Computer 8 | E197: 44616 | F197: 7800 | G197: 3 | H197: =F197*5% -> 390 | I197: =F197-H197 -> 7410 | J197: 0.3167 | K197: 365 | L197: =F197*J197*K197/365 -> 2470.26 | M197: 243.64208 | N197: =L197+M197 -> 2713.9021 | O197: 7556.3579 | P197: =F197-N197 -> 5086.0979
P198: =F198-N198 -> 0
B199: Furniture & Fittings | C199: Furniture 1 | E199: 44546 | F199: 120941 | G199: 10 | H199: =F199*5% -> 6047.05 | I199: =F199-H199 -> 114893.95 | J199: 0.095 | K199: 365 | L199: =F199*J199*K199/365 -> 11489.395 | M199: 3336.6462 | N199: =L199+M199 -> 14826.041 | O199: 117604.35 | P199: =F199-N199 -> 106114.96
C200: Furniture 2 | E200: 44585 | F200: 52333 | G200: 10 | H200: =F200*5% -> 2616.65 | I200: =F200-H200 -> 49716.35 | J200: 0.095 | K200: 365 | L200: =F200*J200*K200/365 -> 4971.635 | M200: 912.60149 | N200: =L200+M200 -> 5884.2365 | O200: 51420.399 | P200: =F200-N200 -> 46448.764
C201: Furniture 3 | E201: 44600 | F201: 26202 | G201: 10 | H201: =F201*5% -> 1310.1 | I201: =F201-H201 -> 24891.9 | J201: 0.095 | K201: 365 | L201: =F201*J201*K201/365 -> 2489.19 | M201: 354.62433 | N201: =L201+M201 -> 2843.8143 | O201: 25847.376 | P201: =F201-N201 -> 23358.186
C202: Furniture 4 | E202: 44608 | F202: 99195 | G202: 10 | H202: =F202*5% -> 4959.75 | I202: =F202-H202 -> 94235.25 | J202: 0.095 | K202: 365 | L202: =F202*J202*K202/365 -> 9423.525 | M202: 1135.9866 | N202: =L202+M202 -> 10559.512 | O202: 98059.013 | P202: =F202-N202 -> 88635.488
C203: Furniture 5 | E203: 44608 | F203: 18328 | G203: 10 | H203: =F203*5% -> 916.4 | I203: =F203-H203 -> 17411.6 | J203: 0.095 | K203: 365 | L203: =F203*J203*K203/365 -> 1741.16 | M203: 209.89326 | N203: =L203+M203 -> 1951.0533 | O203: 18118.107 | P203: =F203-N203 -> 16376.947
K204: 365 | P204: =F204-N204 -> 0
P205: =F205-N205 -> 0
B206: Plant & Machinery | C206: Plant & Machinery 1 | E206: 44287 | F206: 641330 | G206: 15 | H206: =F206*5% -> 32066.5 | I206: =F206-H206 -> 609263.5 | J206: 0.0633 | K206: 365 | L206: =F206*J206*K206/365 -> 40596.189 | M206: 40596.189 | N206: =L206+M206 -> 81192.378 | O206: 600733.81 | P206: =F206-N206 -> 560137.62
C207: Plant & Machinery 2 | E207: 44288 | F207: 443048 | G207: 15 | H207: =F207*5% -> 22152.4 | I207: =F207-H207 -> 420895.6 | J207: 0.0633 | K207: 365 | L207: =F207*J207*K207/365 -> 28044.938 | M207: 27968.103 | N207: =L207+M207 -> 56013.041 | O207: 415079.9 | P207: =F207-N207 -> 387034.96
C208: Plant & Machinery 3 | E208: 44293 | F208: 150626 | G208: 15 | H208: =F208*5% -> 7531.3 | I208: =F208-H208 -> 143094.7 | J208: 0.0633 | K208: 365 | L208: =F208*J208*K208/365 -> 9534.6258 | M208: 9377.8922 | N208: =L208+M208 -> 18912.518 | O208: 141248.11 | P208: =F208-N208 -> 131713.48
C209: Plant & Machinery 4 | E209: 44306 | F209: 50025 | G209: 15 | H209: =F209*5% -> 2501.25 | I209: =F209-H209 -> 47523.75 | J209: 0.0633 | K209: 365 | L209: =F209*J209*K209/365 -> 3166.5825 | M209: 3001.7467 | N209: =L209+M209 -> 6168.3292 | O209: 47023.253 | P209: =F209-N209 -> 43856.671
C210: Plant & Machinery 5 | E210: 44348 | F210: 141234 | G210: 15 | H210: =F210*5% -> 7061.7 | I210: =F210-H210 -> 134172.3 | J210: 0.0633 | K210: 365 | L210: =F210*J210*K210/365 -> 8940.1122 | M210: 7446.0113 | N210: =L210+M210 -> 16386.123 | O210: 133787.99 | P210: =F210-N210 -> 124847.88
...

Sheet Sheet8
A1: Class of Asset | B1: Asset Name | C1: A | D1: Date of Addition | E1: Amount as per Tally | F1: Useful Life | G1: Scrap Value | H1: Depreciable Amonunt | I1: Rate of Depreciation | J1: No of Days used in the F.Y | K1: Depreciation amount | L1: Closing WDV | M1: Accumulated Depreciation | N1: WDV As on 01-04-2022 | O1: Whether 1st Half or Second Half
B2: Computer 9 | C2: c | D2: 44652 | E2: 25000 | F2: 3 | G2: 1250 | H2: 23750 | I2: 0.3167 | J2: 364 | K2: 7895.8082 | L2: 17104.192 | O2: More than 180 Days
B3: Computer 10 | C3: c | D3: 44655 | E3: 43711.864 | F3: 3 | G3: 2185.5932 | H3: 41526.271 | I3: 0.3167 | J3: 361 | K3: 13691.837 | L3: 30020.027 | O3: More than 180 Days
B4: Computer 12 | C4: c | D4: 44692 | E4: 29027.966 | F4: 3 | G4: 1451.3983 | H4: 27576.568 | I4: 0.3167 | J4: 324 | K4: 8160.5009 | L4: 20867.465 | O4: More than 180 Days
B5: Computer 13 | C5: c | D5: 44803 | E5: 50847.458 | F5: 3 | G5: 2542.3729 | H5: 48305.085 | I5: 0.3167 | J5: 213 | K5: 9397.3206 | L5: 41450.137 | O5: More than 180 Days
B6: Computer 14 | C6: c | D6: 44882 | E6: 41445.763 | F6: 3 | G6: 2072.2881 | H6: 39373.475 | I6: 0.3167 | J6: 134 | K6: 4818.8137 | L6: 36626.949 | O6: less than 180 Days
B7: Computer 16 | C7: c | D7: 44947 | E7: 57203.39 | F7: 3 | G7: 2860.1695 | H7: 54343.22 | I7: 0.3167 | J7: 69 | K7: 3424.7278 | L7: 53778.662 | O7: less than 180 Days

Sheet Sheet1 (2)
F2: 27.09.23
F3: purchase
F5: 05.03.23 | G5: Rajasthan steel marwar | K5: 440729 | L5: =K5*18% -> 79331.22 | M5: =K5-L5 -> 361397.78
F6: 03.03.23 | G6: chennai steel company | K6: 533605 | L6: =K6*18% -> 96048.9 | M6: =K6-L6 -> 437556.1
F7: 22.02.23 | G7: rayban industries | K7: 121450 | L7: =K7*18% -> 21861 | M7: =K7-L7 -> 99589
F8: 24.01.23 | G8: sri sai trading | K8: 255991 | L8: =K8*18% -> 46078.38 | M8: =K8-L8 -> 209912.62
F9: 13.01.23 | G9: Rajasthan steel marwar | K9: 183029 | L9: =K9*18% -> 32945.22 | M9: =K9-L9 -> 150083.78
F10: 17.12.22 | G10: prasad combaines | K10: 337271 | L10: =K10*18% -> 60708.78 | M10: =K10-L10 -> 276562.22
F11: 21.10.22 | G11: prasad combaines | K11: 151400 | L11: =K11*18% -> 27252 | M11: =K11-L11 -> 124148
F12: 20.10.22 | G12: national tubes & alloys | K12: 564441 | L12: =K12*18% -> 101599.38 | M12: =K12-L12 -> 462841.62
F13: 07.09.23 | G13: steel link | K13: 513310 | L13: =K13*18% -> 92395.8 | M13: =K13-L13 -> 420914.2
F14: 09.07.22 | G14: steel link | K14: 728358 | L14: =K14*18% -> 131104.44 | M14: =K14-L14 -> 597253.56
F15: 25.07.22 | G15: steel link | K15: 669108 | L15: =K15*18% -> 120439.44 | M15: =K15-L15 -> 548668.56
F16: 01.04.22 | G16: jai sudharshan trading co | K16: 196545 | L16: =K16*18% -> 35378.1 | M16: =K16-L16 -> 161166.9
K17: =SUM(K5:K16) -> 4695237
F18: repairs & maintanance
F20: 15.04.22 | G20: chennai steel company | K20: 25618 | L20: =K20*18% -> 4611.24 | M20: =K20-L20 -> 21006.76
F21: 14.05.22 | G21: national tubes & alloyus | K21: 16822 | L21: =K21*18% -> 3027.96 | M21: =K21-L21 -> 13794.04
F22: 23.05.22 | G22: national tubes & alloyus | K22: 81697 | L22: =K22*18% -> 14705.46 | M22: =K22-L22 -> 66991.54
F23: 21.08.22 | G23: chennai steel company | K23: 48105 | L23: =K23*18% -> 8658.9 | M23: =K23-L23 -> 39446.1
F24: 26.09.22 | G24: shree ganesh steel corpn | K24: 115846 | L24: =K24*18% -> 20852.28 | M24: =K24-L24 -> 94993.72
F25: 31.12.22 | G25: national tubes & alloyus | K25: 30108 | L25: =K25*18% -> 5419.44 | M25: =K25-L25 -> 24688.56
F26: 31.12.22 | G26: national tubes & alloyus | K26: 8095 | L26: =K26*18% -> 1457.1 | M26: =K26-L26 -> 6637.9
F27: 05.01.23 | G27: national tubes & alloyus | K27: 71980 | L27: =K27*18% -> 12956.4 | M27: =K27-L27 -> 59023.6
F28: 19.01.23 | G28: national tubes & alloyus | K28: 54461 | L28: =K28*18% -> 9802.98 | M28: =K28-L28 -> 44658.02
F29: 20.01.23 | G29: national tubes & alloyus | K29: 68611 | L29: =K29*18% -> 12349.98 | M29: =K29-L29 -> 56261.02
F30: 17.02.23 | G30: sri lakshmi steels | K30: 34688 | L30: =K30*18% -> 6243.84 | M30: =K30-L30 -> 28444.16
F31: 25.02.23 | G31: national tubes & alloyus | K31: 65016 | L31: =K31*18% -> 11702.88 | M31: =K31-L31 -> 53313.12
... F37: 06.03.23 | G37: sakthi engineers | K37: 99993 | L37: =K37*18% -> 17998.74 | M37: =K37-L37 -> 81994.26
K38: =SUM(K20:K37) -> 1313768 | M38: =SUM(M5:M37) -> 4927384.1
I40: total | K40: =K17+K38 -> 6009005

Sheet Fixed Assets
A1: SATHIAPAL ENGINEERS (INDIA) PRIVATE LIMITED
A2: 57, 1ST Floor, Canal Road, Kilpauk Garden Colony
A3: Kilpauk,
A4: Chennai - 600 010
A5: CIN: U74210TN2002PLC048568
A6: Ledger Account
A9: 1-Apr-22 to 31-Mar-23
A10: Date | B10: Particulars | D10: Vch Type | F10: Vch No. | G10: AMOUNT CAPITALISED | H10: IGST | I10: CGST | J10: SGST | K10: CESS | M10: AMOUNT TO BE CAPITALISED | N10: Difference | O10: Ledger Name | S10: 2932808
A11: Educational | B11: To | C11: Aurobindo Business Machines | D11: Purchase | F11: 6 | G11: 51580 | H11: 0 | I11: =G11/118*9 -> 3934.0678 | J11: =G11/118*9 -> 3934.0678 | M11: =G11-H11-I11-J11 -> 43711.864 | N11: =G11-M11 -> 7868.1356 | O11: COMPUTER | U11: =VLOOKUP(M11,'FA Register Final'!$F$3:$F$150,1,0) -> 43711.864
A12: 44652 | B12: To | C12: Aurobindo Business Machines | D12: Purchase | F12: 7 | G12: 29500 | H12: 0 | I12: =G12/118*9 -> 2250 | J12: =G12/118*9 -> 2250 | M12: =G12-H12-I12-J12 -> 25000 | N12: =G12-M12 -> 4500 | O12: COMPUTER | U12: =VLOOKUP(M12,'FA Register Final'!$F$3:$F$150,1,0) -> 25000
A13: Educational | B13: To | C13: Amman Motor Pipes | D13: Purchase | F13: 23 | G13: 3300 | H13: 0 | I13: =G13/118*9 -> 251.69492 | J13: =G13/118*9 -> 251.69492 | M13: =G13-H13-I13-J13 -> 2796.6102 | N13: =G13-M13 -> 503.38983 | O13: PLANT & MACHINERY | U13: =VLOOKUP(M13,'FA Register Final'!$F$3:$F$150,1,0) -> 2796.6102
A14: Educational | B14: To | C14: Amman Motor Pipes | D14: Purchase | F14: 24 | G14: 61600 | H14: 0 | I14: =G14/112*6 -> 3300 | J14: =G14/112*6 -> 3300 | M14: =G14-H14-I14-J14 -> 55000 | N14: =G14-M14 -> 6600 | O14: PLANT & MACHINERY | U14: =VLOOKUP(M14,'FA Register Final'!$F$3:$F$150,1,0) -> 55000
A15: Educational | B15: To | C15: Sona Ispat India Pvt Ltd | D15: Purchase | F15: 25 | G15: 455313 | H15: =G15/118*18 -> 69454.525 | I15: 0 | J15: 0 | M15: =G15-H15-I15-J15 -> 385858.47 | N15: =G15-M15 -> 69454.525 | O15: PLANT & MACHINERY | U15: =VLOOKUP(M15,'FA Register Final'!$F$3:$F$150,1,0) -> 385858.47
A16: Educational | B16: To | C16: Sona Ispat India Pvt Ltd | D16: Purchase | F16: 26 | G16: 2187697 | H16: =G16/118*18 -> 333716.49 | I16: 0 | J16: 0 | M16: =G16-H16-I16-J16 -> 1853980.5 | N16: =G16-M16 -> 333716.49 | O16: PLANT & MACHINERY | U16: =VLOOKUP(M16,'FA Register Final'!$F$3:$F$150,1,0) -> 1853980.5
A17: Educational | B17: To | C17: Ramluck Traders | D17: Purchase | F17: 27 | G17: 47790 | H17: 0 | I17: =G17/118*9 -> 3645 | J17: =G17/118*9 -> 3645 | M17: =G17-H17-I17-J17 -> 40500 | N17: =G17-M17 -> 7290 | O17: PLANT & MACHINERY | U17: =VLOOKUP(M17,'FA Register Final'!$F$3:$F$150,1,0) -> 40500
A18: Educational | B18: To | C18: Ramluck Traders | D18: Purchase | F18: 28 | G18: 79650 | H18: 0 | I18: =G18/118*9 -> 6075 | J18: =G18/118*9 -> 6075 | M18: =G18-H18-I18-J18 -> 67500 | N18: =G18-M18 -> 12150 | O18: PLANT & MACHINERY | U18: =VLOOKUP(M18,'FA Register Final'!$F$3:$F$150,1,0) -> 67500
A19: Educational | B19: To | C19: Chennai Steeel Company | D19: Purchase | F19: 30 | G19: 203987 | H19: 0 | I19: =G19/118*9 -> 15558.331 | J19: =G19/118*9 -> 15558.331 | M19: =G19-H19-I19-J19 -> 172870.34 | N19: =G19-M19 -> 31116.661 | O19: PLANT & MACHINERY | U19: =VLOOKUP(M19,'FA Register Final'!$F$3:$F$150,1,0) -> 172870.34
A20: Educational | B20: To | C20: T.R.Fastners | D20: Purchase | F20: 31 | G20: 435538 | H20: =G20/118*18 -> 66438 | I20: 0 | J20: 0 | M20: =G20-H20-I20-J20 -> 369100 | N20: =G20-M20 -> 66438 | O20: PLANT & MACHINERY | U20: =VLOOKUP(M20,'FA Register Final'!$F$3:$F$150,1,0) -> 369100
A21: Educational | B21: To | C21: Rahul Industries | D21: Purchase | F21: 33 | G21: 1433989 | H21: =G21/118*18 -> 218744.08 | I21: 0 | J21: 0 | M21: =G21-H21-I21-J21 -> 1215244.9 | N21: =G21-M21 -> 218744.08 | O21: PLANT & MACHINERY | U21: =VLOOKUP(M21,'FA Register Final'!$F$3:$F$150,1,0) -> 1215244.9
A22: Educational | B22: To | C22: Container Industriel | D22: Purchase | F22: 39 | G22: 253700 | H22: 0 | I22: =G22/118*9 -> 19350 | J22: =G22/118*9 -> 19350 | M22: =G22-H22-I22-J22 -> 215000 | N22: =G22-M22 -> 38700 | O22: PLANT & MACHINERY | U22: =VLOOKUP(M22,'FA Register Final'!$F$3:$F$150,1,0) -> 215000
A23: Educational | B23: To | C23: Chennai Steeel Company | D23: Purchase | F23: 50 | G23: 208215 | H23: 0 | I23: =G23/118*9 -> 15880.805 | J23: =G23/118*9 -> 15880.805 | M23: =G23-H23-I23-J23 -> 176453.39 | N23: =G23-M23 -> 31761.61 | O23: PLANT & MACHINERY | U23: =VLOOKUP(M23,'FA Register Final'!$F$3:$F$150,1,0) -> 176453.39
A24: Educational | B24: To | C24: Potout Solutions | D24: Purchase | F24: 64 | G24: 19116 | H24: 0 | I24: =G24/118*9 -> 1458 | J24: =G24/118*9 -> 1458 | M24: =G24-H24-I24-J24 -> 16200 | N24: =G24-M24 -> 2916 | O24: COMPUTER | U24: =VLOOKUP(M24,'FA Register Final'!$F$3:$F$150,1,0) -> #N/A
A25: Educational | B25: To | C25: FLUID POWER ENGINEERING | D25: Purchase | F25: 70 | G25: 213934 | H25: 0 | I25: =G25/118*9 -> 16317 | J25: =G25/118*9 -> 16317 | M25: =G25-H25-I25-J25 -> 181300 | N25: =G25-M25 -> 32634 | O25: PLANT & MACHINERY | U25: =VLOOKUP(M25,'FA Register Final'!$F$3:$F$150,1,0) -> 181300
A26: Educational | B26: To | C26: Metal Portable Cabins | D26: Purchase | F26: 74 | G26: 192340 | H26: =G26/118*18 -> 29340 | I26: 0 | J26: 0 | M26: =G26-H26-I26-J26 -> 163000 | N26: =G26-M26 -> 29340 | O26: PLANT & MACHINERY | U26: =VLOOKUP(M26,'FA Register Final'!$F$3:$F$150,1,0) -> 163000
A27: Educational | B27: To | C27: PMG Containers (P) Ltd | D27: Purchase | F27: 78 | G27: 194700 | H27: =G27/118*18 -> 29700 | I27: 0 | J27: 0 | M27: =G27-H27-I27-J27 -> 165000 | N27: =G27-M27 -> 29700 | O27: PLANT & MACHINERY | U27: =VLOOKUP(M27,'FA Register Final'!$F$3:$F$150,1,0) -> 165000
A28: Educational | B28: To | C28: Koppu Sadasivamurthy Sons | D28: Purchase | F28: 79 | G28: 684667 | H28: =G28/118*18 -> 104440.73 | I28: 0 | J28: 0 | M28: =G28-H28-I28-J28 -> 580226.27 | N28: =G28-M28 -> 104440.73 | O28: PLANT & MACHINERY | U28: =VLOOKUP(M28,'FA Register Final'!$F$3:$F$150,1,0) -> 580226.27
A29: Educational | B29: To | C29: Aurobindo Business Machines | D29: Purchase | F29: 145 | G29: 34253 | H29: 0 | I29: =G29/118*9 -> 2612.5169 | J29: =G29/118*9 -> 2612.5169 | M29: =G29-H29-I29-J29 -> 29027.966 | N29: =G29-M29 -> 5225.0339 | O29: COMPUTER | U29: =VLOOKUP(M29,'FA Register Final'!$F$3:$F$150,1,0) -> 29027.966
A30: Educational | B30: To | C30: Chennai Steeel Company | D30: Purchase | F30: 183 | G30: 291202 | H30: 0 | I30: =G30/118*9 -> 22210.322 | J30: =G30/118*9 -> 22210.322 | M30: =G30-H30-I30-J30 -> 246781.36 | N30: =G30-M30 -> 44420.644 | O30: PLANT & MACHINERY | U30: =VLOOKUP(M30,'FA Register Final'!$F$3:$F$150,1,0) -> 246781.36
A31: Educational | B31: To | C31: Chennai Steeel Company | D31: Purchase | F31: 184 | G31: 310552 | H31: 0 | I31: =G31/118*9 -> 23686.169 | J31: =G31/118*9 -> 23686.169 | M31: =G31-H31-I31-J31 -> 263179.66 | N31: =G31-M31 -> 47372.339 | O31: PLANT & MACHINERY | U31: =VLOOKUP(M31,'FA Register Final'!$F$3:$F$150,1,0) -> 263179.66
A32: Educational | B32: To | C32: Jothi Welding Works (Kalaiyarasan) | D32: Purchase | F32: 185 | G32: 54912 | H32: 0 | I32: 0 | J32: 0 | M32: =G32-H32-I32-J32 -> 54912 | N32: =G32-M32 -> 0 | O32: PLANT & MACHINERY | U32: =VLOOKUP(M32,'FA Register Final'!$F$3:$F$150,1,0) -> 54912
A33: Educational | B33: To | C33: Jothi Welding Works (Kalaiyarasan) | D33: Purchase | F33: 186 | G33: 69550 | H33: 0 | I33: 0 | J33: 0 | M33: =G33-H33-I33-J33 -> 69550 | N33: =G33-M33 -> 0 | O33: PLANT & MACHINERY | U33: =VLOOKUP(M33,'FA Register Final'!$F$3:$F$150,1,0) -> 69550
A34: Educational | B34: To | C34: Sri Amman Lath Works | D34: Purchase | F34: 187 | G34: 24800 | H34: 0 | I34: 0 | J34: 0 | M34: =G34-H34-I34-J34 -> 24800 | N34: =G34-M34 -> 0 | O34: PLANT & MACHINERY | U34: =VLOOKUP(M34,'FA Register Final'!$F$3:$F$150,1,0) -> 24800
A35: Educational | B35: To | C35: Sri Amman Lath Works | D35: Purchase | F35: 188 | G35: 3280 | H35: 0 | I35: 0 | J35: 0 | M35: =G35-H35-I35-J35 -> 3280 | N35: =G35-M35 -> 0 | O35: PLANT & MACHINERY | U35: =VLOOKUP(M35,'FA Register Final'!$F$3:$F$150,1,0) -> 3280
A36: Educational | B36: To | C36: Sri Amman Lath Works | D36: Purchase | F36: 189 | G36: 113300 | H36: 0 | I36: 0 | J36: 0 | M36: =G36-H36-I36-J36 -> 113300 | N36: =G36-M36 -> 0 | O36: PLANT & MACHINERY | U36: =VLOOKUP(M36,'FA Register Final'!$F$3:$F$150,1,0) -> 113300
A37: Educational | B37: To | C37: Sri Amman Lath Works | D37: Purchase | F37: 190 | G37: 113300 | H37: 0 | I37: 0 | J37: 0 | M37: =G37-H37-I37-J37 -> 113300 | N37: =G37-M37 -> 0 | O37: PLANT & MACHINERY | U37: =VLOOKUP(M37,'FA Register Final'!$F$3:$F$150,1,0) -> 113300
A38: Educational | B38: To | C38: Kaling Hardwares & Construction | D38: Purchase | F38: 203 | G38: 283354 | H38: 0 | I38: =G38/118*9 -> 21611.746 | J38: =G38/118*9 -> 21611.746 | M38: =G38-H38-I38-J38 -> 240130.51 | N38: =G38-M38 -> 43223.492 | O38: PLANT & MACHINERY | U38: =VLOOKUP(M38,'FA Register Final'!$F$3:$F$150,1,0) -> 240130.51
A39: Educational | B39: To | C39: Hogg Hydraulics | D39: Purchase | F39: 242 | G39: 119558 | H39: 0 | I39: =G39/118*9 -> 9118.8305 | J39: =G39/118*9 -> 9118.8305 | M39: =G39-H39-I39-J39 -> 101320.34 | N39: =G39-M39 -> 18237.661 | O39: PLANT & MACHINERY | U39: =VLOOKUP(M39,'FA Register Final'!$F$3:$F$150,1,0) -> 101320.34
A40: Educational | B40: To | C40: JK Industries | D40: Purchase | F40: 245 | G40: 247800 | H40: =G40/118*18 -> 37800 | I40: 0 | J40: 0 | M40: =G40-H40-I40-J40 -> 210000 | N40: =G40-M40 -> 37800 | O40: PLANT & MACHINERY | U40: =VLOOKUP(M40,'FA Register Final'!$F$3:$F$150,1,0) -> 210000
A41: Educational | B41: To | C41: Chennai Steeel Company | D41: Purchase | F41: 246 | G41: 256131 | H41: 0 | I41: =G41/118*9 -> 19535.415 | J41: =G41/118*9 -> 19535.415 | M41: =G41-H41-I41-J41 -> 217060.17 | N41: =G41-M41 -> 39070.831 | O41: PLANT & MACHINERY | U41: =VLOOKUP(M41,'FA Register Final'!$F$3:$F$150,1,0) -> 217060.17
A42: Educational | B42: To | C42: Chennai Steeel Company | D42: Purchase | F42: 247 | G42: 277287 | H42: 0 | I42: =G42/118*9 -> 21149.008 | J42: =G42/118*9 -> 21149.008 | M42: =G42-H42-I42-J42 -> 234988.98 | N42: =G42-M42 -> 42298.017 | O42: PLANT & MACHINERY | U42: =VLOOKUP(M42,'FA Register Final'!$F$3:$F$150,1,0) -> 234988.98
A43: Educational | B43: To | C43: JANNU ENGG.WORKS | D43: Purchase | F43: 248 | G43: 14250 | H43: 0 | I43: 0 | J43: 0 | M43: =G43-H43-I43-J43 -> 14250 | N43: =G43-M43 -> 0 | O43: PLANT & MACHINERY | U43: =VLOOKUP(M43,'FA Register Final'!$F$3:$F$150,1,0) -> 14250
A44: Educational | B44: To | C44: Sri Amman Lath Works | D44: Purchase | F44: 268 | G44: 22330 | H44: 0 | I44: 0 | J44: 0 | M44: =G44-H44-I44-J44 -> 22330 | N44: =G44-M44 -> 0 | O44: PLANT & MACHINERY | U44: =VLOOKUP(M44,'FA Register Final'!$F$3:$F$150,1,0) -> 22330
A45: Educational | B45: To | C45: Rahul Industries | D45: Purchase | F45: 325 | G45: 97350 | H45: =G45/118*18 -> 14850 | I45: 0 | J45: 0 | M45: =G45-H45-I45-J45 -> 82500 | N45: =G45-M45 -> 14850 | O45: PLANT & MACHINERY | U45: =VLOOKUP(M45,'FA Register Final'!$F$3:$F$150,1,0) -> 82500
A46: Educational | B46: To | C46: Sri Amman Lath Works | D46: Purchase | F46: 326 | G46: 52440 | H46: 0 | I46: 0 | J46: 0 | M46: =G46-H46-I46-J46 -> 52440 | N46: =G46-M46 -> 0 | O46: PLANT & MACHINERY | U46: =VLOOKUP(M46,'FA Register Final'!$F$3:$F$150,1,0) -> 52440
A47: Educational | B47: To | C47: Sri Amman Lath Works | D47: Purchase | F47: 327 | G47: 16800 | H47: 0 | I47: 0 | J47: 0 | M47: =G47-H47-I47-J47 -> 16800 | N47: =G47-M47 -> 0 | O47: PLANT & MACHINERY | U47: =VLOOKUP(M47,'FA Register Final'!$F$3:$F$150,1,0) -> 16800
A48: Educational | B48: To | C48: Sri Amman Lath Works | D48: Purchase | F48: 328 | G48: 118450 | H48: 0 | I48: 0 | J48: 0 | M48: =G48-H48-I48-J48 -> 118450 | N48: =G48-M48 -> 0 | O48: PLANT & MACHINERY | U48: =VLOOKUP(M48,'FA Register Final'!$F$3:$F$150,1,0) -> 118450
A49: Educational | B49: To | C49: Steel Link | D49: Purchase | F49: 335 | G49: 1270754 | H49: 0 | I49: =G49/118*9 -> 96921.915 | J49: =G49/118*9 -> 96921.915 | M49: =G49-H49-I49-J49 -> 1076910.2 | N49: =G49-M49 -> 193843.83 | O49: PLANT & MACHINERY | U49: =VLOOKUP(M49,'FA Register Final'!$F$3:$F$150,1,0) -> 1076910.2
A50: Educational | B50: To | C50: Steel Link | D50: Purchase | F50: 336 | G50: 1031472 | H50: 0 | I50: =G50/118*9 -> 78671.593 | J50: =G50/118*9 -> 78671.593 | M50: =G50-H50-I50-J50 -> 874128.81 | N50: =G50-M50 -> 157343.19 | O50: PLANT & MACHINERY | U50: =VLOOKUP(M50,'FA Register Final'!$F$3:$F$150,1,0) -> 874128.81
